[{"id":8675,"n":"戴永东","d":"医学院","r":0.0,"rc":0,"h":100,"g":[],"m":[]},{"id":8676,"n":"陈志刚","d":"医学院","r":0.0,"rc":0,"h":1021,"g":[],"m":[]},{"id":8677,"n":"陈学鹏","d":"医学院","r":0.0,"rc":0,"h":80,"g":[["口腔正畸学",3.97,122,0.58]],"m":[]},{"id":8678,"n":"浦佳丽","d":"医学院","r":0.0,"rc":0,"h":380,"g":[["诊断学Ⅰ",3.94,250,0.75]],"m":[]},{"id":8679,"n":"傅秋黎","d":"医学院","r":0.0,"rc":0,"h":40,"g":[],"m":[]},{"id":8680,"n":"谢海洋","d":"医学院","r":0.0,"rc":0,"h":120,"g":[],"m":[]},{"id":8681,"n":"肖乾","d":"医学院","r":0.0,"rc":0,"h":60,"g":[],"m":[]},{"id":8682,"n":"夏伟良","d":"医学院","r":0.0,"rc":0,"h":40,"g":[],"m":[]},{"id":8683,"n":"吴佳莹","d":"医学院","r":0.0,"rc":0,"h":40,"g":[],"m":[]},{"id":8684,"n":"陈艳杏","d":"医学院","r":0.0,"rc":0,"h":60,"g":[["Internal Medicine Ⅰ",3.08,59,0.64],["医学英语",3.36,85,1.02]],"m":[]},{"id":8685,"n":"张匀","d":"医学院","r":0.0,"rc":0,"h":60,"g":[],"m":[]},{"id":8686,"n":"张嵘","d":"医学院","r":0.0,"rc":0,"h":60,"g":[["诊断学Ⅱ",3.72,0,0.87]],"m":[]},{"id":8687,"n":"蔡加昌","d":"医学院","r":0.0,"rc":0,"h":120,"g":[],"m":[]},{"id":8688,"n":"施毓","d":"医学院","r":0.0,"rc":0,"h":100,"g":[["传染病学",3.46,0,0.71]],"m":[]},{"id":8689,"n":"胡永仙","d":"医学院","r":0.0,"rc":0,"h":460,"g":[["内科学（乙）",4.18,54,0.82]],"m":[]},{"id":8690,"n":"方鹏飞","d":"建筑工程学院","r":0.0,"rc":0,"h":40,"g":[],"m":[]},{"id":8691,"n":"严锋","d":"医学院","r":0.0,"rc":0,"h":400,"g":[["外科学总论(乙)",3.67,133,0.65],["外科学总论（甲）",3.7,255,0.67]],"m":[]},{"id":8692,"n":"邵乐文","d":"医学院","r":0.0,"rc":0,"h":60,"g":[],"m":[]},{"id":8693,"n":"赵鹏","d":"医学院","r":0.0,"rc":1,"h":380,"g":[],"m":[{"t":"2022-03-07 05:34","p":1,"u":1,"d":0,"c":"你赵鹏什么的都在踢中卫，他能踢吗？"}]},{"id":8694,"n":"程宝莉","d":"医学院","r":0.0,"rc":0,"h":60,"g":[["颌面部疼痛学",4.34,116,0.36]],"m":[]},{"id":8695,"n":"陈毅力","d":"医学院","r":0.0,"rc":0,"h":60,"g":[],"m":[]},{"id":8696,"n":"荆娴","d":"经济学院","r":0.0,"rc":0,"h":80,"g":[],"m":[]},{"id":8697,"n":"傅琦涵","d":"医学院","r":0.0,"rc":1,"h":80,"g":[],"m":[]},{"id":8698,"n":"胡建华","d":"医学院","r":0.0,"rc":0,"h":140,"g":[],"m":[]},{"id":8699,"n":"杨介钻","d":"医学院","r":0.0,"rc":0,"h":40,"g":[],"m":[]},{"id":8700,"n":"虞洪","d":"医学院","r":0.0,"rc":2,"h":100,"g":[["外科学（甲）Ⅰ",3.11,201,0.9]],"m":[{"t":"2022-10-23 14:45","p":0,"u":0,"d":0,"c":"nnnbbb"},{"t":"2022-12-30 03:22","p":0,"u":0,"d":0,"c":"大牛nb"}]},{"id":8701,"n":"万婷","d":"医学院","r":0.0,"rc":0,"h":40,"g":[],"m":[]},{"id":8702,"n":"张丽","d":"医学院","r":0.0,"rc":0,"h":380,"g":[["实用眼科学",3.45,56,0.84]],"m":[]},{"id":8703,"n":"王勇杰","d":"医学院","r":0.0,"rc":0,"h":1681,"g":[],"m":[]},{"id":8704,"n":"陶青青","d":"医学院","r":0.0,"rc":0,"h":40,"g":[["神经病学",3.17,68,0.56]],"m":[]},{"id":8705,"n":"晁冠群","d":"医学院","r":0.0,"rc":0,"h":40,"g":[["Community Medicine",4.1,72,0.56]],"m":[]},{"id":8706,"n":"魏群","d":"医学院","r":0.0,"rc":0,"h":120,"g":[],"m":[]},{"id":8707,"n":"吴子衡","d":"医学院","r":0.0,"rc":0,"h":60,"g":[],"m":[]},{"id":8708,"n":"赵妍敏","d":"医学院","r":0.0,"rc":0,"h":60,"g":[["Internal Medicine Ⅲ",3.26,74,0.71],["内科学（甲）Ⅱ",3.56,89,0.62]],"m":[]},{"id":8709,"n":"闫伟","d":"医学院","r":0.0,"rc":0,"h":40,"g":[],"m":[]},{"id":8710,"n":"许璟","d":"医学院","r":0.0,"rc":0,"h":40,"g":[],"m":[]},{"id":8711,"n":"朱亚楠","d":"医学院","r":0.0,"rc":0,"h":40,"g":[["实用眼科学",3.45,56,0.84]],"m":[]},{"id":8712,"n":"林海福","d":"计算机科学与技术学院","r":0.0,"rc":0,"h":80,"g":[],"m":[]},{"id":8713,"n":"吴浩波","d":"医学院","r":0.0,"rc":0,"h":80,"g":[],"m":[]},{"id":8714,"n":"温珍珍","d":"医学院","r":0.0,"rc":0,"h":860,"g":[["内科学（甲）Ⅰ",2.84,106,0.87],["诊断学Ⅰ",3.97,0,0.77]],"m":[]},{"id":8715,"n":"王新刚","d":"医学院","r":0.0,"rc":0,"h":460,"g":[["外科学总论(乙)",3.46,465,0.72]],"m":[]},{"id":8716,"n":"陈卓","d":"医学院","r":0.0,"rc":0,"h":400,"g":[["牙体牙髓病学",3.69,194,0.69]],"m":[]},{"id":8717,"n":"金希","d":"医学院","r":0.0,"rc":0,"h":80,"g":[["Internal Medicine Ⅲ",3.5,72,0.74]],"m":[]},{"id":8718,"n":"谭亚敏","d":"医学院","r":0.0,"rc":0,"h":40,"g":[],"m":[]},{"id":8719,"n":"闾夏轶","d":"医学院","r":0.0,"rc":0,"h":140,"g":[],"m":[]},{"id":8720,"n":"毛江鸿","d":"建筑工程学院","r":0.0,"rc":0,"h":40,"g":[],"m":[]},{"id":8721,"n":"Mondher Bouzayen","d":"农业与生物技术学院","r":0.0,"rc":0,"h":40,"g":[],"m":[]},{"id":8722,"n":"刘志红","d":"医学院","r":0.0,"rc":0,"h":520,"g":[],"m":[]},{"id":8723,"n":"陆邵佳","d":"医学院","r":0.0,"rc":0,"h":40,"g":[["精神病学",3.56,360,0.63],["精神病学（乙）",3.66,157,0.75]],"m":[]},{"id":8724,"n":"Susan Welburn","d":"基础医学系","r":0.0,"rc":0,"h":60,"g":[],"m":[]},{"id":8725,"n":"侯金超","d":"医学院","r":0.0,"rc":0,"h":60,"g":[],"m":[]},{"id":8726,"n":"陈志军","d":"医学院","r":0.0,"rc":0,"h":60,"g":[],"m":[]},{"id":8727,"n":"严森祥","d":"医学院","r":0.0,"rc":0,"h":80,"g":[],"m":[]},{"id":8728,"n":"文世挺","d":"计算机科学与技术学院","r":0.0,"rc":2,"h":200,"g":[],"m":[]},{"id":8729,"n":"陈雅飞","d":"艺术与考古学院","r":0.0,"rc":0,"h":40,"g":[],"m":[]},{"id":8730,"n":"王仁忠","d":"传媒与国际文化学院","r":0.0,"rc":0,"h":40,"g":[],"m":[]},{"id":8731,"n":"黄旦","d":"传媒与国际文化学院","r":0.0,"rc":3,"h":3604,"g":[["新闻传播经典原著选读",4.33,172,0.45]],"m":[{"t":"2021-08-22 16:26","p":-2,"u":2,"d":4,"c":"能跑则跑"},{"t":"2021-08-22 16:27","p":-2,"u":3,"d":5,"c":"挺有思想，就是对学生太刻薄了"},{"t":"2024-06-20 10:42","p":-2,"u":2,"d":4,"c":"服了你这个文科资深。。。"}]},{"id":8732,"n":"王珅","d":"艺术与考古学院","r":0.0,"rc":0,"h":40,"g":[],"m":[]},{"id":8733,"n":"李金柱","d":"建筑工程学院","r":0.0,"rc":0,"h":40,"g":[],"m":[]},{"id":8734,"n":"Kang Mingu","d":"管理学院","r":0.0,"rc":0,"h":1740,"g":[],"m":[]}]