[{"id":6947,"姓名":"欧新文","学院":"物理学系","热度":40,"评分人数":0,"评分":0.0,"拼音":"ouxinwen","拼音缩写":"oxw","comments":[],"gpa_info":[]},{"id":6948,"姓名":"陈涵","学院":"医学院","热度":40,"评分人数":0,"评分":0.0,"拼音":"chenhan","拼音缩写":"ch","comments":[],"gpa_info":[["医学英语",3.36,85,1.02]]},{"id":6949,"姓名":"陈新忠","学院":"医学院","热度":40,"评分人数":0,"评分":0.0,"拼音":"chenxinzhong","拼音缩写":"cxz","comments":[],"gpa_info":[]},{"id":6950,"姓名":"王楠","学院":"海洋学院","热度":1401,"评分人数":0,"评分":0.0,"拼音":"wangnan","拼音缩写":"wn","comments":[],"gpa_info":[["分子生物学",3.88,88,0.91]]},{"id":6951,"姓名":"徐晨燃","学院":"物理学系","热度":60,"评分人数":0,"评分":0.0,"拼音":"xuchenran","拼音缩写":"xcr","comments":[],"gpa_info":[]},{"id":6952,"姓名":"蔡庚午","学院":"化学工程与生物工程学院","热度":60,"评分人数":0,"评分":0.0,"拼音":"caigengwu","拼音缩写":"cgw","comments":[],"gpa_info":[]},{"id":6953,"姓名":"郭霞","学院":"药学院","热度":40,"评分人数":0,"评分":0.0,"拼音":"guoxia","拼音缩写":"gx","comments":[],"gpa_info":[]},{"id":6954,"姓名":"孙继红","学院":"医学院","热度":60,"评分人数":0,"评分":0.0,"拼音":"sunjihong","拼音缩写":"sjh","comments":[],"gpa_info":[["医学影像学",2.87,65,0.77]]},{"id":6955,"姓名":"南山","学院":"生物医学工程与仪器科学学院","热度":40,"评分人数":0,"评分":0.0,"拼音":"nanshan","拼音缩写":"ns","comments":[],"gpa_info":[]},{"id":6956,"姓名":"杜思超","学院":"信息与电子工程学院","热度":40,"评分人数":0,"评分":0.0,"拼音":"dusichao","拼音缩写":"dsc","comments":[],"gpa_info":[]},{"id":6957,"姓名":"何秉卓","学院":"经济学院","热度":40,"评分人数":0,"评分":0.0,"拼音":"hebingzhuo","拼音缩写":"hbz","comments":[],"gpa_info":[]},{"id":6958,"姓名":"孔宪旺","学院":"生物系统工程与食品科学学院","热度":40,"评分人数":0,"评分":0.0,"拼音":"kongxianwang","拼音缩写":"kxw","comments":[],"gpa_info":[]},{"id":6959,"姓名":"纪伟昌","学院":"环境与资源学院","热度":40,"评分人数":0,"评分":0.0,"拼音":"jiweichang","拼音缩写":"jwc","comments":[],"gpa_info":[]},{"id":6960,"姓名":"邵丹蕾","学院":"地球科学学院","热度":140,"评分人数":0,"评分":0.0,"拼音":"shaodanlei","拼音缩写":"sdl","comments":[],"gpa_info":[]},{"id":6961,"姓名":"崔琴琴","学院":"医学院","热度":40,"评分人数":0,"评分":0.0,"拼音":"cuiqinqin","拼音缩写":"cqq","comments":[],"gpa_info":[]},{"id":6962,"姓名":"张琪","学院":"化学系","热度":80,"评分人数":0,"评分":0.0,"拼音":"zhangqi","拼音缩写":"zq","comments":[],"gpa_info":[]},{"id":6963,"姓名":"柴立红","学院":"农业与生物技术学院","热度":60,"评分人数":0,"评分":0.0,"拼音":"chailihong","拼音缩写":"clh","comments":[],"gpa_info":[]},{"id":6964,"姓名":"宋虓","学院":"生命科学学院","热度":40,"评分人数":0,"评分":0.0,"拼音":"songxiao","拼音缩写":"sx","comments":[],"gpa_info":[]},{"id":6965,"姓名":"潘海波","学院":"生物系统工程与食品科学学院","热度":40,"评分人数":0,"评分":0.0,"拼音":"panhaibo","拼音缩写":"phb","comments":[],"gpa_info":[]},{"id":6966,"姓名":"侯杰","学院":"环境与资源学院","热度":360,"评分人数":0,"评分":0.0,"拼音":"houjie","拼音缩写":"hj","comments":[],"gpa_info":[]},{"id":6967,"姓名":"林星","学院":"化学系","热度":6585,"评分人数":10,"评分":8.99145,"拼音":"linxing","拼音缩写":"lx","comments":[{"发表时间":"2022-03-13 11:07:06","点赞减去点踩数量":-10,"点赞量":3,"点踩量":13,"内容":"拉鸡老师"},{"发表时间":"2022-11-09 08:09:30","点赞减去点踩数量":3,"点赞量":3,"点踩量":0,"内容":"很好的老师，特别和善，回消息特别快，还很负责。重点是很帅！！！！！！！！"},{"发表时间":"2024-07-01 11:10:49","点赞减去点踩数量":3,"点赞量":3,"点踩量":0,"内容":"林老师，我的超人"},{"发表时间":"2024-07-06 05:24:40","点赞减去点踩数量":0,"点赞量":0,"点踩量":0,"内容":"这学期最喜欢的课应该就是林星老师的量子信息基础，虽然课程内容有很多数学物理相关，也需要一些基础的线性代数知识进行计算，但总体来说还是很棒的。老师上课也很努力很清晰，希望把知识传授给学生，而且对学生提出的问题总是及时认真回复，是一个非常好的老师！\\n\\n每一节课都认真跟下来的话感觉作业考试什么的难度不会很大，毕竟考试前老师会把作业答案都发出来，期中开卷，期末闭卷，只要面向作业题复习就不会有什么问题，给分也很好。\\n\\n通过这门课真的感受到了量子力学的魅力，例如塌缩、简谐振子模型与粒子数算符、延迟选择等等。个人感觉最后一章量子测量的关联光学和量子成像有点云里雾里，其它都比较清楚。\\n\\n非常推荐林星老师的课！"}],"gpa_info":[["量子信息基础",4.2,58,1.02]]},{"id":6968,"姓名":"吴海波","学院":"医学院","热度":1360,"评分人数":0,"评分":0.0,"拼音":"wuhaibo","拼音缩写":"whb","comments":[],"gpa_info":[]},{"id":6969,"姓名":"滕洪芬","学院":"环境与资源学院","热度":200,"评分人数":0,"评分":0.0,"拼音":"tenghongfen","拼音缩写":"thf","comments":[],"gpa_info":[]},{"id":6970,"姓名":"毛善俊","学院":"化学系","热度":740,"评分人数":2,"评分":0.0,"拼音":"maoshanjun","拼音缩写":"msj","comments":[{"发表时间":"2025-01-09 05:28:49","点赞减去点踩数量":0,"点赞量":0,"点踩量":0,"内容":"比王勇强多了"}],"gpa_info":[["普通化学（甲）",3.8,73,0.67]]},{"id":6971,"姓名":"冯依力","学院":"医学院","热度":40,"评分人数":0,"评分":0.0,"拼音":"fengyili","拼音缩写":"fyl","comments":[],"gpa_info":[]},{"id":6972,"姓名":"郑俊华","学院":"控制科学与工程学院","热度":140,"评分人数":0,"评分":0.0,"拼音":"zhengjunhua","拼音缩写":"zjh","comments":[],"gpa_info":[]},{"id":6973,"姓名":"代晓阳","学院":"药学院","热度":40,"评分人数":0,"评分":0.0,"拼音":"daixiaoyang","拼音缩写":"dxy","comments":[],"gpa_info":[]},{"id":6974,"姓名":"吴昂键","学院":"能源工程学院","热度":2463,"评分人数":1,"评分":0.0,"拼音":"wuangjian","拼音缩写":"waj","comments":[{"发表时间":"2021-12-21 05:58:14","点赞减去点踩数量":0,"点赞量":6,"点踩量":6,"内容":"讲课不错 很负责"}],"gpa_info":[["新能源实验",4.83,7,0.08],["能源与环境实验Ⅰ",4.88,8,0.1],["认识实习",4.0,69,0.69]]},{"id":6975,"姓名":"张秀娟","学院":"海洋学院","热度":40,"评分人数":0,"评分":0.0,"拼音":"zhangxiujuan","拼音缩写":"zxj","comments":[],"gpa_info":[]},{"id":6976,"姓名":"纪盈如","学院":"传媒与国际文化学院","热度":12512,"评分人数":46,"评分":7.96005,"拼音":"jiyingru","拼音缩写":"jyr","comments":[{"发表时间":"2020-06-03 02:13:57","点赞减去点踩数量":1,"点赞量":4,"点踩量":3,"内容":"老师人很好，先给10分！"},{"发表时间":"2020-07-02 04:43:51","点赞减去点踩数量":4,"点赞量":13,"点踩量":9,"内容":"来浙大多年来第一个100分（满分105，你就品品纪老师有多善良），老师人美声甜，上课有时候会对一些热点话题进行讨论，很喜欢这个环节。作业的话对于一门三学分的专业课来说我认为不算多，小组作业大家一起做也学到了很多，期末觉得自己很有收获（最起码以后做策划可以做的更科学了！）这是纪老师来浙大上的第一门课，老师专业能力强，性格又好，果断10分啊！！"},{"发表时间":"2021-01-15 23:58:53","点赞减去点踩数量":3,"点赞量":7,"点踩量":4,"内容":"期末考试前背到晕厥的时候，看看上一轮期末开卷考同学的评价，真的恍如隔世。"},{"发表时间":"2021-01-21 12:30:26","点赞减去点踩数量":2,"点赞量":2,"点踩量":0,"内容":"大爱老师!!! 讲课很棒，给分更棒!!!"},{"发表时间":"2023-05-14 08:25:44","点赞减去点踩数量":-1,"点赞量":1,"点踩量":2,"内容":"高级广告传播课换成这个老师主讲，每次课都拖堂。"},{"发表时间":"2023-06-30 05:06:15","点赞减去点踩数量":-5,"点赞量":2,"点踩量":7,"内容":"事儿贼多，结果给分不好，呵呵"},{"发表时间":"2023-06-30 16:50:36","点赞减去点踩数量":1,"点赞量":1,"点踩量":0,"内容":"【危机传播】回答问题两次以上算满分+八千字以内的小组文献综述+一次半开卷期末测试\\n\\n老师给分好，文献综述的事情可能稍微比较多，但是也学到了写综述的很多方法，我们应该是第一批上危机传播课程的同学，整理PPT资料可能会有点麻烦，但是下几届同学应该可以问问要学长学姐整理的，我感觉老师上课思路还是很清晰的，很认真负责的美女老师～"},{"发表时间":"2023-07-05 09:09:32","点赞减去点踩数量":1,"点赞量":1,"点踩量":0,"内容":"超级爱"},{"发表时间":"2023-07-09 02:23:09","点赞减去点踩数量":1,"点赞量":1,"点踩量":0,"内容":"老师讲课很温柔，给分好"},{"发表时间":"2023-08-31 13:25:06","点赞减去点踩数量":3,"点赞量":4,"点踩量":1,"内容":"美貌智慧口才并存的女人，居然结婚了呜呜呜"},{"发表时间":"2023-09-06 07:22:11","点赞减去点踩数量":4,"点赞量":5,"点踩量":1,"内容":"【公共关系学】一份小组策划案+个人pre+小测，作业难度适中而且体验很好。老师给分很好，能学到东西。最后，最最最想夸的一点是老师会给作业反馈！！！word加批注的那种，我天……我们组成员都很震惊且感动，课后找老师问问题老师也很耐心指导，放心选～"},{"发表时间":"2023-11-29 16:10:37","点赞减去点踩数量":1,"点赞量":1,"点踩量":0,"内容":"老师真的人好好！！努力了就会有回报的课程～爱死纪老师"},{"发表时间":"2023-12-20 17:45:26","点赞减去点踩数量":0,"点赞量":3,"点踩量":3,"内容":"我很难评，，，，，"},{"发表时间":"2023-12-20 20:34:59","点赞减去点踩数量":0,"点赞量":3,"点踩量":3,"内容":"我也很难平。"},{"发表时间":"2023-12-23 06:37:46","点赞减去点踩数量":0,"点赞量":3,"点踩量":3,"内容":"emm真的很难评"},{"发表时间":"2023-12-24 11:52:24","点赞减去点踩数量":0,"点赞量":0,"点踩量":0,"内容":"老师特别特别特别好，是我上大学三年以来最喜欢对我影响最大的老师之一，能看到学生的实际需求，给的指导非常细致基础，对我帮助真的很大，感恩"},{"发表时间":"2024-01-03 19:36:11","点赞减去点踩数量":1,"点赞量":2,"点踩量":1,"内容":"上大学以来最喜欢的一个老师，虽然还没结课，也还没出分，但不管结果怎么样都想说爱您纪老师！特别善良特别负责特别温柔！会给特别详细的作业反馈，会给你很多鼓励！"},{"发表时间":"2024-01-09 09:35:07","点赞减去点踩数量":0,"点赞量":1,"点踩量":1,"内容":"纪老师我爱你！！！！"},{"发表时间":"2024-01-09 09:50:34","点赞减去点踩数量":0,"点赞量":4,"点踩量":4,"内容":"速来给纪老师写评语！\\n\\n超温柔的老师！很年轻所以上课不会有距离感，会给我们分享追星经历和省钱购物）。分析作业也会提很认真负责的建议，专业水平是绝对够的认真听可以学到很多。\\n\\n课程内容属于公关入门，以记忆为主所以很好理解也不会觉得硬核。可以线上线下相结合，基本不点名，点名没点到好像也不会有事）。但是作业会有策划案，建议零基础的同学找好策略传播的队友，小组合作是要花时间的！而且免不了熬夜！大家很卷！虽然但是最后策划案做出来真的太有成就感了，也和小组里的同学成为了好朋友！\\n\\n考试是选择，半开卷，难度不高，整理下PPT成绩会不错的。只要作业考试都不是太划水给分一定很好！\\n\\n这个学期学到很多也学得很开心的课程！策传里相当好的课！选她！"},{"发表时间":"2024-01-09 10:02:15","点赞减去点踩数量":1,"点赞量":1,"点踩量":0,"内容":"老师真的很好。每一次策划案阶段作业都会认真反馈，每个组都会有专门的答疑时间，担心我们做策划案太累去掉了考试的简答论述题，给分也超好"},{"发表时间":"2024-01-09 10:41:26","点赞减去点踩数量":-1,"点赞量":1,"点踩量":2,"内容":"。。。"},{"发表时间":"2024-01-09 11:06:02","点赞减去点踩数量":3,"点赞量":5,"点踩量":2,"内容":"纪老师真的超级无敌好啊啊啊！老师长得美 讲课逻辑清晰 声音响亮 给分好 不点名 教学安排作业要求讲得清清楚楚 课后耐心细致给我们每个小组一对一答疑 在我们的策划案存在的不足被评委指出时老师还会安慰我们 除了老师自己讲课之外还会请到业界大佬来做分享 总之在公共关系学课上真的学到了很多很多 最后完成一份完整的公关策划案也让人很有成就感！！yrjj我爱你ε٩(๑> ₃ <)۶ з！！！"},{"发表时间":"2024-01-09 13:28:44","点赞减去点踩数量":2,"点赞量":2,"点踩量":0,"内容":"盈如jj我爱你！！！！！！！出了分感觉没有辜负自己整个冬学期的努力！！！"},{"发表时间":"2024-01-13 04:17:08","点赞减去点踩数量":2,"点赞量":4,"点踩量":2,"内容":"全程认真做了，期末考感觉也不错都写出来了，就是课堂发言少了点。\\n\\n70分出头，有点吓人的，不知道的以为我少交了个作业呢！"},{"发表时间":"2024-05-10 10:14:08","点赞减去点踩数量":0,"点赞量":0,"点踩量":0,"内容":"认真完成作业，给分很好"},{"发表时间":"2024-06-06 05:58:03","点赞减去点踩数量":2,"点赞量":3,"点踩量":1,"内容":"很难评。课程要求一成不变，自己水，对学生要求高"},{"发表时间":"2024-06-06 06:00:21","点赞减去点踩数量":0,"点赞量":1,"点踩量":1,"内容":"很难评，文献八百年不更新，课时那么少，一页ppt不做，只让学生生讲，真的合适嘛"},{"发表时间":"2024-06-11 15:55:13","点赞减去点踩数量":0,"点赞量":2,"点踩量":2,"内容":"毕业论文开题结题都是给分最低问题最抠，无语至极，隔壁新闻结题动辄60+，是我们传播低人一等了，谢谢老师，提前明年申请寄了"},{"发表时间":"2024-08-22 00:54:15","点赞减去点踩数量":0,"点赞量":2,"点踩量":2,"内容":"上课好 给分高 无脑选 好人"},{"发表时间":"2024-11-06 12:35:42","点赞减去点踩数量":0,"点赞量":3,"点踩量":3,"内容":"老师人很好，上课会有一定的任务量但是认真学的话分数不会低，并且能学到东西。虽然纪老师日常很忙但是会认真给同学反馈，当班主任的时候还会安排时间和班里的同学一对一或者多对一交流，总而言之是一个非常负责的好老师。"},{"发表时间":"2024-11-10 12:46:00","点赞减去点踩数量":7,"点赞量":11,"点踩量":4,"内容":"【公共关系学】真的无语。自己上课讲的理论是没什么用的，就上课体验而言个人水平是一般的，小组作业是距离我们极远的、难做的，要求是高的，问问题office hour是没有的，回答是完全不解决问题只有空话的，个人作业布置是不清晰的，给分不知道但是事情是真的多的。。。"},{"发表时间":"2024-11-11 11:20:35","点赞减去点踩数量":1,"点赞量":2,"点踩量":1,"内容":"吐槽一下个人作业\\n\\n开学时说的案例分析培训是没有的\\n\\n实践导向的课给的参考是纯学术的"},{"发表时间":"2024-11-12 07:52:30","点赞减去点踩数量":2,"点赞量":5,"点踩量":3,"内容":"从讲课到作业到案例点评，每一部分都难以置信。要求是高的，教是不教的，自己没水平还要硬点评的。"},{"发表时间":"2024-11-13 06:33:36","点赞减去点踩数量":0,"点赞量":0,"点踩量":0,"内容":"eee"},{"发表时间":"2025-01-01 06:18:27","点赞减去点踩数量":3,"点赞量":5,"点踩量":2,"内容":"就是不喜欢"},{"发表时间":"2025-01-05 10:39:00","点赞减去点踩数量":2,"点赞量":3,"点踩量":1,"内容":"很认真的老师，会很认真看每组案例并给出很有针对性的建议，可能也是大家说的要求比较高的原因。考试也不难，感觉非常负责一位老师"},{"发表时间":"2025-01-09 11:26:25","点赞减去点踩数量":1,"点赞量":1,"点踩量":0,"内容":"新闻学选公关当作专业选修课，老师很好的，一开始会觉得要求比较高，但是给的建议都是很有建设性的，PPT、作业考试要求也都清晰明确，一对一答疑包括期末考试总体都还是比较友好的，给分也不错，收获很大。"},{"发表时间":"2025-01-10 14:18:58","点赞减去点踩数量":0,"点赞量":2,"点踩量":2,"内容":"小组作业跟着组长走，个人作业查查资料，期末随便准备一下，然后满了。\\n\\n谢谢老师。"},{"发表时间":"2025-01-19 06:18:05","点赞减去点踩数量":2,"点赞量":2,"点踩量":0,"内容":"对中东要有一辈子阴影了，以后我只说西亚，不说中东"},{"发表时间":"2025-04-24 09:14:30","点赞减去点踩数量":0,"点赞量":0,"点踩量":0,"内容":"传院小天使"}],"gpa_info":[["公共关系学",4.33,382,0.9],["危机传播",4.58,126,0.72]]},{"id":6977,"姓名":"周林","学院":"化学工程与生物工程学院","热度":40,"评分人数":0,"评分":0.0,"拼音":"zhoulin","拼音缩写":"zl","comments":[],"gpa_info":[]},{"id":6978,"姓名":"夏冬冬","学院":"人文学院","热度":40,"评分人数":0,"评分":0.0,"拼音":"xiadongdong","拼音缩写":"xdd","comments":[],"gpa_info":[]},{"id":6979,"姓名":"VARKHEDKAR RAJESH","学院":"化学系","热度":60,"评分人数":0,"评分":0.0,"拼音":"varkhedkarrajesh","拼音缩写":"vr","comments":[],"gpa_info":[]},{"id":6980,"姓名":"王崧","学院":"化学工程与生物工程学院","热度":80,"评分人数":0,"评分":0.0,"拼音":"wangsong","拼音缩写":"ws","comments":[],"gpa_info":[]},{"id":6981,"姓名":"方伊曼","学院":"地球科学学院","热度":1340,"评分人数":0,"评分":0.0,"拼音":"fangyiman","拼音缩写":"fym","comments":[],"gpa_info":[]},{"id":6982,"姓名":"刘一丹","学院":"医学院","热度":60,"评分人数":0,"评分":0.0,"拼音":"liuyidan","拼音缩写":"lyd","comments":[],"gpa_info":[]},{"id":6983,"姓名":"王昭荣","学院":"动物科学学院","热度":40,"评分人数":0,"评分":0.0,"拼音":"wangzhaorong","拼音缩写":"wzr","comments":[],"gpa_info":[]},{"id":6984,"姓名":"Sankar Prasad Bag","学院":"航空航天学院","热度":40,"评分人数":0,"评分":0.0,"拼音":"sankarprasadbag","拼音缩写":"spb","comments":[],"gpa_info":[]},{"id":6985,"姓名":"张硕卿","学院":"化学系","热度":60,"评分人数":1,"评分":0.0,"拼音":"zhangshuoqing","拼音缩写":"zsq","comments":[{"发表时间":"2024-09-21 03:50:45","点赞减去点踩数量":1,"点赞量":1,"点踩量":0,"内容":"他的课10甚至是9分的好听，日麻水平很高"}],"gpa_info":[]},{"id":6986,"姓名":"雷力","学院":"物理学系","热度":160,"评分人数":0,"评分":0.0,"拼音":"leili","拼音缩写":"ll","comments":[],"gpa_info":[]},{"id":6987,"姓名":"朱文娟","学院":"光电科学与工程学院","热度":40,"评分人数":0,"评分":0.0,"拼音":"zhuwenjuan","拼音缩写":"zwj","comments":[],"gpa_info":[]},{"id":6988,"姓名":"陈国新","学院":"地球科学学院","热度":2302,"评分人数":7,"评分":6.77056,"拼音":"chenguoxin","拼音缩写":"cgx","comments":[{"发表时间":"2021-11-30 05:13:35","点赞减去点踩数量":4,"点赞量":9,"点踩量":5,"内容":"傻逼。"},{"发表时间":"2022-05-17 05:40:24","点赞减去点踩数量":5,"点赞量":13,"点踩量":8,"内容":"陈老师很好很耐心呀，也很为学生着想，很理解学生的难处，同时为学生提供了大量的资源援助。"},{"发表时间":"2022-05-18 04:30:34","点赞减去点踩数量":4,"点赞量":10,"点踩量":6,"内容":"傻逼把你嘴里的拖鞋拿出来再说话"},{"发表时间":"2022-06-16 02:47:35","点赞减去点踩数量":1,"点赞量":5,"点踩量":4,"内容":"贱逼"},{"发表时间":"2022-11-04 07:52:04","点赞减去点踩数量":4,"点赞量":5,"点踩量":1,"内容":"希望大家理性评论，客观评价，不要出口成脏污蔑老师"},{"发表时间":"2024-05-17 07:13:54","点赞减去点踩数量":1,"点赞量":1,"点踩量":0,"内容":"还行吧"}],"gpa_info":[]},{"id":6989,"姓名":"李林","学院":"生命科学学院","热度":80,"评分人数":0,"评分":0.0,"拼音":"lilin","拼音缩写":"ll","comments":[],"gpa_info":[]},{"id":6990,"姓名":"杨易栋","学院":"建筑设计研究院","热度":80,"评分人数":0,"评分":0.0,"拼音":"yangyidong","拼音缩写":"yyd","comments":[],"gpa_info":[]},{"id":6991,"姓名":"李苹","学院":"农业与生物技术学院","热度":40,"评分人数":0,"评分":0.0,"拼音":"liping","拼音缩写":"lp","comments":[],"gpa_info":[]},{"id":6992,"姓名":"梁黎","学院":"医学院","热度":40,"评分人数":0,"评分":0.0,"拼音":"liangli","拼音缩写":"ll","comments":[],"gpa_info":[]},{"id":6993,"姓名":"方学贤","学院":"医学院","热度":40,"评分人数":1,"评分":0.0,"拼音":"fangxuexian","拼音缩写":"fxx","comments":[{"发表时间":"2020-09-10 11:11:31","点赞减去点踩数量":-1,"点赞量":0,"点踩量":1,"内容":"哈哈哈哈"}],"gpa_info":[]},{"id":6994,"姓名":"吉晨","学院":"信息与电子工程学院","热度":2586,"评分人数":13,"评分":9.04058,"拼音":"jichen","拼音缩写":"jc","comments":[{"发表时间":"2021-06-22 14:17:28","点赞减去点踩数量":2,"点赞量":5,"点踩量":3,"内容":"讲课有水平，英语很标准，但是个绩杀"},{"发表时间":"2021-06-27 15:19:29","点赞减去点踩数量":8,"点赞量":11,"点踩量":3,"内容":"Prof. Chen Ji 【信息与电子工程导论】\\n\\n全英文的课，老师很厉害英语也很标准。康奈尔ECE的PhD毕业，在美国硅谷待过几年后回国的，因此内容会比中文丰富一些。\\n\\n讲课也不错，作为导论课能带来很开阔的视野。英语不错的同学可以挑战一下，对外交流项目之类的会很有帮助。\\n\\n点名！点名！老师似乎有点中规中矩，学校教务部门要求课程点名所以就点……\\n\\n老师不太管每周的作业和最后的大作业，有问题建议找助教。\\n\\n最后的绩点也挺高的。考试和中文考试一样，比较水。如果考试没太大问题，大作业稍有点错误（我们组制作出来3位），总评绩点上4.5/4.8也不太难。"},{"发表时间":"2022-04-24 04:38:30","点赞减去点踩数量":2,"点赞量":2,"点踩量":0,"内容":"还没出成绩 来给老师评分\\n\\n很好的老师 人格魅力超nice 水平高赞也说了\\n\\n有问题问助教 助教很负责任 老师不太管作业和测试\\n\\n任务和其他班一样多 期末考全英文但不会看不懂（唯一能带ppt的班级）\\n\\n好像有一点舍不得上完他的课（虽然并没有好好听 惭愧 十分了"},{"发表时间":"2023-05-15 11:24:50","点赞减去点踩数量":1,"点赞量":1,"点踩量":0,"内容":"没雷，很轻松的课，能听懂的地方听下就好\\n\\n全程数字点名，所以实际上课间开下智云就能水过\\n\\n中文课本要早买，三个lab费了好多时间"},{"发表时间":"2023-07-11 03:14:28","点赞减去点踩数量":0,"点赞量":1,"点踩量":1,"内容":"计院大三老狗选信电导，轻松4.8 不错不错"},{"发表时间":"2024-01-02 15:21:31","点赞减去点踩数量":1,"点赞量":1,"点踩量":0,"内容":"超级好的老师，给分好"},{"发表时间":"2024-05-09 00:23:12","点赞减去点踩数量":-2,"点赞量":2,"点踩量":4,"内容":"给昏没想象中好，但我也没太学好所以也就这样吧。纯英课后期真听不懂，老师确实在认真教但感觉大家英语水平实在有限。。。我是课基本都翘了靠同学的数字点名，要是想学的话可以看其他老师的中文课，想水的话考前看看PPT和书也行。"},{"发表时间":"2024-05-09 09:28:44","点赞减去点踩数量":-1,"点赞量":5,"点踩量":6,"内容":"老师英语水平真的很好（远超绝大多数大英老师），专业小白也不会因纯英而听不懂，专业词汇翻来覆去不超过50个，只要听课时顺手查一下，期末考基本用不上字典也认识了。至于给分应该是这次期末偏难了，没预期高，不过大多数人还是有4.5 +，说绩杀可能并不公平。"}],"gpa_info":[]},{"id":6995,"姓名":"章爱斌","学院":"医学院","热度":40,"评分人数":0,"评分":0.0,"拼音":"zhangaibin","拼音缩写":"zab","comments":[],"gpa_info":[]},{"id":6996,"姓名":"蓝丽华","学院":"生物系统工程与食品科学学院","热度":440,"评分人数":0,"评分":0.0,"拼音":"lanlihua","拼音缩写":"llh","comments":[],"gpa_info":[]}]