[{"id":4183,"姓名":"郭文刚","学院":"建筑工程学院","热度":784,"评分人数":1,"评分":0.0,"拼音":"guowengang","拼音缩写":"gwg","comments":[{"发表时间":"2018-12-16 12:23:31","点赞减去点踩数量":-11,"点赞量":2,"点踩量":13,"内容":"老师讲课很好，挺有趣的，备课也很认真。但是他真的不知道几点钟下课啊啊啊啊啊啊！8:05下课永远拖到8:55"}],"gpa_info":[["形势与政策Ⅰ","3.79","488","0.52"]]},{"id":4184,"姓名":"罗小华","学院":"信息与电子工程学院","热度":3126,"评分人数":5,"评分":4.74717,"拼音":"luoxiaohua","拼音缩写":"lxh","comments":[{"发表时间":"2023-11-29 03:51:36","点赞减去点踩数量":4,"点赞量":4,"点踩量":0,"内容":"没有感情的念PPT机器"},{"发表时间":"2024-01-16 04:28:17","点赞减去点踩数量":3,"点赞量":3,"点踩量":0,"内容":"《结构体自己定义》你是懂增加学生负担的，考试前一天晚上专门说一句生怕我们把时间都花在复习考试要考的内容上是吧，真是幽默。"},{"发表时间":"2024-12-25 02:34:56","点赞减去点踩数量":7,"点赞量":7,"点踩量":0,"内容":"我来歌颂你。shb很好，以后不要再跟“它”了"},{"发表时间":"2025-01-16 11:23:22","点赞减去点踩数量":0,"点赞量":0,"点踩量":0,"内容":"连考试范围都说不清楚。。。"}],"gpa_info":[["微控制器原理、接口与应用","3.75","303","0.95"]]},{"id":4187,"姓名":"王俊","学院":"生物系统工程与食品科学学院","热度":2831,"评分人数":13,"评分":4.07698,"拼音":"wangjun","拼音缩写":"wj","comments":[{"发表时间":"2018-07-06 16:42:45","点赞减去点踩数量":5,"点赞量":8,"点踩量":3,"内容":"浙大原来有三个王俊..."},{"发表时间":"2019-06-30 01:34:34","点赞减去点踩数量":3,"点赞量":3,"点踩量":0,"内容":"上课不给PPT，讲的内容都是十多年的旧东西，每次上课八点一打铃就拍照点名，给分巨低，刁难学生"},{"发表时间":"2020-09-16 10:18:07","点赞减去点踩数量":3,"点赞量":3,"点踩量":0,"内容":"生工食品学院的sb代表（没人反对吧？）\\n\\n\\n\\n钉钉上课，迟到一节课，一句道歉都没有\\n\\n\\n\\n给分极差"},{"发表时间":"2022-12-15 16:28:08","点赞减去点踩数量":3,"点赞量":3,"点踩量":0,"内容":"没开课先来骂贵院的sb一下，希望不要不识抬举"},{"发表时间":"2023-04-29 09:27:07","点赞减去点踩数量":6,"点赞量":7,"点踩量":1,"内容":"sgsp最逆天的课之一，一学期五个ppt还闭卷考，逆天他妈给逆天开门，逆天到家了"},{"发表时间":"2023-06-08 16:47:17","点赞减去点踩数量":5,"点赞量":5,"点踩量":0,"内容":"生工食品这个傻卵子学院最恶心人的一点是，他恶心了你还要教你写心得体悟夸夸他，我他妈夸你妈的，一天到晚心得，得你妈的，一群臭傻逼。"},{"发表时间":"2023-07-06 10:59:47","点赞减去点踩数量":5,"点赞量":5,"点踩量":0,"内容":"具备了我院破课所有典型特征:\\n\\n事多，五个ppt，还鼓励多做，此其一。\\n\\n分烂，是真的很烂，此其二。\\n\\n什么都学不到，这没什么，我院的课就不可能学到东西，此其三。\\n\\n心得体会，一坨大便，此其四。\\n\\n爱点名，这也是我院风格，此其五。\\n\\n学弟学妹们自重。"},{"发表时间":"2023-07-06 12:30:49","点赞减去点踩数量":2,"点赞量":4,"点踩量":2,"内容":"赶紧414"},{"发表时间":"2023-07-07 02:42:05","点赞减去点踩数量":3,"点赞量":4,"点踩量":1,"内容":"分烂，但王俊的部分好歹还是能速成的，恶心的是王永维，鼓励多做的也是王永维，隔壁那个才是真傻逼"},{"发表时间":"2023-09-07 12:54:47","点赞减去点踩数量":-1,"点赞量":1,"点踩量":2,"内容":"内容详实"},{"发表时间":"2024-07-07 00:34:19","点赞减去点踩数量":0,"点赞量":0,"点踩量":0,"内容":"没挂哦耶"},{"发表时间":"2024-07-07 04:34:37","点赞减去点踩数量":1,"点赞量":1,"点踩量":0,"内容":"上课不清，ppt又长又臭，考点不明，消息不看，还没王永w负责。每个点都故意提一嘴，还不告诉答案，美名其曰锻炼自学能力，师者所以传道授业解惑也，我要自学都会了还要你教啥？？？？"}],"gpa_info":[["哲学问题","4.30","199","0.47"],["大学物理（丙）","3.53","500+","1.07"],["大学物理（甲）Ⅱ","3.45","356","1.03"],["现代西方哲学I","4.29","249","0.57"],["生物物料学","3.43","220","0.75"]]},{"id":4188,"姓名":"熊卫平","学院":"马克思主义学院","热度":2409,"评分人数":0,"评分":0.0,"拼音":"xiongweiping","拼音缩写":"xwp","comments":[],"gpa_info":[["习近平新时代中国特色社会主义思想概论","4.27","500+","0.39"],["公共关系学","3.99","114","0.56"],["新时代中国特色社会主义理论和实践热点问题研究","3.81","60","0.68"],["毛泽东思想和中国特色社会主义理论体系概论","4.11","500+","0.46"]]},{"id":4189,"姓名":"费兰兰","学院":"马克思主义学院","热度":3973,"评分人数":40,"评分":6.14629,"拼音":"feilanlan","拼音缩写":"fll","comments":[{"发表时间":"2018-02-01 12:03:37","点赞减去点踩数量":9,"点赞量":16,"点踩量":7,"内容":"与马老师形成鲜明对比\\n\\n"},{"发表时间":"2018-06-19 17:42:39","点赞减去点踩数量":0,"点赞量":3,"点踩量":3,"内容":"好过mjq"},{"发表时间":"2018-09-16 09:19:16","点赞减去点踩数量":-6,"点赞量":2,"点踩量":8,"内容":"拉个分保佑我"},{"发表时间":"2018-11-23 06:10:24","点赞减去点踩数量":16,"点赞量":21,"点踩量":5,"内容":"话真多"},{"发表时间":"2018-12-25 07:46:01","点赞减去点踩数量":-4,"点赞量":3,"点踩量":7,"内容":"会举很多她经历的事情，挺有趣的"},{"发表时间":"2019-03-06 10:52:09","点赞减去点踩数量":10,"点赞量":12,"点踩量":2,"内容":"费兰兰老师，您是我奶奶，我想跪在您脚下"},{"发表时间":"2019-05-22 02:23:45","点赞减去点踩数量":13,"点赞量":14,"点踩量":1,"内容":"校团委沈书记的夫人?"},{"发表时间":"2019-09-23 08:34:36","点赞减去点踩数量":2,"点赞量":2,"点踩量":0,"内容":"就这样吧"},{"发表时间":"2019-10-17 15:58:15","点赞减去点踩数量":8,"点赞量":10,"点踩量":2,"内容":"自己院会借教室还那么多鬼话？不可取，有失公正，建议革职"},{"发表时间":"2020-06-15 17:43:11","点赞减去点踩数量":0,"点赞量":5,"点踩量":5,"内容":"关心学生的老师，学习/生活上的事情大可以咨询一下费老师"},{"发表时间":"2020-09-07 04:39:40","点赞减去点踩数量":18,"点赞量":29,"点踩量":11,"内容":"生工食品学院的流氓 乌烟瘴气\\n\\n许堪鑫这种人包pi\\n\\n估计是有利益瓜葛吧hhh\\n\\n毕竟是校团委夫人对吧"},{"发表时间":"2020-11-26 00:53:38","点赞减去点踩数量":-1,"点赞量":2,"点踩量":3,"内容":"我觉得老师很好啊 上课都很有意思 不仅是思修课堂 可以发展学生的多方面能力"},{"发表时间":"2021-02-01 04:14:34","点赞减去点踩数量":-8,"点赞量":2,"点踩量":10,"内容":"老师人很好，会分享自己的故事。\\n\\n讲课还行，给分貌似还不错？"},{"发表时间":"2021-02-01 04:35:14","点赞减去点踩数量":1,"点赞量":5,"点踩量":4,"内容":"老师事情还算少吧，没有志愿者报告只看小时数，课上多发言，最后绩点4.5还是感谢老师！"},{"发表时间":"2021-02-01 05:40:10","点赞减去点踩数量":-5,"点赞量":1,"点踩量":6,"内容":"课上的很好"},{"发表时间":"2021-09-17 00:26:13","点赞减去点踩数量":8,"点赞量":9,"点踩量":1,"内容":"嘴上都是主义，心里全是生意\\n\\n废话多，自我感觉好\\n\\n和潘老师对比鲜明"},{"发表时间":"2021-09-28 03:13:39","点赞减去点踩数量":0,"点赞量":1,"点踩量":1,"内容":"呵呵呵呵"},{"发表时间":"2021-10-08 01:23:34","点赞减去点踩数量":-1,"点赞量":1,"点踩量":2,"内容":"上课很好笑简直了超级好笑"},{"发表时间":"2022-01-10 18:33:26","点赞减去点踩数量":0,"点赞量":3,"点踩量":3,"内容":"谢谢\\n\\n思修   组长\\n\\n拉低了绩点可还行"},{"发表时间":"2022-01-13 01:44:59","点赞减去点踩数量":3,"点赞量":3,"点踩量":0,"内容":"水平不足"},{"发表时间":"2022-01-17 07:32:07","点赞减去点踩数量":2,"点赞量":3,"点踩量":1,"内容":"从思修课角度来看，事情算少，给分正常（政治生平时摸鱼考试自信不错最后4.2）但是真的不是很喜欢这个老师的三观吧。作为思政老师，有厌女倾向（说不建议女生读计算机之类的各种发言）害，说话大多假大空，会举一些学生拜托自己然后获得成就的例子。我还是比较尊重学术上有成就的老师。"},{"发表时间":"2022-03-11 10:07:36","点赞减去点踩数量":3,"点赞量":3,"点踩量":0,"内容":"讲话很低能"},{"发表时间":"2022-11-01 00:29:29","点赞减去点踩数量":3,"点赞量":3,"点踩量":0,"内容":"球门高一米，费兰大四喜"},{"发表时间":"2023-04-03 11:34:13","点赞减去点踩数量":3,"点赞量":3,"点踩量":0,"内容":"说话真的肤浅，都是口号，体育生文化水平就这样"},{"发表时间":"2023-10-28 06:12:53","点赞减去点踩数量":1,"点赞量":1,"点踩量":0,"内容":"思修课闭卷考?您自己试试?!"},{"发表时间":"2023-12-04 01:45:07","点赞减去点踩数量":0,"点赞量":0,"点踩量":0,"内容":"😺😺😺"},{"发表时间":"2023-12-08 06:52:50","点赞减去点踩数量":0,"点赞量":0,"点踩量":0,"内容":"自己品味吧"},{"发表时间":"2024-01-17 03:44:00","点赞减去点踩数量":0,"点赞量":0,"点踩量":0,"内容":"给分一般还卡绩"},{"发表时间":"2024-01-17 16:07:33","点赞减去点踩数量":-1,"点赞量":2,"点踩量":3,"内容":"不知道该怎么说，翻了下以往的评论，感觉这位老师的风评不是很好，但是真的上过她的课直到结课后，我真觉得没有评论说得那么难听。我一开始也是带着“先入为主”的印象上的课的，我觉得老师真的没什么问题，人美而且也比较负责，感觉大家还是不要先入为主吧。"},{"发表时间":"2024-05-31 21:30:02","点赞减去点踩数量":0,"点赞量":1,"点踩量":1,"内容":"狗喜欢亲近人类，当狗认主之后，对于主人就有较大的依赖性。\\n\\n与之相对的，很多狗在遇到陌生人时，因为缺乏安全感，就会容易发生吠叫的情况。\\n\\n\\n\\n其实狗仗人势很大一部分是因为天性。因为狗和人一样都是群居动物，而人在有后盾的情况下，都是比较张狂的，狗也是一样。\\n\\n所以造成了很多狗在有宠主的情况下，会更大胆，甚至连比它厉害的人和动物都敢挑衅。\\n\\n\\n\\n狗是很擅长于模仿的动物，尤其喜欢模仿宠主。\\n\\n所以如果平时宠主的作风就是“狗仗人势”的话，那经过时间的锻炼，狗就会和宠主一样，作风也就变成狗仗人势了。"},{"发表时间":"2024-06-04 07:26:14","点赞减去点踩数量":0,"点赞量":0,"点踩量":0,"内容":"不好。"},{"发表时间":"2025-01-10 01:36:00","点赞减去点踩数量":2,"点赞量":2,"点踩量":0,"内容":"上的她跟sly的思政课  她只来上过两三遍  不过都会点名\\n\\n\\n\\n平心而论  老师确实好漂亮  下面有些人的评价也很中肯   她还会给我们讲转专业的事情  总之至少那两节课我能看出她还是用心上的吧"}],"gpa_info":[["思想道德与法治","4.21","489","0.46"],["思想道德修养与法律基础","3.98","79","0.60"]]},{"id":4191,"姓名":"田生科","学院":"环境与资源学院","热度":2666,"评分人数":4,"评分":0.0,"拼音":"tianshengke","拼音缩写":"tsk","comments":[{"发表时间":"2019-07-06 17:09:02","点赞减去点踩数量":9,"点赞量":11,"点踩量":2,"内容":"垃圾老师，给分极差，付出得到不成正比"},{"发表时间":"2020-07-04 11:37:31","点赞减去点踩数量":-7,"点赞量":0,"点踩量":7,"内容":"谢谢老师！"},{"发表时间":"2022-06-23 07:38:57","点赞减去点踩数量":1,"点赞量":1,"点踩量":0,"内容":"事情有点多，给分不好"}],"gpa_info":[["植物营养与施肥实习","4.27","133","0.40"],["植物营养实习与劳动实践","4.06","48","0.60"],["植物营养诊断与施肥","3.93","165","0.52"]]},{"id":4192,"姓名":"廖敏","学院":"动物科学学院","热度":2245,"评分人数":1,"评分":0.0,"拼音":"liaomin","拼音缩写":"lm","comments":[{"发表时间":"2018-05-11 01:24:57","点赞减去点踩数量":0,"点赞量":4,"点踩量":4,"内容":"老师偶尔点个名 不过给分好是真的 我翘了一次点名有4.2 而且全班平均好像4.18吧…一次个人展示+开卷考试 性价比很高的个性课了 基本不用花什么时间在上面"}],"gpa_info":[["兽医公共卫生学","4.49","47","0.26"],["兽医公共卫生学实验","4.50","45","0.43"],["动物免疫学","3.95","200","0.81"],["动物免疫学实验","4.37","68","0.50"],["土壤与植物营养现代分析技术","3.27","31","0.62"],["土壤与环境分析","3.27","172","0.84"],["生物制品学","4.35","131","0.48"]]},{"id":4193,"姓名":"詹良通","学院":"宁波理工学院","热度":621,"评分人数":0,"评分":0.0,"拼音":"zhanliangtong","拼音缩写":"zlt","comments":[],"gpa_info":[["土力学","3.02","87","0.95"]]},{"id":4194,"姓名":"管文军","学院":"医学院","热度":682,"评分人数":0,"评分":0.0,"拼音":"guanwenjun","拼音缩写":"gwj","comments":[],"gpa_info":[["医学微生物与免疫学","3.36","446","0.95"],["生物化学（乙）","3.30","188","0.96"],["生物化学（甲）","3.14","38","1.29"]]},{"id":4195,"姓名":"丁婉婧","学院":"海洋学院","热度":2244,"评分人数":3,"评分":0.0,"拼音":"dingwanjing","拼音缩写":"dwj","comments":[{"发表时间":"2024-11-06 10:26:56","点赞减去点踩数量":1,"点赞量":1,"点踩量":0,"内容":"事少，讲得好，考前会划重点总结，细胞生物学体验非常好！！！"},{"发表时间":"2024-11-06 10:27:10","点赞减去点踩数量":1,"点赞量":1,"点踩量":0,"内容":"讲得好，条理清晰，划重点很到位，非常好的老师，人也很温柔，不选真的血亏"},{"发表时间":"2025-04-09 12:26:27","点赞减去点踩数量":0,"点赞量":0,"点踩量":0,"内容":"据说丁老师实验室非常好经常看到研究生出去玩XDDD"}],"gpa_info":[["现代药理学实验技术","3.82","17","1.10"],["细胞生物学","3.51","87","1.00"]]},{"id":4197,"姓名":"王昊","学院":"先进技术研究院","热度":162,"评分人数":1,"评分":0.0,"拼音":"wanghao","拼音缩写":"wh","comments":[],"gpa_info":[["电子电路基础及实验","3.19","144","1.05"]]},{"id":4198,"姓名":"王飞","学院":"电气工程学院","热度":422,"评分人数":1,"评分":0.0,"拼音":"wangfei","拼音缩写":"wf","comments":[{"发表时间":"2018-06-07 07:35:26","点赞减去点踩数量":0,"点赞量":0,"点踩量":0,"内容":"沙壁吧，给分乱七八糟，之前跟我们说实验报告手写分数高，写了一段时间，某一周不手写改打印了，结果分数变高了，一对比，发现之前手写的都是偏低的，你说气人不气人"}],"gpa_info":[["新能源系统检测与控制","4.02","85","0.81"],["现代分析测试技术","3.10","96","0.80"]]},{"id":4200,"姓名":"从飞云","学院":"机械工程学院","热度":11051,"评分人数":32,"评分":7.51334,"拼音":"congfeiyun","拼音缩写":"cfy","comments":[{"发表时间":"2019-03-28 03:14:05","点赞减去点踩数量":10,"点赞量":20,"点踩量":10,"内容":"“如果这个班的女生被其他班追去，班长是要受处分的！”给老师点赞?！"},{"发表时间":"2019-06-20 05:25:40","点赞减去点踩数量":2,"点赞量":4,"点踩量":2,"内容":"助教姐姐好好看"},{"发表时间":"2019-07-04 00:51:01","点赞减去点踩数量":3,"点赞量":4,"点踩量":1,"内容":"语速快，讲着讲着开始满嘴跑火车。"},{"发表时间":"2019-07-04 14:26:17","点赞减去点踩数量":1,"点赞量":6,"点踩量":5,"内容":"很负责的老师，上课深入浅出，尊重学生，讲的重点期末基本都考了，问问题发邮件回复很及时，好老师"},{"发表时间":"2019-07-08 09:15:16","点赞减去点踩数量":-2,"点赞量":1,"点踩量":3,"内容":"老师不错的 给分也挺好的"},{"发表时间":"2020-11-26 03:07:45","点赞减去点踩数量":11,"点赞量":15,"点踩量":4,"内容":"机械设计课程设计快逃\\n\\n管成班一堆满绩，抄袭两天完成的人4.5\\n\\n从飞云班认真做两个月都只有3+的绩点屁事还多很多，要求太严格\\n\\nfine 是我不配"},{"发表时间":"2022-06-29 08:54:26","点赞减去点踩数量":0,"点赞量":1,"点踩量":1,"内容":"你是觉得记得记得就地解决"},{"发表时间":"2023-07-06 06:11:46","点赞减去点踩数量":6,"点赞量":6,"点踩量":0,"内容":"上课深入浅出，遇到复杂的问题就“这个你们自己理解一下”"},{"发表时间":"2023-07-08 01:25:11","点赞减去点踩数量":6,"点赞量":22,"点踩量":16,"内容":"老师讲课水平一般，然后很多难点都是带带过，但好像机械考研里很重要。这门课内容是很多的，个人觉得最难的应该是齿轮，一堆公式看不太明白，别的其实b站上看看视频，总结一下题目类型，写在A4纸上带进去就行（轮系要自己做做，没有什么题型总结；自由度第一题纯送分）。老师给分真不错，可能赋分过（？）（复）预习一天也够了，最后满了。"},{"发表时间":"2023-07-08 13:59:36","点赞减去点踩数量":2,"点赞量":5,"点踩量":3,"内容":"给分不好"},{"发表时间":"2024-01-22 09:22:42","点赞减去点踩数量":3,"点赞量":6,"点踩量":3,"内容":"能不能别惦记你那车了"},{"发表时间":"2024-01-31 14:33:06","点赞减去点踩数量":-1,"点赞量":1,"点踩量":2,"内容":"老师给分感觉一般般，上课还行的"},{"发表时间":"2024-05-02 09:22:01","点赞减去点踩数量":-1,"点赞量":0,"点踩量":1,"内容":"csb"},{"发表时间":"2024-06-26 01:24:42","点赞减去点踩数量":-1,"点赞量":1,"点踩量":2,"内容":"可以的"},{"发表时间":"2024-06-26 03:30:19","点赞减去点踩数量":5,"点赞量":7,"点踩量":2,"内容":"元神云玩家"},{"发表时间":"2024-09-12 03:51:13","点赞减去点踩数量":0,"点赞量":1,"点踩量":1,"内容":"老师挺好，上课不会睡着。斩获专业课第一次满绩"},{"发表时间":"2024-09-20 02:25:15","点赞减去点踩数量":2,"点赞量":3,"点踩量":1,"内容":"满昏！感觉非常有激情，是上大学两三年来机械工程唯一一个讲课不会让人想睡觉的老师！现在在听的这课老师就是一句话一句话往外蹦，每句的声音都是渐弱，好像有一只mosquito在飞～从飞云会点名，随机喊人点名，扣不扣分我也不清楚，大家加油！"},{"发表时间":"2024-10-18 11:33:49","点赞减去点踩数量":3,"点赞量":3,"点踩量":0,"内容":"OK的从飞云的课很棒很棒，太棒了，兄弟，从老师是觉得你一个机械工程学院大二的学生，你刚学完设计与制造二 就应该画出很满分的作品 我们寝室隔壁李立新班两个满绩 从飞云两个3.6卡绩 我不觉得一个不看学长作品的机械大二学生能画出符合从老师心理期望的作品 还是希望老师给分能慈悲一点 合理考虑我们的实力"},{"发表时间":"2024-10-24 02:11:15","点赞减去点踩数量":2,"点赞量":2,"点踩量":0,"内容":"寝室哥们破防了"},{"发表时间":"2025-01-16 11:48:13","点赞减去点踩数量":1,"点赞量":1,"点踩量":0,"内容":"老师讲课很有激情，连着听三节课不困，给分也还可以！"},{"发表时间":"2025-01-16 14:12:13","点赞减去点踩数量":3,"点赞量":3,"点踩量":0,"内容":"设计与制造三玛德分巨低"},{"发表时间":"2025-02-19 13:39:52","点赞减去点踩数量":0,"点赞量":0,"点踩量":0,"内容":"盐都不盐了"}],"gpa_info":[["机械原理课程设计","4.10","207","0.78"],["机械设计课程设计（乙）","3.74","37","0.59"],["设计与制造Ⅱ","3.36","477","1.15"],["设计与制造Ⅲ","3.23","296","0.86"]]},{"id":4201,"姓名":"黄方亮","学院":"生命科学学院","热度":1185,"评分人数":2,"评分":0.0,"拼音":"huangfangliang","拼音缩写":"hfl","comments":[{"发表时间":"2022-12-08 06:15:41","点赞减去点踩数量":9,"点赞量":9,"点踩量":0,"内容":"生物芯片原理与数据处理：课程内容虽然比较顶，不过黄老师人真的好好，同学们有问题都能得到很耐心的解答和指导，实验课结果不好老师也会很热心的帮忙，感觉像亲近的学长一样~"}],"gpa_info":[["生物信息学","3.56","81","0.79"],["生物芯片原理及数据分析","4.31","33","0.46"]]},{"id":4202,"姓名":"夏冰","学院":"建筑工程学院","热度":2352,"评分人数":30,"评分":8.73032,"拼音":"xiabing","拼音缩写":"xb","comments":[{"发表时间":"2018-03-08 01:23:42","点赞减去点踩数量":1,"点赞量":3,"点踩量":2,"内容":"老师点子比较多，也比较爱开玩笑；不过不太懂如何与学生搞好关系，而且上他的课，要么你有想法，没想法你就得被他牵着鼻子走。。。"},{"发表时间":"2018-04-12 07:10:38","点赞减去点踩数量":29,"点赞量":32,"点踩量":3,"内容":"这个老师发型很赞！"},{"发表时间":"2018-05-14 15:15:21","点赞减去点踩数量":0,"点赞量":1,"点踩量":1,"内容":"? ? ?"},{"发表时间":"2018-06-30 05:06:39","点赞减去点踩数量":16,"点赞量":19,"点踩量":3,"内容":"夏老师\\n\\n我\\n\\nyyx\\n\\n实名表白\\n\\n上课讲的很多还会单独指点很多\\n\\n平常也是一个大朋友\\n\\n"},{"发表时间":"2018-06-30 05:07:35","点赞减去点踩数量":6,"点赞量":8,"点踩量":2,"内容":"很优秀噢~"},{"发表时间":"2018-10-17 04:04:51","点赞减去点踩数量":4,"点赞量":6,"点踩量":2,"内容":"大一夏老师班的同学到大二以后su和cad都用的特别6哦 看着其他同学头发一根一根掉 自己把任务量压缩到1/3真的很爽\\n\\n我敬仰夏老师"},{"发表时间":"2018-11-12 00:20:58","点赞减去点踩数量":3,"点赞量":4,"点踩量":1,"内容":"上课讲话声音太小了，上建制大课和平时上建基声音差不多，表示有时坐在前四排都听不到在说什么。有时喜欢尬笑。。。但是很有想法，如果有自己想法更好，不然会被牵着鼻子走"},{"发表时间":"2018-11-15 03:40:41","点赞减去点踩数量":1,"点赞量":1,"点踩量":0,"内容":"?"},{"发表时间":"2018-11-22 06:36:26","点赞减去点踩数量":1,"点赞量":2,"点踩量":1,"内容":"老师很可爱\\n\\n"},{"发表时间":"2018-11-22 07:17:43","点赞减去点踩数量":1,"点赞量":9,"点踩量":8,"内容":"大家做好准备，这门课可能会让你均绩下降一分。听学长一句劝，建工伤身伤心，赶紧转业。"},{"发表时间":"2019-03-01 01:03:01","点赞减去点踩数量":2,"点赞量":3,"点踩量":1,"内容":"老师讲课很温柔，让我很想睡觉"},{"发表时间":"2019-04-30 07:01:41","点赞减去点踩数量":5,"点赞量":7,"点踩量":2,"内容":"我真的真的好崇拜冰冰！！！真的很有想法而且能够减轻学生的负担！！虽然有时候会因为太佛了不太催导致跟不上任务书的进度 但真的上夏老师的课很放松而且感觉思路被打开了！！冰冰真的很棒只是有时候不太好意思说话！！！我爱冰冰！！！"},{"发表时间":"2019-06-26 16:25:06","点赞减去点踩数量":0,"点赞量":1,"点踩量":1,"内容":"老师真的很好很有想法！！！而且性格很温和 做事效率很高"},{"发表时间":"2019-06-28 06:08:26","点赞减去点踩数量":6,"点赞量":7,"点踩量":1,"内容":"欢迎大家匿名提意见！我会时常关注留言！并反馈于教学过程中！?"},{"发表时间":"2019-07-02 09:39:04","点赞减去点踩数量":1,"点赞量":1,"点踩量":0,"内容":"hhhhhhhhhhhhhhhhhhhhhhhhhhhhhhhz1"},{"发表时间":"2019-07-02 16:18:35","点赞减去点踩数量":10,"点赞量":12,"点踩量":2,"内容":"大家不要担心，那个冒充老师的是我儿子，请畅所欲言哈"},{"发表时间":"2019-10-18 04:48:13","点赞减去点踩数量":3,"点赞量":4,"点踩量":1,"内容":"讲课不会占用太多时间，也不会强迫学生按照自己的思路走，作业负担也比其他老师低。选上挺值得的。"},{"发表时间":"2019-10-19 02:45:12","点赞减去点踩数量":1,"点赞量":3,"点踩量":2,"内容":"你怎么连话都说不清楚？\\n\\n不如自学，书里讲的清楚多了"},{"发表时间":"2019-10-19 06:17:30","点赞减去点踩数量":0,"点赞量":0,"点踩量":0,"内容":"老师很认真 说话声音再大点就好了"},{"发表时间":"2019-12-13 03:41:38","点赞减去点踩数量":1,"点赞量":1,"点踩量":0,"内容":"老师很可爱"},{"发表时间":"2020-12-25 00:12:11","点赞减去点踩数量":0,"点赞量":3,"点踩量":3,"内容":"设计基础课是唯一一个可以用sketch up的，真的超爽，不像隔壁组不停的瞎做模型。"},{"发表时间":"2021-01-25 04:39:26","点赞减去点踩数量":2,"点赞量":3,"点踩量":1,"内容":"事少分好"},{"发表时间":"2021-11-26 14:02:54","点赞减去点踩数量":1,"点赞量":1,"点踩量":0,"内容":"喜欢冰冰，体贴和蔼。"},{"发表时间":"2022-06-10 20:59:50","点赞减去点踩数量":0,"点赞量":0,"点踩量":0,"内容":"我从没见过他摘下他的帽子。"},{"发表时间":"2022-06-27 06:25:57","点赞减去点踩数量":1,"点赞量":1,"点踩量":0,"内容":"嗯…夏老师人很好…嗯但是给分真的嗯…真的迷，给分真的有点垃圾wa"},{"发表时间":"2023-09-22 13:03:01","点赞减去点踩数量":0,"点赞量":0,"点踩量":0,"内容":"上了老师的设计课 人特别特别特别好的老师 男神"},{"发表时间":"2023-12-19 06:34:45","点赞减去点踩数量":1,"点赞量":1,"点踩量":0,"内容":"md越看越气   讲得太差了。。。。很不喜欢"}],"gpa_info":[["专题化设计Ⅰ","4.58","5","0.29"],["专题化设计Ⅱ","4.56","6","0.13"],["建筑制图","4.04","176","0.65"],["建筑制图Ⅰ","4.21","197","0.59"],["建筑设计初步","4.29","24","0.46"],["建筑设计基础","4.30","21","0.35"],["建筑设计基础Ⅰ","4.20","11","0.27"],["建筑设计基础Ⅱ","4.17","10","0.52"],["渲染周","3.95","282","0.68"],["现场研究","4.28","8","0.45"],["设计基础Ⅰ","4.26","10","0.42"],["设计基础Ⅱ","4.16","8","0.34"]]},{"id":4204,"姓名":"张颖岚","学院":"人文学院","热度":6507,"评分人数":11,"评分":9.05448,"拼音":"zhangyinglan","拼音缩写":"zyl","comments":[{"发表时间":"2018-02-06 15:43:26","点赞减去点踩数量":1,"点赞量":1,"点踩量":0,"内容":"很有干货"},{"发表时间":"2018-09-20 09:32:50","点赞减去点踩数量":1,"点赞量":1,"点踩量":0,"内容":"干货很足"},{"发表时间":"2019-09-04 07:01:06","点赞减去点踩数量":1,"点赞量":1,"点踩量":0,"内容":"张老师的课每节都收获满满，上课能把知识讲得很清楚，深入浅出，全程走动教学，想再上！而且老师下课后非常亲和！"},{"发表时间":"2019-12-20 09:15:30","点赞减去点踩数量":1,"点赞量":1,"点踩量":0,"内容":"优雅从容＋干货超足"},{"发表时间":"2020-01-21 17:53:38","点赞减去点踩数量":1,"点赞量":3,"点踩量":2,"内容":"上的是文化遗产导论 老师来讲了两节课，深入浅出真的讲得很好 而且后来有一份要交的纸质作业，由于寄托东教打印机导致没交上…给老师发邮件直接说帮我打印（我都做好去西溪交作业准备了qwq）还祝我学业进步（虽然可能是礼仪性单比起不回或者只回收到的真的太感动了qwq"},{"发表时间":"2022-01-22 22:37:57","点赞减去点踩数量":1,"点赞量":1,"点踩量":0,"内容":"老师温文尔雅，很好"},{"发表时间":"2023-09-27 07:47:54","点赞减去点踩数量":3,"点赞量":3,"点踩量":0,"内容":"很儒雅随和的老师，讲文化遗产导论时让人如沐春风，能够深入浅出地把案例和理论结合起来"},{"发表时间":"2023-09-27 09:54:33","点赞减去点踩数量":1,"点赞量":1,"点踩量":0,"内容":"男神！我的男神！"},{"发表时间":"2024-11-28 05:39:17","点赞减去点踩数量":2,"点赞量":2,"点踩量":0,"内容":"非常好的老师，很有气质很有学识。上课喜欢启发性的提问，鼓励大家思考说错乱说都不要紧，担心同学们跑两个校区加开了一节课┭┮﹏┭┮感动。期末一般是论文，基本不会点名，可翘但是不建议翘。"},{"发表时间":"2025-01-15 07:11:53","点赞减去点踩数量":0,"点赞量":0,"点踩量":0,"内容":"有幸上了在文化遗产导论上了老师的三次课，是我听得最认真的几次"},{"发表时间":"2025-04-18 03:28:35","点赞减去点踩数量":0,"点赞量":0,"点踩量":0,"内容":"第一次来査老师上评分！张老师温文尔雅，汉唐考古讲得非常优秀，干货满满，为人风趣。每次见面都会和同学们打招呼，下课后还会主动询问有没有不懂的点，期末就是一篇很开放的论文，事少课好人更棒！张老师我爱您！qwq"}],"gpa_info":[["博物馆经营","4.43","133","0.29"],["汉唐考古","4.45","106","0.37"]]},{"id":4206,"姓名":"王志坚","学院":"社会科学研究院","热度":5393,"评分人数":38,"评分":5.6759,"拼音":"wangzhijian","拼音缩写":"wzj","comments":[{"发表时间":"2018-05-09 16:24:21","点赞减去点踩数量":-10,"点赞量":4,"点踩量":14,"内容":"666"},{"发表时间":"2018-07-08 08:23:50","点赞减去点踩数量":-12,"点赞量":5,"点踩量":17,"内容":"能学到很多知识，老师认真又谦虚，更难得的是小班化教学。"},{"发表时间":"2018-07-15 08:17:33","点赞减去点踩数量":-10,"点赞量":4,"点踩量":14,"内容":"nan"},{"发表时间":"2019-05-10 14:25:27","点赞减去点踩数量":-8,"点赞量":19,"点踩量":27,"内容":"这门课在今年的通识改革中成了科技创新类的通选课，以下------------------课程安排：八次课+开卷考试，前六次课后每次会有一次老师自己出的几道题作为作业，题目不会很难并且很有意思；后两次课会将全班分成小组完成一道大题作为project-----------------------关于老师：王老师是演化博弈理论走在世界前沿的学者之一，但是为人很谦虚，而且很关心学生；-----------------------关于课程难度：这门课需要一些编程与数学基础，如MATLAB与线性代数，但是要求不高，我是大一下选的这门课，修完了C程与线代感觉基本够用。；--------------关于给分：给分大家可以自己看课程均绩，但是这门课真的是一门收获大到可以无视给分的课程，同时王老师的教学也注重对科研能力的培养，如果抱着“只谈学术，不问成绩”的心态去选是最好的。----------其他：如果想选一门水水的通识建议把选这门课的机会留给别人吧，当时我也是抱着试试看的心态选了这门课，第一节课时也有自己数学水平会不会不够，一门通识会不会占用自己太多时间的担忧，但是其实王老师会考虑到这些所以不必担心大胆去选并且坚持下去。现在看来这门课真的是我这一年在浙大上过的最有意思，质量最高，收获最大的一门课，如果你之前就对博弈论感兴趣，王老师会带你探究这个领域最前沿也最有意思的知识。"},{"发表时间":"2018-12-29 06:46:43","点赞减去点踩数量":-6,"点赞量":9,"点踩量":15,"内容":"修改一下之前的评论，王老师这门课之前是竺院下的课，现在改为通识必然要受正态分布的限制，希望同学们不要为了高绩点选这门课，\"只谈学术，不问成绩\""},{"发表时间":"2019-01-03 06:04:22","点赞减去点踩数量":-9,"点赞量":2,"点踩量":11,"内容":"nan"},{"发表时间":"2019-10-19 01:02:58","点赞减去点踩数量":-25,"点赞量":4,"点踩量":29,"内容":"老师超级好！听说还是竺院的班主任，很厉害，很谦虚。"},{"发表时间":"2019-03-02 08:41:25","点赞减去点踩数量":-9,"点赞量":5,"点踩量":14,"内容":"节奏慢，但能学到很多"},{"发表时间":"2019-03-05 01:17:44","点赞减去点踩数量":20,"点赞量":26,"点踩量":6,"内容":"我怀疑下面的好评是他找人刷的。不尊重同学，上课笑点奇怪，上过别的博弈论你就会发现他自己逻辑有些混乱，一会儿前面一会儿后面，也不能用很直观的话描述定义。拿几个简单的例题就想让我们融会贯通了，别的课的老师也不带这样教的。"},{"发表时间":"2019-03-07 07:29:55","点赞减去点踩数量":19,"点赞量":25,"点踩量":6,"内容":"”第一次作业没交的同学，建议全部退选本课程，及格已经来不及了”"},{"发表时间":"2019-03-31 12:43:01","点赞减去点踩数量":11,"点赞量":15,"点踩量":4,"内容":"今天做作业算是弄懂了，好好看看课程名吧，这门课讲的应该是实验科学。。。我一个伪码农学啥子实验科学。。。我为什么没退课???"},{"发表时间":"2019-03-27 12:07:20","点赞减去点踩数量":10,"点赞量":13,"点踩量":3,"内容":"打算让我们无师自通博弈论，随机过程，matlab等等？！！课上讲的什么狗屁。"},{"发表时间":"2019-05-05 15:40:41","点赞减去点踩数量":10,"点赞量":14,"点踩量":4,"内容":"其他的不说，表面上乐于交流，但是为什么问他问题总是有2/3推脱最近有什么事让你自己去搞懂或者答得文不对题呢？上课烂也就算了，既然课程内容这么硬核请别把时间花在吹牛皮上或者扯一些奇奇怪怪的比喻。看看其他老师的上课方式吧，既然拿着每个学生75元/学分的学费和从纳税款中抽调出的经费，教师的作用就应该是帮助、教导而不是宣泄自己奇奇怪怪的观点，满足自己的表达欲和被认可欲!"},{"发表时间":"2019-04-02 04:12:45","点赞减去点踩数量":8,"点赞量":11,"点踩量":3,"内容":"听他上课不如去看各种软件教程，课上讲又不讲清楚，之后又嫌我们做的差，建议这门课可以多加几个学分，这么耗时，还得去找他答疑，不多加学分好亏啊。选了这个通识真的是瞎了眼，果然这种课还是适合优秀的理工科竺院学子，还是不要开给我们菜鸡上了。"},{"发表时间":"2019-04-02 12:59:47","点赞减去点踩数量":10,"点赞量":14,"点踩量":4,"内容":"难受。"},{"发表时间":"2019-05-18 14:31:30","点赞减去点踩数量":17,"点赞量":22,"点踩量":5,"内容":"第一次课教室满座，退课后还剩19人，期末大作业按时上交15人。。。\\n\\n慎选，慎选"},{"发表时间":"2019-04-02 15:06:08","点赞减去点踩数量":12,"点赞量":14,"点踩量":2,"内容":"这还没大作业呢，我就已经原地爆炸了。选这课的各位你们后面一定会怀疑自己脑子进了水。"},{"发表时间":"2019-04-03 02:23:35","点赞减去点踩数量":9,"点赞量":14,"点踩量":5,"内容":"这个人自命不凡，迂腐尖酸，但上课逻辑混乱，喜欢发呆傻笑。建议还是不要开课了。"},{"发表时间":"2019-04-04 01:49:35","点赞减去点踩数量":-6,"点赞量":7,"点踩量":13,"内容":"说实话这个课确实比较硬核，然后老师学术能力很强，可能上课讲得比较慢，但是还是很重视学生接受程度的。课后作业需要自己多花力气，对数学基础能力和软件有一定的要求，但是老师也鼓励大家互帮互助，每次作业都会给我们一定的参考。同班的很多同学都很优秀，课程和作业结合还是可以学习到很多东西，优秀的同学也让我认识到自己还要好好努力，实话说，虽然老师要求相比其他水课严厉了很多，但是这半个学期我真的学习到了很多知识和技能，这点不可否认。本人因为答疑时间和其他课程安排冲突的原因没有去过答疑，但是课程也跟得上啊（就是每次作业都赶在ddl前交，有点心虚）"},{"发表时间":"2019-05-08 04:09:48","点赞减去点踩数量":2,"点赞量":2,"点踩量":0,"内容":"！！！\\n\\n"},{"发表时间":"2019-05-27 08:27:30","点赞减去点踩数量":18,"点赞量":19,"点踩量":1,"内容":"我看到评论区里有不少批评王志坚先生的，我认为这种论调太片面，甚至从评价系统存在的意义上来说，这样的评论是错误的。王先生给了学生许多东西，比如，关于情商的知识，让人提高情商的动力，尤其是当这个人以实际行动暗示你，你的前任和你分手不是为别的，就是为你情商低的时候。选了这门课之后，我才发现，原来生活中大大小小的事，甚至还有那些愚蠢的争吵，都是那么的亲切；遇到这个人之后，我才恍然大悟，我以前错怪了多少人呐！我得原谅他们，他们是那么的可爱。我才发现生活是那么美好，一草一木背后都有一个美妙的世界，所以，让我们拥抱生活，热爱生活，不要选这个人的课吧。"},{"发表时间":"2019-05-29 01:16:16","点赞减去点踩数量":-6,"点赞量":8,"点踩量":14,"内容":"课程初步成绩出来了，所以打个分。\\n\\n和成绩无关，首先，本人认为课程预备知识不多，只要学过常微分方程和线性代数就能较好地理解基础知识，编程像我之前只学过python程序设计（学得还不咋地），但是也能初步掌握使用本课程需要的一些软件（一共两个？），代码需要修改的地方老师上课也会直接把需要修改的地方和内容发在群里，再讲解一下。那些说老师讲的不够仔细的，讲的不好的，是要求大学老师和高中老师一样把知识都嚼碎了喂给学生吗？确实，如果想水的同学不必要选这个课，，这门通识课和评论里部分人想要的通识课不一样，他一点也不水。关于课程质量的问题，我个人认为大学生想要学习知识的话，也不应该全靠老师，被动学习的，老师课上虽没有讲到所有的细节，但是课后可答疑，也可自学，老师也鼓励同学之间进行一定的交流，按水课的方式上课当然会自觉跟不上。\\n\\n收获:之前学习的课程多为基础理论为主，应用偏少，学习了演化博弈与实验这门课之后才开始明了原来之前学习的常微分、代数知识是这样应用的，课程也迫使我提前学习了一些随机过程的知识，可以说给我打开了一扇新的大门。但是毕竟只是一门通识课，课程有一定的知识量，但很多细节在一个短学期无法学到。老师是一位较严格的老师，希望我们能完整地学习到一个完整的博弈论实验是怎么样的，我在上课之前还是有点害怕的，怕这个课太难我跟不上，但是最后看来我还是收获了许多。\\n\\n建议:最后大作业可以早一点开始，然后早点ddl，一直拖到夏学期开始几周还在做，主要也有我自己拖延的原因，ddl是第一生产力（笑哭），无论如何，谢谢老师，也谢谢一起上课的同学（抱拳）。"},{"发表时间":"2019-05-29 06:58:52","点赞减去点踩数量":9,"点赞量":11,"点踩量":2,"内容":"反驳夸这门课的同学，如果老师课上不讲实质性的东西，范围还很大，课后要你自己去学，这样算不是水课，收获很大，那zju怕是没有水课了，老师提高要求就完事了。我diss这门课的原因不是说作业很难，而是上课内容的问题，这老师上课真刷新了我对zju老师的看法，之前觉得讲课再差也不过念ppt，上这课你会有新的认识。––––––说不懂就问的，不是所有人都有时间，再者了大部分都去答疑?那侧面反应这老师课上没讲啥，如果愿意把学分多提提，安排一节课专门答疑倒差不多..."},{"发表时间":"2019-05-29 02:42:08","点赞减去点踩数量":-9,"点赞量":4,"点踩量":13,"内容":"每周两次答疑，这都是明示了，不懂就去问啊"},{"发表时间":"2019-05-30 16:17:04","点赞减去点踩数量":10,"点赞量":11,"点踩量":1,"内容":"王志坚先生情商为0？"},{"发表时间":"2019-06-12 06:11:04","点赞减去点踩数量":7,"点赞量":7,"点踩量":0,"内容":"不好意思，我兢兢业业学，作业认真做，然而仍然极低分，原因只是因为没什么原因。老师自己也说不出什么原因，只是因为需要正态。平时分不量化，完全靠他自己的感觉，想打多少打多少，呵呵"},{"发表时间":"2019-07-02 23:51:54","点赞减去点踩数量":5,"点赞量":5,"点踩量":0,"内容":"不是，要正态就正态吧，你把成绩在群里公示了出分又降档是什么鬼。"},{"发表时间":"2021-09-01 12:02:09","点赞减去点踩数量":0,"点赞量":0,"点踩量":0,"内容":"支持楼上全部好评，也支持楼上全部差评。"},{"发表时间":"2023-12-23 10:49:52","点赞减去点踩数量":1,"点赞量":1,"点踩量":0,"内容":"适合有一定数学基础且想浅浅了解一下博弈论的同学（有点微积分线代基础就行），课上讲的例子挺有趣，而且通俗易懂，期末是考试和大作业自己二选一。给分的话我是22年春选的这门课，班里一共不到十个人，也没像评论里说的正态啥的，最后4.5"},{"发表时间":"2024-04-09 10:33:06","点赞减去点踩数量":0,"点赞量":0,"点踩量":0,"内容":"哈哈哈"},{"发表时间":"2025-04-02 12:39:20","点赞减去点踩数量":0,"点赞量":0,"点踩量":0,"内容":"硬课不水，大一慎选。千万别信所谓的只需要一点点微积分线性代数就行（除非你根本不在意绩点）\\n\\n王老师人挺认真的，也比较和蔼，但是讲课可能不易理解，虽然老师讲课时也会注意大家的进度，但是其实课后还是需要花不少的时间。"}],"gpa_info":[["演化博弈理论与实验","3.98","24","0.55"]]},{"id":4208,"姓名":"李世阳","学院":"光华法学院","热度":13418,"评分人数":102,"评分":9.46266,"拼音":"lishiyang","拼音缩写":"lsy","comments":[{"发表时间":"2018-02-05 13:37:08","点赞减去点踩数量":1,"点赞量":2,"点踩量":1,"内容":"老师上课很认真，而且给分好好啊～"},{"发表时间":"2018-02-05 15:22:53","点赞减去点踩数量":4,"点赞量":4,"点踩量":0,"内容":"李博士上课超有意思，试题超强?给分超好！"},{"发表时间":"2018-02-05 15:38:25","点赞减去点踩数量":3,"点赞量":4,"点踩量":1,"内容":"上课不点名，期末开卷，考的都是上课讲过的理论、知识点。上课认真做笔记，期末会省很多时间复习。 最后，李博士的给分真的太好了吧！！"},{"发表时间":"2018-02-05 17:19:29","点赞减去点踩数量":3,"点赞量":4,"点踩量":1,"内容":"人好，课程有趣，给分好=李世阳老师刑总。"},{"发表时间":"2018-02-05 18:34:51","点赞减去点踩数量":7,"点赞量":10,"点踩量":3,"内容":"给分好到无法理解自己怎么能拿到这个绩点"},{"发表时间":"2018-02-06 01:24:47","点赞减去点踩数量":1,"点赞量":2,"点踩量":1,"内容":"老师给分超好啊，上课内容很丰富也很有趣，最好能带支录音笔方便整理笔记，考试开卷（虽然不知道以后还是不是这个形式）"},{"发表时间":"2018-02-07 07:27:48","点赞减去点踩数量":6,"点赞量":8,"点踩量":2,"内容":"给分超好超好，上课很有趣，会介绍很多种观点，每次都拿自己举例，同学们我现在嗑药了陷入了一种很嗨的状态hhh"},{"发表时间":"2018-02-11 06:29:48","点赞减去点踩数量":31,"点赞量":35,"点踩量":4,"内容":"一位被法学耽误的编剧"},{"发表时间":"2018-02-19 16:02:57","点赞减去点踩数量":1,"点赞量":2,"点踩量":1,"内容":"还不错"},{"发表时间":"2018-03-07 00:14:50","点赞减去点踩数量":3,"点赞量":5,"点踩量":2,"内容":"给分超好"},{"发表时间":"2018-03-10 11:30:37","点赞减去点踩数量":3,"点赞量":6,"点踩量":3,"内容":"老师人很好呀，给分很nice，讲课也很有趣，就是少了一点体系性。讲课不好做笔记，很跳跃。"},{"发表时间":"2018-03-14 01:31:32","点赞减去点踩数量":10,"点赞量":13,"点踩量":3,"内容":"李博士其实体系很清楚，就是每次都会因为我们不回应觉得我们没听懂然后翻来覆去换方法讲一个概念很多遍，给分超级好！！！！顺便真的好想念他为什么不来上刑分?"},{"发表时间":"2018-03-18 14:27:33","点赞减去点踩数量":5,"点赞量":6,"点踩量":1,"内容":"真的太太太喜欢李博士了！！如果刑分还是他来上该多好啊！！"},{"发表时间":"2018-06-27 03:17:15","点赞减去点踩数量":3,"点赞量":4,"点踩量":1,"内容":"老师很可爱！"},{"发表时间":"2018-11-29 03:03:59","点赞减去点踩数量":1,"点赞量":1,"点踩量":0,"内容":"请问比较刑法是论文还是考试呢"},{"发表时间":"2018-12-19 01:06:52","点赞减去点踩数量":-32,"点赞量":10,"点踩量":42,"内容":"我觉得起码一个人要懂得尊重他人吧，李博士每节课重复一遍类似上课时间太少（本学期李博士教授半学期的刑分）你们没有接受先进刑法教育的言论，至少在我看来是对前一位刑法老师的不尊重，更何况我觉得前一位老师教得很好。李博士滔滔不绝地讲着他曾经接受到的刑法理论同时主观觉得我们从来不曾接触过这些是总论教学的失败，但事实上在总论的教学中已有涉及只是我们无法像他一样口若悬河。真的受够了某些留学回来的老师每节课不接地气“掉书袋”般地搬弄自己的学问且不尊重他人。"},{"发表时间":"2019-02-01 05:39:32","点赞减去点踩数量":9,"点赞量":11,"点踩量":2,"内容":"老师讲的超好"},{"发表时间":"2019-05-06 10:59:28","点赞减去点踩数量":-22,"点赞量":11,"点踩量":33,"内容":"我觉得起码一个人要懂得尊重他人吧，李博士每节课重复一遍类似上课时间太少（本学期李博士教授半学期的刑分）你们没有接受先进刑法教育的言论，至少在我看来是对前一位刑法老师的不尊重，更何况我觉得前一位老师教得很好。李博士滔滔不绝地讲着他曾经接受到的刑法理论同时主观觉得我们从来不曾接触过这些是总论教学的失败，但事实上在总论的教学中已有涉及只是我们无法像他一样口若悬河。真的受够了某些留学回来的老师每节课不接地气“掉书袋”般地搬弄自己的学问且不尊重他人。"},{"发表时间":"2019-03-04 11:30:46","点赞减去点踩数量":6,"点赞量":6,"点踩量":0,"内容":"好，喜欢！"},{"发表时间":"2019-04-15 06:06:17","点赞减去点踩数量":5,"点赞量":7,"点踩量":2,"内容":"赞赞赞"},{"发表时间":"2019-04-29 03:28:06","点赞减去点踩数量":7,"点赞量":7,"点踩量":0,"内容":"超喜欢李老师，刑法深入浅出，笔芯！"},{"发表时间":"2019-07-04 15:07:27","点赞减去点踩数量":72,"点赞量":89,"点踩量":17,"内容":"大二有幸得上李世阳老师的刑法总论，大三重回刑事案例研习的课堂，李老师开口讲课的那一刻，我险些没有控制住自己的眼泪，我已经太久太久太久没有听到这样的讲课了！到了山上的这半年多里，曾让我一度怀疑自己，怀疑自己的学习状态和学习态度—— 一台复读机？一百多台复读机？精彩的个人表演？水分十足的分数？我们迎合着老师的自我感动？更有甚者语出惊人，让学生们不得不质疑其师德人品，有时我也会恍惚间以为自己在上大一的通识课……这样说或许是大不敬，但我还是忍不住想问一问，借用一位同学的话，到底是一些老师们放弃了假装在教学，还是我真正放弃了学习…\\n\\n    我们学院有很多优秀的年轻老师，陆帅，程宝，李博士，春燕女神，诚然跟谷神，章老师这样德高望重的前辈们相比，他们的讲课还有一些不足，或许没有那么凝练老道，对课程时间安排的掌握不够精准，但是相比于一些事业编制下得过且过的老员工们，他们的课堂是实实在在地能让你感受到一种活力，一种学术的生命力，让你得以窥见法学这个庞大的知识体系深沉又磅礴的魅力，从物权，债法，行政法，到合同法，刑法，每一堂课都有同学早早来占座，每一堂课大家都聚精会神地听课，思考，对法学的感情是在一点一滴知识的积累，框架的搭建，思维的培养中渐渐发酵，是在日复一日的求学与教学的过程中越发深刻。\\n\\n    能再次坐在李博士的课堂里，我满怀感激也觉得难受，我只希望学弟学妹们千万千万要珍惜紫金港这些基础课程的学习，我们要庆幸，起码我们有最好的启蒙老师，让你在往后的求学生涯中，不至于成为被“误”的子弟…\\n\\n    为什么学习法律？为什么学习法律？不管当初为何选择它，在成为法学生之后，我们就需要承担起这份责任——不管你今后遭遇了怎样的“教诲”，法律人的信仰不可灭，作为健全的法律人的人格不可侵犯——因为我们是什么样，中国法学的未来就是什么样。"},{"发表时间":"2019-05-06 10:56:03","点赞减去点踩数量":-10,"点赞量":7,"点踩量":17,"内容":"我觉得起码一个人要懂得尊重他人吧，李博士每节课重复一遍类似上课时间太少（本学期李博士教授半学期的刑分）你们没有接受先进刑法教育的言论，至少在我看来是对前一位刑法老师的不尊重，更何况我觉得前一位老师教得很好。李博士滔滔不绝地讲着他曾经接受到的刑法理论同时主观觉得我们从来不曾接触过这些是总论教学的失败，但事实上在总论的教学中已有涉及只是我们无法像他一样口若悬河。真的受够了某些留学回来的老师每节课不接地气“掉书袋”般地搬弄自己的学问且不尊重他人。"},{"发表时间":"2019-06-12 09:49:24","点赞减去点踩数量":25,"点赞量":26,"点踩量":1,"内容":"李博士对于“民法帝国主义”的???让人记忆犹新。说起来，确实对李博士问心有愧啊。喜欢zcgg也喜欢李博士，我很庆幸初入法门就遇到了这么好的引路人。好了我合上民法去学习刑法了～"},{"发表时间":"2019-05-27 05:36:44","点赞减去点踩数量":-11,"点赞量":5,"点踩量":16,"内容":"能不能别重复讲东西了\\n\\n背个课吧"},{"发表时间":"2019-06-03 05:36:51","点赞减去点踩数量":-11,"点赞量":4,"点踩量":15,"内容":"求求老师别翻过来覆过去讲东西了"},{"发表时间":"2019-07-01 05:54:26","点赞减去点踩数量":4,"点赞量":4,"点踩量":0,"内容":"李博士啥都好，就是别考试周还没过完就发答案?"},{"发表时间":"2019-07-02 06:16:44","点赞减去点踩数量":-3,"点赞量":1,"点踩量":4,"内容":"上课真的欢乐，也干货满满，上课一定要好好记笔记。ppt 会比较复杂，期末考好好看平时笔记还有ppt 上一些理论和解释之类的，一定要看往年的卷子和答案，考点不会差太大，但是重在分析（李博士说结论和他完全一样是不可能的，所以不重视结论，但也别太扯），找全案情基本考点按答题套路来   上4了"},{"发表时间":"2019-07-02 09:36:45","点赞减去点踩数量":5,"点赞量":5,"点踩量":0,"内容":"大爱李博士！！！上课超级欢乐！虽然上课内容和ppt有点不一样，然后刑法体系真的超级庞大，但是李博士会把刑法一点一点抽丝剥茧讲给你看，好好记笔记，期末考没有标准答案，主要看重思路分析，一定要看往年卷子！！！考点重复率很高！！！"},{"发表时间":"2019-07-04 17:30:12","点赞减去点踩数量":2,"点赞量":2,"点踩量":0,"内容":"谢老师不挂之恩"},{"发表时间":"2019-07-04 17:32:17","点赞减去点踩数量":0,"点赞量":1,"点踩量":1,"内容":"刚出分4.2 我爱李博士！\\n\\n"},{"发表时间":"2019-07-04 17:53:48","点赞减去点踩数量":3,"点赞量":3,"点踩量":0,"内容":"考试的时候没有分析完人物，只分析了三个人，最后李博士给了3.9，感谢李博士!给分超好!"},{"发表时间":"2019-07-04 22:27:23","点赞减去点踩数量":1,"点赞量":6,"点踩量":5,"内容":"4.8!\\n\\n希望能选上李博士的刑分~"},{"发表时间":"2019-07-04 22:34:33","点赞减去点踩数量":1,"点赞量":2,"点踩量":1,"内容":"很好啊啊啊啊"},{"发表时间":"2019-07-04 23:45:31","点赞减去点踩数量":8,"点赞量":8,"点踩量":0,"内容":"虽然只有3.6，但是这并不妨碍我继续爱李老师！！！情怀与知识面前，只能说我是不够努力了！明年刑分再接再厉~"},{"发表时间":"2019-07-05 23:28:10","点赞减去点踩数量":0,"点赞量":1,"点踩量":1,"内容":"老师真的认真博学，事少给分好，希望下学期刑分再接再厉，共同努力！"},{"发表时间":"2019-07-10 00:32:06","点赞减去点踩数量":1,"点赞量":2,"点踩量":1,"内容":"李博士是刑法的启蒙老师。超级认真，认真给我吗梳理每一个知识点，虽然刑总内容很多没上完，但把刑总里最重要的部分都讲得很透彻。大爱李博士！"},{"发表时间":"2019-07-11 03:34:05","点赞减去点踩数量":2,"点赞量":3,"点踩量":1,"内容":"大爱李博士!不解释!"},{"发表时间":"2020-02-16 05:55:31","点赞减去点踩数量":8,"点赞量":14,"点踩量":6,"内容":"老师好是好，但是这给分真的烂了（跟隔壁ylf相比），好好学了一学期2.7我真的佛了....而且明明在群里说了对分数有质疑的可以联系他，加了四五遍好友都不通过...老师你说话像放屁诶"},{"发表时间":"2020-07-22 16:33:52","点赞减去点踩数量":4,"点赞量":6,"点踩量":2,"内容":"刑法总论。老师学识人品俱佳。但打分方式稍显随意。相比隔壁班成绩也低了不少。"},{"发表时间":"2021-01-27 07:08:00","点赞减去点踩数量":2,"点赞量":3,"点踩量":1,"内容":"。。。"},{"发表时间":"2021-03-03 16:00:33","点赞减去点踩数量":1,"点赞量":4,"点踩量":3,"内容":"我从未杀过这么多人"},{"发表时间":"2021-03-04 04:31:03","点赞减去点踩数量":9,"点赞量":14,"点踩量":5,"内容":"李世阳老师真的非常仁慈了。既然老师都说了“我这次不杀你们”，相信老师一定尽力不让我们挂科了。不知道其他人怎么样，就我所知而言，两个4.2，一个3.9，其他人也都70+。\\n\\n确实相比叶良芳班，成绩会有一定差距；但既然不同出卷，成绩有差异就是难免的；大家都知道李博士刑总给分比较一般，还是选了他的刑分，被害人自陷风险也不能全怪老师。在我看来，卷面分低的主要原因在李华老师的40分选择题和纯闭卷的背诵考试形式，结果却是李世阳老师替她挨骂。卷面分数成了那个样子，老师想捞都很难；所谓开根号再乘十的方法，老师原话“系统里不存在这种算法”，起码法学院是如此。p.s.如果去看以前的访谈，会发现李世阳老师之前是很反对闭卷考试的形式的，不知道近两年为什么态度有如此大的转变。\\n\\n就讲课而言，做纵向的比较，老师的分论确实不如总论讲得好，或许是不再有手写提纲的原因，感觉凌乱了好多；又受到课时限制，很多知识点不能展开，老师的学术观点也不太好理解；还因为有事找徐万龙老师代课了两次。做横向的比较，确实不如车浩、柏浪涛和罗翔等学术或法考大牛，但远胜李华老师了，在学院里肯定也是排名相当靠前的，至少堪当九分的评价。平时抄了人身财产罪的法条、一次小作业、几次随堂的鉴定式案例分析，事情也不算很多。虽然朋友圈和朵朵铺天盖地，还是希望学弟学妹们敢选李世阳老师的课。\\n\\n以前不太明白为什么有时老师上着课突然闹脾气，突然说“你们不要所有时间都去学民法，也学一学刑法”，现在稍微能理解一点了；平心而论，我对刑法的投入和努力确实远远不够，老师的批评是中肯的。我无心再上刑案，抛开法考和考研，刑法之路到此已告一段落，感谢李世阳老师的启蒙和一路陪伴！"},{"发表时间":"2021-03-04 12:48:09","点赞减去点踩数量":3,"点赞量":5,"点踩量":2,"内容":"感觉至少我所见的查老师评论，部分人评判一个老师好、一个课程班好多以“事少课水给分好”为要旨。但上过李老师刑总课的难道不能体会到老师的良苦用心吗？老师在春夏学期网课的时候手写笔记，每次几乎到一两点发送出来（虽然这个可能也有老师自己在准备出版的原因？），老师大可不必这样做，甚至也可以打字，但无疑这样的手写笔记在我们（至少我自己）的刑法学习道路上起到了非常大的帮助作用。虽然这学期上老师的刑分，明显也感觉到课堂上的氛围似乎不如春夏学期的刑总那样好，甚至有时可能有些沉闷（其实也多数是因为老师提问，同学们回答积极性不高的缘故），但无疑老师的教学方式和教学风格都很有其特色，不是念PPT，不是对各种案例简单地蜻蜓点水，也不是单纯掉书袋，刑法那么多理论和学派，老师能够纵横捭阖地引申讲来而且厘清，已经很难能可贵了。\\n\\n总而言之，非常庆幸能够在最初接触刑法时遇到李老师。平时和他没有什么交流，对刑法目前也没有很大的偏好，但对于这样的我来说老师也已经很好了。后来者请不要被一面之词蒙蔽……"},{"发表时间":"2022-03-03 02:28:37","点赞减去点踩数量":0,"点赞量":2,"点踩量":2,"内容":"老师上课思路真的好清楚！"},{"发表时间":"2022-03-16 03:44:12","点赞减去点踩数量":3,"点赞量":7,"点踩量":4,"内容":"听不懂。。。"},{"发表时间":"2022-03-28 15:21:20","点赞减去点踩数量":1,"点赞量":3,"点踩量":2,"内容":"能这么用心和同学交流这么用心备课这么用心给同学找资料的还有谁！！"},{"发表时间":"2022-04-11 14:35:48","点赞减去点踩数量":20,"点赞量":23,"点踩量":3,"内容":"老师很好呜呜呜\\n\\n只是在鼓励同学们认真做作业的同时，能不能扼制一下鹅颈哇…\\n\\n完全不觉得五千字的作业写一万七是在体现对一门课的重视，即使是，又是不是过度了呢\\n\\n这样对在相对合理字数内认真完成作业的同学打击很大呜呜"},{"发表时间":"2022-05-27 09:29:54","点赞减去点踩数量":4,"点赞量":6,"点踩量":2,"内容":"李老师真的很不错，真的设身处地为学生考虑。"},{"发表时间":"2022-06-06 15:16:21","点赞减去点踩数量":7,"点赞量":9,"点踩量":2,"内容":"闭卷的形式对我构成了具体紧迫的风险！但还是给老师打9分，李博士萌萌哒"},{"发表时间":"2022-06-08 00:47:02","点赞减去点踩数量":-34,"点赞量":10,"点踩量":44,"内容":"sb 情绪不稳定 疯子"},{"发表时间":"2022-06-09 16:33:35","点赞减去点踩数量":17,"点赞量":21,"点踩量":4,"内容":"李世阳老师是目前唯一一位让我感受到了对法律的热情的法学院老师。"},{"发表时间":"2022-06-11 09:24:52","点赞减去点踩数量":-20,"点赞量":10,"点踩量":30,"内容":"别的老师都开卷，你闭卷，一大半的复习时间都被一门刑法占用掉了。你认为绩点不重要，拿学生的绩点当儿戏，我不认可。绩杀李世阳绩杀绩杀绩杀"},{"发表时间":"2022-06-13 13:48:54","点赞减去点踩数量":22,"点赞量":23,"点踩量":1,"内容":"刑总，大一下学期最喜欢的课。大家一定要好好学。李老师对刑法真的有很深厚的热爱和非常深厚的钻研。另外我认为按时到课是学生应该做的事情。闭卷实际上也没有太难为学生，都是应该会的。有没有一种可能，学习，本来就不应是为了绩点。"},{"发表时间":"2022-06-16 00:03:12","点赞减去点踩数量":16,"点赞量":27,"点踩量":11,"内容":"怎么着要求到课期末闭卷考试还不行了？平常不好好背天天睡大觉打游戏没见你怎么反思自己！就不应该惯你那些臭毛病！你到这来是学习的，不是干别的来的，学习就是你的天职！"},{"发表时间":"2022-06-17 09:05:59","点赞减去点踩数量":-5,"点赞量":10,"点踩量":15,"内容":"很喜欢阴阳怪气的一个人"},{"发表时间":"2022-07-06 13:48:21","点赞减去点踩数量":4,"点赞量":6,"点踩量":2,"内容":"高分高评，低分低评，不喜欢就信手捏来一顿骂，做个善人吧"},{"发表时间":"2022-10-25 10:16:00","点赞减去点踩数量":20,"点赞量":24,"点踩量":4,"内容":"认真听了李博士一学期的刑总，最后成绩很一般，但这是我第一次在大学中有一门课完全不在乎成绩会怎么样。期末一遍一遍梳理上课笔记的时候，我知道刑法的大概框架我搭起来了，这就足够了。而这也让我在这学期的刑分学习里依然受益匪浅。\\n\\n回想学习刑总的半年，每个7:55等着李博士抱着1L装椰子水走进教室的时刻、窝在床上看老师推荐的一部部电影的时刻、一点点敲案例分析和观后感的时刻、翻来覆去听共犯论一节的智云的时刻……我觉得这会是我法学学习生涯里最初、也最珍贵和快乐的记忆。李博士是第一个让我领略到法学体系的奇妙和庞大的老师，他最好地教会了我法律人应当有所敬畏。\\n\\n“事后来看，一切都是必然的。但从事前来看，一切却是偶然的。\\n\\n我希望同学们要记住，刑法总论的学习它不限于是对刑法本身的学习，更多的其实是一个法律人的思维的训练。所以我特别希望同学们能把刑法总论扎实地学好，并且把它扩散到其他法学学科的学习。\\n\\n法律人的素养是最重要的。\\n\\n所以从这个意义上而言，你哪怕去牺牲一点绩点，让你自己平时有更多的收获，去看更多的书，我觉得这都是值得的。然后呢，在学有余力的情况之下，最好去学一门外语，在能旅行的情况下，要多去旅行。好，下课。”"},{"发表时间":"2023-01-04 13:56:46","点赞减去点踩数量":2,"点赞量":4,"点踩量":2,"内容":"很棒好老师"},{"发表时间":"2023-03-14 01:22:24","点赞减去点踩数量":1,"点赞量":4,"点踩量":3,"内容":"一位真正在准备课堂内容，给学生讲课的老师；一位切实给予学生获得感的老师。"},{"发表时间":"2023-05-13 17:38:12","点赞减去点踩数量":1,"点赞量":3,"点踩量":2,"内容":"超好的老师"},{"发表时间":"2023-06-28 05:04:12","点赞减去点踩数量":5,"点赞量":16,"点踩量":11,"内容":"跟xwl相比真的差很多，讲课给人带来一种疲惫和混乱感，虽然很努力，但是讲课什么的还是很一般"},{"发表时间":"2023-05-27 02:49:17","点赞减去点踩数量":15,"点赞量":19,"点踩量":4,"内容":"为什么我觉得李老师的刑总非常混乱，感觉有点东拉西扯，想到哪里讲哪里，感觉体系性不是那么强？而且感觉一些主要内容都没有写在PPT上，纯靠嘴讲？？到现在感觉课上不完了。。"},{"发表时间":"2023-06-14 03:39:25","点赞减去点踩数量":6,"点赞量":14,"点踩量":8,"内容":"讲课很混乱，有的知识点自己也讲不清楚，ppt也不是很清晰，还是推荐xwl"},{"发表时间":"2023-06-27 15:22:15","点赞减去点踩数量":1,"点赞量":2,"点踩量":1,"内容":"考试前求放过，李博士很厉害，但是我就是听不懂，啊啊啊啊啊"},{"发表时间":"2023-06-28 02:54:07","点赞减去点踩数量":4,"点赞量":6,"点踩量":2,"内容":"非常好的老师！！其实我之前上课的时候也会觉得有点混乱，但后来全部上完梳理的时候觉得其实是非常有条理的！三阶层很清晰，老师会在重点的地方扩充一些知识。如果自己在课后多花一些时间整理会觉得收获非常大！"},{"发表时间":"2023-08-08 04:57:38","点赞减去点踩数量":12,"点赞量":13,"点踩量":1,"内容":"老师挺好的 但是成绩难以置信地低 心碎了 感觉自己写的差不多啊"},{"发表时间":"2023-08-09 02:47:46","点赞减去点踩数量":-6,"点赞量":2,"点踩量":8,"内容":"挺好的，讲的很有深度，也调分了，改的松+卷面分加了5分这样，所以给分也在变好ing"},{"发表时间":"2023-12-15 17:24:32","点赞减去点踩数量":0,"点赞量":3,"点踩量":3,"内容":"底层逻辑讲得很清晰，个人觉得比xwl好很多"},{"发表时间":"2023-12-25 09:23:05","点赞减去点踩数量":1,"点赞量":4,"点踩量":3,"内容":"给分巨烂。。目前最低"},{"发表时间":"2024-03-20 16:09:10","点赞减去点踩数量":0,"点赞量":3,"点踩量":3,"内容":"很难评"},{"发表时间":"2024-03-21 06:46:42","点赞减去点踩数量":2,"点赞量":5,"点踩量":3,"内容":"给分巨烂无比，跟所有人欠他一样，辛辛苦苦花这么多时间写了这么多就这点分数，也不知道李博士到底多高水平呵呵呵"},{"发表时间":"2024-06-05 14:05:26","点赞减去点踩数量":1,"点赞量":5,"点踩量":4,"内容":"年少无知刑法总论选了李老师，但是肉眼可见老师上课时的状态并不好，可能是因为同时也在写书比较累的原因。上课总是很疲惫，最后也没有讲完，上课讲的很慢很拖沓，常常前面讲了一大段，后面又开始重复地讲。ppt跟口述内容相差很大，上课的思路很发散，课下整理笔记很困难。\\n\\n考试内容考的还是比较常规，但是给分很差，据我所知很多人都获得了很低的分数。\\n\\n谷神说他年轻的时候听付老师的课一下子激起了对民法学的兴趣，希望老师能认真对待课堂，为之后的法律人点亮对刑法的兴趣吧。"},{"发表时间":"2024-06-25 15:12:58","点赞减去点踩数量":1,"点赞量":3,"点踩量":2,"内容":"乐，看评价挺好的，但也只是评价吧"},{"发表时间":"2024-06-29 14:08:43","点赞减去点踩数量":0,"点赞量":3,"点踩量":3,"内容":"老师讲课蛮有趣的！看得出来老师花了很大的力气来上这门课，课上有很多理论拓展和案例讲解。不过比较可惜的是老师后面不开课了（他说不开课了的时候脸上浮现出社畜的疲惫感。。。）\\n\\n期末考完之后本来满绝望的，但是被老师表扬和鼓励了真的特别特别感动！\\n\\n总之是入股不亏的好老师！"},{"发表时间":"2024-07-01 17:11:33","点赞减去点踩数量":4,"点赞量":5,"点踩量":1,"内容":"给老师打10分，闭卷考考前背得确实有点点崩溃，但出的题目都是上课强调过的，不偏，好好准备都能够答上来。最后班级的优秀率远超出学校规定但是老师说他“拒绝修改”，谁懂，我真的感动落泪🥹虽然上课的时候总是会说“你们肯定不回去复习”“知道你们肯定没提前看过ppt”，但是老师真的有在努力想办法把我们教会，三阶层的框架给的特别清晰，闭卷的形式也确实督促我们再把知识系统地复习了一边，这学期学到很多，最后也拿到了很满意的绩点，特别感谢老师～"},{"发表时间":"2024-07-01 22:26:30","点赞减去点踩数量":1,"点赞量":2,"点踩量":1,"内容":"阳阳老师真的好好~😭😭"},{"发表时间":"2024-07-03 03:58:54","点赞减去点踩数量":-6,"点赞量":7,"点踩量":13,"内容":"没去过一次课堂 最后4.5 满分不解释啊"},{"发表时间":"2024-07-03 08:03:23","点赞减去点踩数量":1,"点赞量":2,"点踩量":1,"内容":"今年给分感觉比去年好了不少，对刑法有兴趣的请一定要认真学，虽然平时到教室听课挺痛苦的，但是好好学真的有收获（不局限于绩点"},{"发表时间":"2024-07-18 03:07:12","点赞减去点踩数量":0,"点赞量":1,"点踩量":1,"内容":"9分老师，授课和给分都很好"},{"发表时间":"2024-07-23 09:36:21","点赞减去点踩数量":2,"点赞量":3,"点踩量":1,"内容":"虽然卡机，但是爱你"},{"发表时间":"2024-09-07 06:34:30","点赞减去点踩数量":3,"点赞量":3,"点踩量":0,"内容":"李博士真的特别好，给人一种学者的风范。虽然李博士可能平时比较严肃，但其实感觉内心还是很可爱的哈哈哈哈。解答问题都很详细有耐心，讲课刚开始可能会有一点不适应，但是如果认真听讲的话真的会发现李博士的内在思路还是很清晰的。期末出分比隔壁快很多哈哈哈哈，出成绩前还会私信报喜好可爱"},{"发表时间":"2024-09-09 07:49:45","点赞减去点踩数量":19,"点赞量":19,"点踩量":0,"内容":"本来觉得一般的，上了gyd的刑法分论之后，深感牵李世阳博士一个满分💯"},{"发表时间":"2024-11-07 13:11:12","点赞减去点踩数量":8,"点赞量":8,"点踩量":0,"内容":"你怎么能不讲分论呢？这怎么能允许呢？再不来讲分论就把你浙刑法所炸了"},{"发表时间":"2025-02-25 02:12:36","点赞减去点踩数量":3,"点赞量":3,"点踩量":0,"内容":"人好好啊啊啊啊啊 补选刑案失败了 给他说了一声 他就说他扩容了💕💕💕💕💕"}],"gpa_info":[["刑事案例研习","4.44","244","0.56"],["刑法分论","3.39","88","0.56"],["刑法总论","3.76","216","0.86"]]},{"id":4209,"姓名":"寺内伸介","学院":"外国语言文化与国际交流学院","热度":1550,"评分人数":12,"评分":7.35118,"拼音":"sineishenjie","拼音缩写":"snsj","comments":[{"发表时间":"2018-11-28 06:45:59","点赞减去点踩数量":-1,"点赞量":4,"点踩量":5,"内容":"最喜欢寺寺了！！人超好！懂超多！学历高！有素养！"},{"发表时间":"2019-01-19 16:32:00","点赞减去点踩数量":-6,"点赞量":9,"点踩量":15,"内容":"上课挺划的"},{"发表时间":"2019-01-21 06:26:16","点赞减去点踩数量":2,"点赞量":8,"点踩量":6,"内容":"很有趣 可爱的老师"},{"发表时间":"2019-01-23 13:02:13","点赞减去点踩数量":-8,"点赞量":9,"点踩量":17,"内容":"真的很混"},{"发表时间":"2019-07-03 06:30:48","点赞减去点踩数量":8,"点赞量":13,"点踩量":5,"内容":"寺内先生超好 温柔 和蔼"},{"发表时间":"2020-11-21 06:05:23","点赞减去点踩数量":8,"点赞量":13,"点踩量":5,"内容":"僕は金持ちだ！"},{"发表时间":"2021-11-02 09:02:53","点赞减去点踩数量":-3,"点赞量":2,"点踩量":5,"内容":"好老师1！"},{"发表时间":"2022-06-03 13:35:32","点赞减去点踩数量":-3,"点赞量":5,"点踩量":8,"内容":"君たち貧乏だ、誰も興味なさそう、なんて君たち、誰もぜんぜん反応してくれない，寺内超有意思了，胖胖憨憨可可爱爱！"},{"发表时间":"2022-12-06 02:45:53","点赞减去点踩数量":2,"点赞量":6,"点踩量":4,"内容":"很水很摆，不过是唯一的外教所以大家也没得挑~"}],"gpa_info":[["中日文化交流史","4.26","16","0.79"],["中级日语Ⅰ","4.03","71","0.83"],["中级日语Ⅱ","3.78","45","0.93"],["日本文学","4.60","17","0.61"],["日本文学史","3.94","7","0.66"],["日本语言与社会文化","4.05","28","0.60"],["日语写作","4.29","29","0.57"],["日语演讲与辩论","4.29","49","0.51"],["日语阅读与写作","4.50","21","0.43"],["综合日语Ⅰ","3.81","48","1.03"],["综合日语Ⅱ","3.87","50","0.87"],["西方文艺批评理论入门","4.60","9","0.21"],["高级日语","4.39","72","0.52"]]},{"id":4210,"姓名":"崔浩","学院":"马克思主义学院","热度":145,"评分人数":0,"评分":0.0,"拼音":"cuihao","拼音缩写":"ch","comments":[],"gpa_info":[["毛泽东思想和中国特色社会主义理论体系概论","3.87","500+","0.51"]]},{"id":4212,"姓名":"马婕","学院":"化学工程与生物工程学院","热度":1684,"评分人数":1,"评分":0.0,"拼音":"majie","拼音缩写":"mj","comments":[{"发表时间":"2023-07-05 02:42:03","点赞减去点踩数量":-1,"点赞量":1,"点踩量":2,"内容":"给分特别好！！是化工学院辅导员开得职规，一年好像才一节，特别幸运地选上了，除了期末大作业以外没有课后任务，课上也真的能听到有用的知识，会邀请优秀学长姐来讲，各个专业，真的会有启发！"}],"gpa_info":[["军训","4.56","113","0.28"],["思想道德与法治","4.54","139","0.29"],["职业生涯规划","4.47","266","0.42"],["职业生涯规划A","4.12","59","0.62"]]},{"id":4215,"姓名":"王万成","学院":"海洋学院","热度":3655,"评分人数":81,"评分":2.25121,"拼音":"wangwancheng","拼音缩写":"wwc","comments":[{"发表时间":"2018-08-26 23:38:18","点赞减去点踩数量":3,"点赞量":5,"点踩量":2,"内容":"绩杀，"},{"发表时间":"2018-12-27 16:24:36","点赞减去点踩数量":-6,"点赞量":2,"点踩量":8,"内容":"老师超级好的，每次都会和我们讨论一些东西，而且观点都很新的。对人也很和蔼，非常好，非常好"},{"发表时间":"2019-06-02 11:13:06","点赞减去点踩数量":0,"点赞量":2,"点踩量":2,"内容":"挺好的，在他课上作业补了挺多"},{"发表时间":"2019-06-14 03:48:35","点赞减去点踩数量":1,"点赞量":4,"点踩量":3,"内容":"辣鸡老师"},{"发表时间":"2019-06-28 16:18:09","点赞减去点踩数量":5,"点赞量":7,"点踩量":2,"内容":"为什么没有0分"},{"发表时间":"2019-06-29 18:38:55","点赞减去点踩数量":-3,"点赞量":1,"点踩量":4,"内容":"点了一次到，还能补签，海星"},{"发表时间":"2019-07-03 08:13:21","点赞减去点踩数量":1,"点赞量":3,"点踩量":2,"内容":"..."},{"发表时间":"2019-07-05 00:04:08","点赞减去点踩数量":-12,"点赞量":7,"点踩量":19,"内容":"考前刷课后选择题，附录时事政治扫一眼，单元主题要有印象。王老师是一个有思想的老师。绩点4.5！！！"},{"发表时间":"2019-07-05 01:04:13","点赞减去点踩数量":-6,"点赞量":3,"点踩量":9,"内容":"刚开始看到均绩二点几对自己很担心...没想到老师给分太好了吧！事少分高的典型了。平常没有论文，不用学习强国打卡，只需要点名和做一次小组展示。"},{"发表时间":"2019-07-06 02:25:06","点赞减去点踩数量":0,"点赞量":5,"点踩量":5,"内容":"看到自己的绩点感觉老师为了拯救海院均绩已经尽力了……事情少，两个长学期一次小组展示，发言也没什么鹅颈，认真写了卷面给分也很好。"},{"发表时间":"2019-08-06 06:10:20","点赞减去点踩数量":-4,"点赞量":0,"点踩量":4,"内容":"老师挺和蔼的！"},{"发表时间":"2019-11-17 13:35:31","点赞减去点踩数量":-3,"点赞量":2,"点踩量":5,"内容":"挺好的老师！\\n\\n"},{"发表时间":"2020-02-27 11:18:39","点赞减去点踩数量":-6,"点赞量":2,"点踩量":8,"内容":"形策老师里面事情最少的了吧……一年一共一个展示，不用听课，只要每次课在就行，最后考试好好写给分不会差的"},{"发表时间":"2020-09-14 08:28:01","点赞减去点踩数量":1,"点赞量":4,"点踩量":3,"内容":"垃圾老师，乱给分的，带的班恶竞严重"},{"发表时间":"2020-09-14 08:29:48","点赞减去点踩数量":2,"点赞量":5,"点踩量":3,"内容":"鹅颈极其严重 给分惊人 就这？还6分多的老师？出成绩第一件事居然是解散群聊？"},{"发表时间":"2021-07-03 13:50:07","点赞减去点踩数量":11,"点赞量":14,"点踩量":3,"内容":"我实在是无语了，作业什么的都认真写了，期末考试也好好复习了，考试时候尽量把字写的很漂亮，答案也是尽量完整，最后2.7?！考完试就把群解散了也是nb，淦！"},{"发表时间":"2021-07-05 14:33:58","点赞减去点踩数量":3,"点赞量":5,"点踩量":2,"内容":"浅色红一只，还不如中学历史老师"},{"发表时间":"2021-07-06 06:02:51","点赞减去点踩数量":4,"点赞量":7,"点踩量":3,"内容":"这个老师讲课其实倒是挺好，第一次课给我们每人各送了一本竺可桢演讲选录，而且老师上课之余也会给我们提出许多很有用的建议，课堂开始会给我们介绍国内外时事，就课堂本身来说还是不错的\\n\\n作业只有两次，算是很少的了\\n\\n但是...这老师乱给分也是真的，身边好多人都没上3，估计是早料到会被学生骂了，刚考完就解散了钉钉群，就nm离谱...\\n\\n就凭这点，4分，不能再多了\\n\\n最后关于点名，老师说是只在第一节课点名，但是老师会不时点学生提问，更离谱的是，这老师经常出差，只能让助教代课，然后助教完美无视了这个承诺，直接全班点名...吐"},{"发表时间":"2021-07-06 06:42:08","点赞减去点踩数量":5,"点赞量":7,"点踩量":2,"内容":"拖堂分低"},{"发表时间":"2021-07-17 02:37:18","点赞减去点踩数量":3,"点赞量":6,"点踩量":3,"内容":"没意思，反正努力也没分，不努力分高，微卷屁用没有，要卷拿满绩就当毕业设计去卷"},{"发表时间":"2021-10-23 06:53:38","点赞减去点踩数量":4,"点赞量":6,"点踩量":2,"内容":"乱给分算是见识到了"},{"发表时间":"2021-11-14 15:50:57","点赞减去点踩数量":5,"点赞量":7,"点踩量":2,"内容":"小组展示半个小时起步就离谱"},{"发表时间":"2021-12-26 12:22:21","点赞减去点踩数量":12,"点赞量":13,"点踩量":1,"内容":"拖堂，不说了"},{"发表时间":"2022-02-24 07:06:55","点赞减去点踩数量":6,"点赞量":7,"点踩量":1,"内容":"傻逼玩意儿"},{"发表时间":"2022-02-27 12:10:42","点赞减去点踩数量":6,"点赞量":7,"点踩量":1,"内容":"拖堂，毫无意义的课程"},{"发表时间":"2022-03-13 12:23:43","点赞减去点踩数量":12,"点赞量":13,"点踩量":1,"内容":"老是拖堂老是拖堂，讲一堆没有内容的东西，什么也学不到 浪费时间"},{"发表时间":"2022-03-18 02:36:28","点赞减去点踩数量":16,"点赞量":17,"点踩量":1,"内容":"傻逼东西"},{"发表时间":"2022-05-20 14:29:06","点赞减去点踩数量":10,"点赞量":11,"点踩量":1,"内容":"吊毛一个"},{"发表时间":"2022-06-06 03:34:36","点赞减去点踩数量":16,"点赞量":17,"点踩量":1,"内容":"勾八玩意儿给爷爬，就你配当海院思政部部长？妈的屌毛东西让你办个事逼逼那么多话还不给办，tmd到处踢皮球，不会办事就给爷去死，傻逼玩意儿cnmd"},{"发表时间":"2022-06-10 12:06:56","点赞减去点踩数量":30,"点赞量":33,"点踩量":3,"内容":"我操你妈了个逼的傻逼玩意儿\\n\\n一天天整的跟个脑瘫一样\\n\\n问问题从来都不回复\\n\\n学生会要举办活动就纯瞎jb扯踢皮球\\n\\n还他妈的思政部部长\\n\\n你他妈个逼的以为自己是谁啊\\n\\n整天热衷于做宣传，从不考虑学生感受\\n\\n把学生当作牛马来使唤，自己坐收渔翁之利\\n\\n纯纯傻逼一个"},{"发表时间":"2022-06-21 17:04:46","点赞减去点踩数量":-8,"点赞量":4,"点踩量":12,"内容":"没什么作业，期末被狠狠捞了，感觉不像以前的评论"},{"发表时间":"2022-06-22 04:33:07","点赞减去点踩数量":-10,"点赞量":4,"点踩量":14,"内容":"感觉有必要加一加了💦上课的体验不止2.9这个分....事少，一次小组一起的展示，20-30min好像，然后寒假似乎有一篇800字作文，其他再也没有了。第一节课点名，然后说以后的课提问代点名，但提问真的很少...我第二学期就开始翘课了，大家看情况自己去，拖课是真的，最多拖到20-30min，（但是人都没到就没的拖了），期末裸考，最后得分4.2/86，似乎说被捞的人也不少，大家看情况选择哦"},{"发表时间":"2022-06-23 06:06:51","点赞减去点踩数量":19,"点赞量":21,"点踩量":2,"内容":"表白xjzh学长，班群说会考ppt原题，结果真的就考到了！！"},{"发表时间":"2022-08-08 01:43:24","点赞减去点踩数量":8,"点赞量":9,"点踩量":1,"内容":"。。。"},{"发表时间":"2022-08-29 03:52:57","点赞减去点踩数量":11,"点赞量":13,"点踩量":2,"内容":"无语子"},{"发表时间":"2022-08-31 06:51:17","点赞减去点踩数量":21,"点赞量":22,"点踩量":1,"内容":"wwc绝对是我见过最傻逼的东西，真不知道学校党委是怎么把这种人放到这么重要的思政部部长岗位上来的，格局中只有自己的升官从来不加考虑学生们的感受。对学生抠抠搜搜的，对领导点头哈腰。\\n\\n办事永远只会想着这事儿对领导好不好，对自己好不好。在他眼中哪儿来的为人名服务，只有“为自己服务，为领导服务”学生要办个什么事情，首先想到的是有没有出事的风险，自己会不会下岗。\\n\\n还有很多的东西不适合多说，反正就请大家知道这是个人品很有问题的东西就好"},{"发表时间":"2022-09-10 08:20:24","点赞减去点踩数量":13,"点赞量":14,"点踩量":1,"内容":"傻逼东西。家里面没人了才会是这样。"},{"发表时间":"2022-10-30 13:00:57","点赞减去点踩数量":5,"点赞量":7,"点踩量":2,"内容":"虚伪的一批，装腔作势"},{"发表时间":"2022-12-16 14:32:27","点赞减去点踩数量":4,"点赞量":7,"点踩量":3,"内容":"SB无语"},{"发表时间":"2023-03-05 13:01:28","点赞减去点踩数量":14,"点赞量":15,"点踩量":1,"内容":"不想骂人的我两年回来追评：wwc同样也绝对是我见过最傻逼的东西，真不知道学校党委是怎么把这种人放到这么重要的思政部部长岗位上来的，省级优秀毕业生答辩吃相简直不要太难看，格局中只有巴结自己以及留本院读研的学生才是最优秀的，其他就算你成绩再好，学生工作做的再多也白搭，一听到你保研出去直接脸色拉的难看的一批，最后提问环节搞得就像是法院审判罪犯一样审问你。\\n\\n其次就是表面功夫做尽，紫金港遭遇疫情期间倒是知道给低年级本科生发物资，结果舟山校区的学生找你办事，你倒成了缩头乌龟了。大四申请回紫金港住宿永远要被这玩意盘问来盘问去，最后一票否决不给签字盖章，永远只会想着这事儿对领导好不好，对自己好不好。\\n\\n我只能说在海洋学院呆的后两年是我活这么大所经历的最窝囊的两年，曾经昧着良心尽量不给学弟学妹传递海院的负能量是非常后悔的做法，就指望这样子的人建设海洋学院，落实海洋强国战略，你妈你信吗？\\n\\n如果再让我给低年级学生做分享，我只会劝他们赶紧逃离海院，越快越好，留在这只会徒增精神内耗。"},{"发表时间":"2023-04-18 21:19:11","点赞减去点踩数量":6,"点赞量":8,"点踩量":2,"内容":"枉为人师"},{"发表时间":"2023-04-04 11:08:34","点赞减去点踩数量":2,"点赞量":4,"点踩量":2,"内容":"呵呵呵"},{"发表时间":"2023-06-27 10:47:45","点赞减去点踩数量":-1,"点赞量":1,"点踩量":2,"内容":"老师给分巨好！！！"},{"发表时间":"2023-06-27 10:49:25","点赞减去点踩数量":-2,"点赞量":1,"点踩量":3,"内容":"这老师给分真的好好，我平时上课水一下考前ppt都没怎么看竟然有4.5！！！（感觉老师现在已经改过自新了，还是可以给个机会的）"},{"发表时间":"2023-06-27 11:04:56","点赞减去点踩数量":-3,"点赞量":1,"点踩量":4,"内容":"给我卡94 服辣"},{"发表时间":"2023-06-27 15:49:10","点赞减去点踩数量":1,"点赞量":3,"点踩量":2,"内容":"就因为他给了我满绩，我也必须给他满分了"},{"发表时间":"2023-06-28 02:54:00","点赞减去点踩数量":2,"点赞量":2,"点踩量":0,"内容":"阿巴阿巴阿巴"},{"发表时间":"2023-06-30 13:07:49","点赞减去点踩数量":0,"点赞量":1,"点踩量":1,"内容":"意满离"},{"发表时间":"2023-07-05 11:12:25","点赞减去点踩数量":8,"点赞量":8,"点踩量":0,"内容":"这么喜欢海洋怎么调去历史学院了呢？"},{"发表时间":"2023-08-27 13:27:46","点赞减去点踩数量":7,"点赞量":7,"点踩量":0,"内容":"傻逼玩意儿"},{"发表时间":"2023-10-15 12:38:56","点赞减去点踩数量":8,"点赞量":8,"点踩量":0,"内容":"🤗拖堂好手"},{"发表时间":"2024-01-19 22:35:07","点赞减去点踩数量":4,"点赞量":4,"点踩量":0,"内容":"垃圾老师"},{"发表时间":"2024-06-23 04:41:31","点赞减去点踩数量":1,"点赞量":1,"点踩量":0,"内容":"疑似有点太能装了"},{"发表时间":"2024-06-25 12:15:38","点赞减去点踩数量":-2,"点赞量":1,"点踩量":3,"内容":"23-24学年，不知道为啥这个老师评分这么低。但我感觉老师蛮好的，最后认真背一下老师发的ppt，老师给了4.5的绩点，不卡绩，挺好的~好多其他班的同学绩点才3开头。"},{"发表时间":"2024-06-25 13:03:09","点赞减去点踩数量":-2,"点赞量":0,"点踩量":2,"内容":"来救一下老师的分 形策课没有签到只有随机点人回答问题 本人一次病假+一次发言+考前速通两小时，最后4.5挺满意的"},{"发表时间":"2024-07-05 02:55:37","点赞减去点踩数量":-2,"点赞量":0,"点踩量":2,"内容":"事情少，给分好而且不卡绩"},{"发表时间":"2024-07-05 11:48:47","点赞减去点踩数量":0,"点赞量":0,"点踩量":0,"内容":"臭煞笔"},{"发表时间":"2024-10-15 07:08:53","点赞减去点踩数量":2,"点赞量":2,"点踩量":0,"内容":"不要用文字游戏般的法律条文欺压学生，当老师的该有一定的职业操守"},{"发表时间":"2024-12-01 13:47:09","点赞减去点踩数量":3,"点赞量":3,"点踩量":0,"内容":"迟到十分钟不给补签。难评。说什么靠平时成绩自己补。好吧，我是还没遇到过这种老师。🙄🙄🙄"},{"发表时间":"2025-04-03 06:22:24","点赞减去点踩数量":0,"点赞量":0,"点踩量":0,"内容":"每每想到这笔都要过来打个1分"}],"gpa_info":[["形势与政策Ⅰ","3.97","439","0.66"]]},{"id":4216,"姓名":"陈南菲","学院":"马克思主义学院","热度":2790,"评分人数":4,"评分":0.0,"拼音":"chennanfei","拼音缩写":"cnf","comments":[{"发表时间":"2018-01-28 23:44:54","点赞减去点踩数量":1,"点赞量":1,"点踩量":0,"内容":"老师超级好的！！！！！！力荐"},{"发表时间":"2018-01-29 00:21:28","点赞减去点踩数量":0,"点赞量":0,"点踩量":0,"内容":"上课很有趣"},{"发表时间":"2018-01-30 03:09:37","点赞减去点踩数量":0,"点赞量":0,"点踩量":0,"内容":"最能掌控课堂节奏的老师没有之一"},{"发表时间":"2018-05-04 05:31:02","点赞减去点踩数量":0,"点赞量":0,"点踩量":0,"内容":"老师人挺好，非常可爱呐，口才超棒，课堂氛围好，课业任务少，给分也比较合理吧，强推一波～～"}],"gpa_info":[["大学生朋辈心理辅导","4.41","356","0.42"],["思想道德与法治","4.51","205","0.24"],["思想道德修养与法律基础","3.88","500+","0.47"],["职业生涯规划","4.41","83","0.38"],["职业生涯规划A","4.23","58","0.67"]]},{"id":4217,"姓名":"Chloi Sofia Fassou","学院":"外国语言文化与国际交流学院","热度":183,"评分人数":4,"评分":0.0,"拼音":"chloisofiafassou","拼音缩写":"csf","comments":[{"发表时间":"2022-06-19 03:35:15","点赞减去点踩数量":7,"点赞量":7,"点踩量":0,"内容":"🐒🐒🐒护国大使索菲亚👊👊👊新官上任三把火🔥🔥🔥可威风了👍🏻👍🏻👍🏻"},{"发表时间":"2022-06-19 06:43:19","点赞减去点踩数量":2,"点赞量":2,"点踩量":0,"内容":"给分也太差了🆘！！！！快逃！！！"},{"发表时间":"2022-09-27 14:53:18","点赞减去点踩数量":1,"点赞量":2,"点踩量":1,"内容":"连夜给София评论！！！她的课制作很用心，视听说背单词就因为我们说喜欢玩电脑上的的背单词游戏，她就又精心制作了两课！！！上课氛围超好，她超级可爱！！中文说的很好！！！"}],"gpa_info":[]},{"id":4218,"姓名":"申屠建中","学院":"附属第一医院","热度":282,"评分人数":1,"评分":0.0,"拼音":"shentujianzhong","拼音缩写":"stjz","comments":[{"发表时间":"2018-07-15 14:14:17","点赞减去点踩数量":0,"点赞量":0,"点踩量":0,"内容":"给分结果很难过 觉得做的好不错 结果分数不理想"}],"gpa_info":[["临床药理学","2.83","31","0.88"],["药物经济学","4.16","100","0.76"]]},{"id":4220,"姓名":"蔡圣","学院":"药学院","热度":2264,"评分人数":4,"评分":0.0,"拼音":"caisheng","拼音缩写":"cs","comments":[{"发表时间":"2022-03-14 02:01:51","点赞减去点踩数量":5,"点赞量":5,"点踩量":0,"内容":"在上生化，老师好可爱哈哈哈哈，我都不困了"},{"发表时间":"2023-05-08 01:24:43","点赞减去点踩数量":1,"点赞量":1,"点踩量":0,"内容":"老师真可爱啊哈哈哈哈好喜欢"},{"发表时间":"2024-07-09 18:02:39","点赞减去点踩数量":0,"点赞量":0,"点踩量":0,"内容":"老师挺可爱的，虽然上课一般，但是感觉人很有趣，对待学生也非常温和，也许做他的研究生也不错hhhh"}],"gpa_info":[["生物化学与分子生物学","3.37","53","0.86"],["药物分析学","3.86","218","0.82"],["药物分析学实验","4.49","272","0.36"]]},{"id":4222,"姓名":"陈文腾","学院":"药学院","热度":4307,"评分人数":4,"评分":0.0,"拼音":"chenwenteng","拼音缩写":"cwt","comments":[{"发表时间":"2022-01-10 15:18:34","点赞减去点踩数量":3,"点赞量":5,"点踩量":2,"内容":"好老师  讲课逻辑很清楚"},{"发表时间":"2022-12-23 02:31:20","点赞减去点踩数量":-4,"点赞量":1,"点踩量":5,"内容":"有点抽象，老师说话布置作业不是很有条理"},{"发表时间":"2025-01-02 12:41:47","点赞减去点踩数量":0,"点赞量":1,"点踩量":1,"内容":"老师很温和，讲课非常有条理，钉钉每次都秒回真的爱了😍😍😍"}],"gpa_info":[["药物化学","3.48","170","1.05"],["药物化学实验","4.55","135","0.32"],["药物合成反应与波谱解析","3.84","23","0.78"],["药物波谱解析","3.10","175","0.94"],["药物科学研究实训","4.57","300","0.29"],["药物设计","4.27","7","0.62"]]},{"id":4223,"姓名":"王璇","学院":"数学科学学院","热度":4233,"评分人数":37,"评分":3.44276,"拼音":"wangxuan","拼音缩写":"wx","comments":[{"发表时间":"2018-01-30 08:37:06","点赞减去点踩数量":6,"点赞量":8,"点踩量":2,"内容":"新老师，外校的，不太懂规矩（甚至不知道概统书有答案），说话像一个吊坠在你眼前晃，讲课没什么逻辑，小测非常简单。我上的是概率论，一学期下来全靠自学，给分还算正常。"},{"发表时间":"2018-03-05 06:00:03","点赞减去点踩数量":-15,"点赞量":4,"点踩量":19,"内容":"比较简单，不过老师挺认真的。"},{"发表时间":"2018-03-06 01:22:54","点赞减去点踩数量":-15,"点赞量":1,"点踩量":16,"内容":"好好好"},{"发表时间":"2018-04-12 00:09:25","点赞减去点踩数量":13,"点赞量":15,"点踩量":2,"内容":"概统书后作业题全部布置是一种什么样的体验？"},{"发表时间":"2018-04-10 04:19:59","点赞减去点踩数量":14,"点赞量":16,"点踩量":2,"内容":"平时作业多到爆炸"},{"发表时间":"2018-04-13 08:22:29","点赞减去点踩数量":20,"点赞量":22,"点踩量":2,"内容":"布置作业多到爆，一章课后练习分两次全部做完，挑都不挑一下...只要你们吧课后习题全部做会！考试一定考得好！"},{"发表时间":"2018-04-16 03:36:23","点赞减去点踩数量":14,"点赞量":16,"点踩量":2,"内容":"上的抽样调查，不认真备课，不熟悉课件和课本，板书经常出错，布置作业之前不看作业题的内容，经常这节课布置了下节课的作业，然后下节课没作业可以交，上课想不起来、板书出错还不承认"},{"发表时间":"2018-04-16 06:49:44","点赞减去点踩数量":-1,"点赞量":4,"点踩量":5,"内容":"第一年上概率论，讲的一般，但考试周前特地找了间教室上复习课，期末考卷她自己出的，比较简单。总体上还行。"},{"发表时间":"2018-04-16 08:45:18","点赞减去点踩数量":13,"点赞量":15,"点踩量":2,"内容":"没找到在哪里评零分 就打了个1"},{"发表时间":"2018-04-24 03:06:47","点赞减去点踩数量":12,"点赞量":13,"点踩量":1,"内容":"像一个rapper一样拿话筒，于是口水声和呼吸声比讲课声更清楚！而且感觉说每句话前都没想清楚说什么，除了读ppt就是说'这个灯息''相当于''这个''那个'，手在ppt上画画画，根本不懂她指哪个！\\n\\n"},{"发表时间":"2018-05-09 09:00:48","点赞减去点踩数量":11,"点赞量":15,"点踩量":4,"内容":"第一作业极多\\n\\n第二讲课差劲，简单的地方讲得慢，复杂的地方一跳而过\\n\\n第三不关心学生，认为只有数学系的学生才配上她的课"},{"发表时间":"2018-05-14 16:17:55","点赞减去点踩数量":7,"点赞量":8,"点踩量":1,"内容":"作业好多"},{"发表时间":"2018-05-19 01:45:05","点赞减去点踩数量":25,"点赞量":30,"点踩量":5,"内容":"王老师讲课之差并不在于其水平不足，而在于根本就不在乎。不在乎学生有没有听懂，不在乎作业是不是布置了错题，不在乎自己有没有弄懂，上来劈头盖脸就是一通讲，错了也不知道。我觉得作业布置的难没问题，但要是错题就相当生气了，试想一下你考虑了一两天的题目，不停的从头开始演算，最后只是题目有问题，还有那些模棱两可的题目表述，看着就格外令人生气。然而老师吊儿郎当的态度让人觉得即使去问她，也不会有任何改观。"},{"发表时间":"2018-05-20 07:30:00","点赞减去点踩数量":11,"点赞量":11,"点踩量":0,"内容":"讲课真的不怎么样啊"},{"发表时间":"2018-05-28 15:22:34","点赞减去点踩数量":5,"点赞量":8,"点踩量":3,"内容":"补作业中，，，离猝死不远了。这个老师，我只想说，好胆你就来。。。"},{"发表时间":"2018-06-12 03:41:01","点赞减去点踩数量":21,"点赞量":21,"点踩量":0,"内容":"最可怜的是助教吧，得自己做完所有课后题，给我们看详细过程，每周批一百多本本子，还特么是全部课后题，最后老师还怀疑他有没有仔细看过程？\\n\\n尤其第八章，都是重复来重复去的题，就不会挑几个典型的做？还是根本没有看过课后题？\\n\\n我就算绩点爆炸也不会说这老师的好话，重修预定吧"},{"发表时间":"2018-06-13 01:26:32","点赞减去点踩数量":42,"点赞量":46,"点踩量":4,"内容":"给老师两分 因为她知道开空调 别的真的没有什么优点了呢！我觉得这个女老师向我们展现了一个失败的青年人是什么样子的，觉得自己是国外回来的，教这种公共课很屈才的样子，只能说学校还有点数不让你去祸祸数院的朋友。难道你不应该认真备课，兢兢业业，提高自己的教学水平吗？给自己敲响警钟以后不要成为这种浮躁的年轻人！我真的觉得那些好好学的大佬都比你讲的好，另外感觉自己是个小天才靠自学学了这门课。好气啊，浙大怎么招的老师啊？失望！"},{"发表时间":"2018-06-26 04:08:20","点赞减去点踩数量":3,"点赞量":4,"点踩量":1,"内容":"对待点名不严肃。差评。说消除就消除"},{"发表时间":"2018-07-01 13:12:05","点赞减去点踩数量":3,"点赞量":4,"点踩量":1,"内容":"好老师，上课讲的很细致 我二十年前听她的概统课受益匪浅。至今还在赌博界叱咤风云。"},{"发表时间":"2018-07-08 12:16:01","点赞减去点踩数量":0,"点赞量":3,"点踩量":3,"内容":"抽样不给重点真的背的很想死，但是试卷很基础，给分正常吧。上课基本读ppt 人还挺随和的"},{"发表时间":"2018-07-09 13:24:34","点赞减去点踩数量":1,"点赞量":3,"点踩量":2,"内容":"点名。抽样 最后3 很气"},{"发表时间":"2018-07-09 14:22:57","点赞减去点踩数量":-1,"点赞量":2,"点踩量":3,"内容":"很无语。。。"},{"发表时间":"2018-07-14 13:30:26","点赞减去点踩数量":6,"点赞量":7,"点踩量":1,"内容":"第一节课讲排列组合全讲错的，就自学了，作业比较多，一般要做一整个下午"},{"发表时间":"2018-07-15 00:32:22","点赞减去点踩数量":7,"点赞量":8,"点踩量":1,"内容":"这是我从小学开始见过的最优秀的老师，在她的眼里她并不适合教我们这些垃圾学概统，课后问她问题她从来都不回，把学生分三六九等，不给成绩不理想的学生宽容，素质极高，是浙江大学的标杆！"},{"发表时间":"2018-07-15 08:31:32","点赞减去点踩数量":11,"点赞量":11,"点踩量":0,"内容":"上课话筒贴着嘴巴和bbox一样讲课 口水声呼吸声都听的清清楚楚 一学期一共就那么十几节课点名点了6 7次吧 然后说高年级的不容易有几次人没来就没算(不是说高年级不好的意思 我也是高年级 只是觉得不公平)而且记没到的人的时候还会出bug 记串行什么的 最后一节课来的人前面缺课的记录可以消除…那要点名干嘛呢…？上课的时候经常表现出自己胸怀大志不屑于教(这种很垃圾的)公选课的不满态度…真的不敢置信这就是一个年轻海龟的素质 和接触的其他海龟老师比起来差的不是一点两点"},{"发表时间":"2018-07-16 04:17:00","点赞减去点踩数量":6,"点赞量":10,"点踩量":4,"内容":"给助教小姐姐疯狂打call，我们做课后所有作业题，她都自己认真做，写过程发公邮。考前还可以补交作业，最后一天答疑超级认真，有不会的题目还可以微信问她。"},{"发表时间":"2018-07-21 12:50:39","点赞减去点踩数量":1,"点赞量":4,"点踩量":3,"内容":"很差的"},{"发表时间":"2018-09-21 02:25:32","点赞减去点踩数量":3,"点赞量":5,"点踩量":2,"内容":"辣鸡辣鸡"},{"发表时间":"2018-11-23 02:57:14","点赞减去点踩数量":5,"点赞量":8,"点踩量":3,"内容":"我觉得老师挺好的啊，喷她的请你们去听听张南松的课好吧。推导过程很详细，布置作业很多也是为我们好啊，上课听的下去，除了说话姿势像rapper其他没槽点了吧，而且也很有特点啊"},{"发表时间":"2019-01-24 15:55:21","点赞减去点踩数量":6,"点赞量":8,"点踩量":2,"内容":"讲真我觉得老师上得挺不错的 至少我每节课认认真真听了觉得讲得挺细致挺清楚的 作业布置得比其他老师多是事实 但也是为了我们好 期末疯狂刷题看书不如平时多花点时间弄清楚多练习不是吗  可以抱怨老师作业多但也要明白老师的用意吧  上课有时会喷麦也是话筒和个人讲话方式问题（老师也有在努力调整了） 作为学生不应该一味苛责老师而是尽量适应老师的方式鸭  个人上课好好听讲了作业也都问心无愧 最后成绩也还nice  给出自认为客观的评价?"},{"发表时间":"2019-01-25 00:33:07","点赞减去点踩数量":3,"点赞量":7,"点踩量":4,"内容":"老师挺好的，会一直问学生自己有哪里做的不好的，会改正，认真学最后的绩点也是不错的"},{"发表时间":"2019-01-26 17:23:33","点赞减去点踩数量":2,"点赞量":5,"点踩量":3,"内容":"没怎么听过，因为上课时间全用来做她布置的作业了。试问当你的老师布置的题量几乎等于整本书时你是什么感想？真的光题目都做吐了，而且给分也让我绝望，话说真的有这么险恶的课？"}],"gpa_info":[]},{"id":4225,"姓名":"唐晓武","学院":"宁波理工学院","热度":862,"评分人数":0,"评分":0.0,"拼音":"tangxiaowu","拼音缩写":"txw","comments":[],"gpa_info":[["中国概况","4.03","500+","0.70"],["国际贸易实务","3.90","31","0.36"],["土力学","3.02","87","0.95"],["当代中国经济","4.25","34","0.31"],["环境岩土工程","4.52","31","0.32"]]},{"id":4226,"姓名":"程晓东","学院":"附属妇产科医院","热度":102,"评分人数":0,"评分":0.0,"拼音":"chengxiaodong","拼音缩写":"cxd","comments":[],"gpa_info":[["Obstetrics & Gynecology","3.74","287","0.80"]]},{"id":4227,"姓名":"梁社红","学院":"本科生院学生工作处","热度":1243,"评分人数":1,"评分":0.0,"拼音":"liangshehong","拼音缩写":"lsh","comments":[{"发表时间":"2021-12-28 10:06:59","点赞减去点踩数量":4,"点赞量":5,"点踩量":1,"内容":"老师打分要求比较严格，但我认为很客观呀！我们组上课认真、小组作业完成得很好，老师给的分也很高！个人感受是：心理学是需要静心学习的！课程很有意义，收获很大，谢谢老师！"}],"gpa_info":[["大学生朋辈心理辅导","4.25","298","0.50"],["积极心理学","4.10","141","0.62"]]},{"id":4228,"姓名":"金建伟","学院":"马克思主义学院","热度":2369,"评分人数":2,"评分":0.0,"拼音":"jinjianwei","拼音缩写":"jjw","comments":[{"发表时间":"2019-04-15 09:51:32","点赞减去点踩数量":1,"点赞量":8,"点踩量":7,"内容":"推理论证，思辨性比较强，但有时转换太快，有点跟不上。\\n\\n"}],"gpa_info":[["社会主义发展史","4.38","500+","0.34"],["马克思主义基本原理","4.06","500+","0.59"],["马克思主义基本原理概论","4.01","500+","0.52"]]},{"id":4229,"姓名":"鲁汪涛","学院":"数学科学学院","热度":16494,"评分人数":64,"评分":8.93182,"拼音":"luwangtao","拼音缩写":"lwt","comments":[{"发表时间":"2018-03-06 04:04:47","点赞减去点踩数量":8,"点赞量":11,"点踩量":3,"内容":"新老师很谦虚，讲课很认真，鼓励一下。\\n\\n希望板书能再工整一点。"},{"发表时间":"2018-03-08 14:37:33","点赞减去点踩数量":7,"点赞量":11,"点踩量":4,"内容":"感天动地好老师，就是人有点少"},{"发表时间":"2018-03-13 03:56:07","点赞减去点踩数量":-3,"点赞量":0,"点踩量":3,"内容":"。。。"},{"发表时间":"2018-04-03 02:35:55","点赞减去点踩数量":-21,"点赞量":18,"点踩量":39,"内容":"给这个老师打一分是因为没有零分这个选项。有这个老师给你上微积分，基本你就凉了一半了。"},{"发表时间":"2018-03-23 12:51:46","点赞减去点踩数量":20,"点赞量":30,"点踩量":10,"内容":"努汪涛老师上课很认真！\\n\\n板书错了会说“不好意思”\\n\\n布置作业也很负责！\\n\\n群里发言数第一好吗！\\n\\n助教小姐姐也hin可爱呀嘿嘿"},{"发表时间":"2018-04-03 02:06:51","点赞减去点踩数量":6,"点赞量":9,"点踩量":3,"内容":"感觉挺负责，就是有点快_(:з」∠)_"},{"发表时间":"2018-05-10 13:00:48","点赞减去点踩数量":7,"点赞量":12,"点踩量":5,"内容":"老师很认真了，助教小姐姐超级好"},{"发表时间":"2018-04-17 04:38:45","点赞减去点踩数量":-2,"点赞量":5,"点踩量":7,"内容":"不停写错 不停抄错"},{"发表时间":"2018-06-15 03:47:57","点赞减去点踩数量":12,"点赞量":14,"点踩量":2,"内容":"老师讲的超仔细超认真，没有任何口音听的好舒服！所有细节都老老实实讲一点也不含糊，真的很有帮助"},{"发表时间":"2018-06-20 04:11:14","点赞减去点踩数量":-21,"点赞量":4,"点踩量":25,"内容":"求求老师别揪着这个百分之七十超纲题这个梗不放了好么。我错了行了不（呜呜呜呜）说了好几次我听着都不好意思了。我再也不敢在大群里乱说话了。老师太耿直了，反语夸张统统听不懂，全部按字面意思处理，真的笑出声了。。。。。本着对学生负责的态度。。。。。。emmmmm，对我们这么不信任怕我们抄答案就放弃苏德矿的书，逻辑神奇。本着对学生负责的态度，今天就布置。。。。。多作业。。本着对学生负责的态度。。。。。你好歹写个参考答案吧，知道你忙，但是我们每次作业都没有详细答案真的好累的(´;︵;`)老师自己写的答案还特别潦草，真让人头秃。。。"},{"发表时间":"2018-06-20 05:39:30","点赞减去点踩数量":-20,"点赞量":4,"点踩量":24,"内容":"三次小测的微积分，上课到后期真心听不懂了呀!知道老师忙，但是以怕我们抄答案为由放弃矿爷的教材（全班投票几乎全部拒绝的情况下，让学生投票但似乎投票结果毫无作用），而自己给我们做的答案真的也是无力吐槽，想好好看答案纠错都不行。。。上课的内容例题似乎全部都是课本上的，本着负责任的态度，作业多到不用学别的科目，，，。。。"},{"发表时间":"2018-07-03 03:54:37","点赞减去点踩数量":7,"点赞量":8,"点踩量":1,"内容":"涛涛真的很不错很负责，满分！"},{"发表时间":"2018-07-11 06:59:58","点赞减去点踩数量":21,"点赞量":26,"点踩量":5,"内容":"老师是青千，讲课很清楚，备课备得也很认真，还有助教姐姐也超负责，把习题课上成了精华总结课。"},{"发表时间":"2018-07-11 07:22:38","点赞减去点踩数量":4,"点赞量":5,"点踩量":1,"内容":"好老师！感谢不挂之恩！是我下半学期没花时间对不起老师TAT"},{"发表时间":"2018-07-11 07:55:47","点赞减去点踩数量":11,"点赞量":13,"点踩量":2,"内容":"负责的老师和助教～态度100分！\\n\\n我觉得课后更多的还是靠自己，老师有自己的想法，不一定所有人都可以适合呀"},{"发表时间":"2018-07-11 08:51:23","点赞减去点踩数量":3,"点赞量":4,"点踩量":1,"内容":"鲁老师其实真的还不错啦，认真负责。作业偏多但平时基本功打扎实期末确实会省不少力，比较适合我这种数学基础不那么好的，讲课也不算很快。最后上4了感谢老师和助教小姐姐啦！！！"},{"发表时间":"2018-07-11 08:55:58","点赞减去点踩数量":8,"点赞量":10,"点踩量":2,"内容":"鲁老师作为青千，知识水平高又谦虚认真负责，普通话标准，课堂无需抢座。那些退课的你们就后悔去吧！"},{"发表时间":"2018-07-12 04:28:16","点赞减去点踩数量":3,"点赞量":3,"点踩量":0,"内容":"老师真的很认真负责又谦虚，助教小姐姐更加。棒棒棒！！！"},{"发表时间":"2018-08-25 03:29:31","点赞减去点踩数量":0,"点赞量":2,"点踩量":2,"内容":"作业布置得很多，最后因为考试太多了微积分没有复习? ，不过老师给分还不错，作业多的好处是期末没时间复习平时好好做了作业期末还是能够过的"},{"发表时间":"2018-09-17 16:05:02","点赞减去点踩数量":1,"点赞量":3,"点踩量":2,"内容":"好老师，真的好"},{"发表时间":"2019-06-06 12:57:22","点赞减去点踩数量":1,"点赞量":1,"点踩量":0,"内容":"还行吧"},{"发表时间":"2019-06-20 02:00:33","点赞减去点踩数量":1,"点赞量":2,"点踩量":1,"内容":"老师人很好"},{"发表时间":"2019-09-11 12:50:53","点赞减去点踩数量":1,"点赞量":2,"点踩量":1,"内容":"老师讲课很仔细，也很认真，讲的大多都能听懂，很棒"},{"发表时间":"2019-10-23 05:48:23","点赞减去点踩数量":1,"点赞量":3,"点踩量":2,"内容":"鲁老师是我见过最沉稳的老师。他上课语调非常平稳，不说废话，逻辑缜密，边写边讲，节奏不快。我感觉他在讲台上不像一个老师在讲课，更像一个学者在做报告。真心很喜欢他的线代，满分"},{"发表时间":"2019-11-11 08:33:39","点赞减去点踩数量":2,"点赞量":2,"点踩量":0,"内容":"老师非常认真负责！每次都在Keynote里写板书，当天晚上上传到QQ群。印象很深的是，老师把所有同学的期中试卷所有题的给分重新认真审核了一遍！"},{"发表时间":"2019-11-13 05:13:16","点赞减去点踩数量":5,"点赞量":6,"点踩量":1,"内容":"选了鲁老师的线代甲，老师上课认真负责，讲行nie式讲的也很清楚，课上有很多讲习题的环节。老师对学生的态度也超级好，期中考为了让大家的分数不出差错特意自己核对了一遍班级的卷子，助教也超级好，每本作业都有评语。老师真好，下次还选。"},{"发表时间":"2020-01-17 23:37:23","点赞减去点踩数量":1,"点赞量":1,"点踩量":0,"内容":"老师超级可爱！爱了爱了！讲课没有口音！真的太喜欢了！！"},{"发表时间":"2020-01-20 01:30:46","点赞减去点踩数量":-1,"点赞量":1,"点踩量":2,"内容":"上课又好，给分又好，还负责（期中亲自检查试卷，担心我们被别的班的助教多扣分；期末亲自整理慕课成绩，成绩有错还细心的帮我们该分）这种老师去哪里找哇。老师群里那番话，真的看哭了，太感动了，超级谢谢老师和助教。"},{"发表时间":"2019-12-18 05:16:29","点赞减去点踩数量":-1,"点赞量":1,"点踩量":2,"内容":"鲁老师很年轻，年轻到让人以为是学生... 但是老师很负责，很认真，很会为学生着想，学术水平也很高。另外，助教超级负责，认真批改每一本作业，给每一份作业写评语，给每一次作业题做详解，赞赞赞。"},{"发表时间":"2019-12-12 09:22:02","点赞减去点踩数量":2,"点赞量":2,"点踩量":0,"内容":"鲁老师很幽默！！经常被萌到。而且上课讲的很全面，进度有点快是因为最后会为学生准备很多复习课！平时偶尔会有点跟不上，但是课后问老师他都会很认真的回答，而且会举很多例子讲得很好懂，还会不停的问理解了没有，非常贴心。作业量大的时候会挑一些题作为选做，而且题目都挑得很精髓 工作很负责 有时候也会水班群 和学生相处很友好。而且助教xgg也超级负责！改作业会加很多批注，而且考前会发放很多复习题（（"},{"发表时间":"2020-01-21 17:46:22","点赞减去点踩数量":1,"点赞量":1,"点踩量":0,"内容":"讲课讲得不错，老师和助教超认真～"},{"发表时间":"2020-03-02 14:18:50","点赞减去点踩数量":-1,"点赞量":1,"点踩量":2,"内容":"细致入微的老师，宝藏级别的助教。\\n\\n鲁老师是我见过对学生最负责的老师，各个方面都非常照顾学生的感受。上课亲自手写笔记并且会上传到班级群，进度太快的时候会把重点再细讲一遍，上课还会讲习题，给出答案方便复习。期中期末考试还会在批改完之后再把全班同学的卷子拿出来核查，最后出分也是花了不少时间在群里核对慕课分。\\n\\n助教xgg绝对的认真负责!每一次作业都认真批改，甚至有评语!考试前还会找出十几套卷子给我们复习!老实说对我这种数学悟性不高的学生，这种方法简直有奇效。\\n\\n总之墙裂推荐这个老师!"},{"发表时间":"2020-03-05 10:20:31","点赞减去点踩数量":0,"点赞量":0,"点踩量":0,"内容":"上鲁老师的线代课真的是一种享受！！！还有助教xgg超级超级超级超级好！！！！"},{"发表时间":"2021-06-25 07:17:27","点赞减去点踩数量":2,"点赞量":2,"点踩量":0,"内容":"好喜欢老师！虽然偏微分学不会，但老师讲的很好，知道我们有些没学就会慢一点。老师人也很好，很随和。"},{"发表时间":"2021-07-07 21:24:27","点赞减去点踩数量":27,"点赞量":31,"点踩量":4,"内容":"爹，偏微分让我过吧！！！！"},{"发表时间":"2021-07-08 02:48:21","点赞减去点踩数量":1,"点赞量":1,"点踩量":0,"内容":"偏微分 捞捞 呜呜\\n\\n老师真的蛮好的"},{"发表时间":"2021-07-09 17:39:37","点赞减去点踩数量":3,"点赞量":3,"点踩量":0,"内容":"上过他的课，真的是一位很负责的老师（因为自己太菜最终挂了可是他还安慰我：不要难过，这只是一个小挫折而已以后还有机会，继续努力就好）爱了爱了！！！"},{"发表时间":"2021-12-21 08:30:52","点赞减去点踩数量":0,"点赞量":1,"点踩量":1,"内容":"。。。"},{"发表时间":"2022-01-13 04:06:23","点赞减去点踩数量":-4,"点赞量":1,"点踩量":5,"内容":"。。。"},{"发表时间":"2022-06-22 05:19:26","点赞减去点踩数量":8,"点赞量":9,"点踩量":1,"内容":"爹 pde让我过吧！"},{"发表时间":"2022-06-22 05:21:45","点赞减去点踩数量":1,"点赞量":2,"点踩量":1,"内容":"鲁大师捞捞我！分离变量法解出来的ode不会解，我真的哭死（\\n\\n鲁老师是很好的一个老师，思路清晰，上课就像是一个学者在跟你进行交流，每一个东西都会让你知其然而知其所以然，虽然我期末可能考得不是很好但是还是学到了很多东西，妥妥给10分"},{"发表时间":"2023-11-22 10:24:50","点赞减去点踩数量":22,"点赞量":23,"点踩量":1,"内容":"老师上课不点名，水平很强，上课很有深度。老师人也特别好，也会耐心解答问题。\\n\\n\\n\\n（声明:以下言论对事不对人，仅代表个人观点。老师还是很好的，只是评价《数值计算方法》这门课！）\\n\\n\\n\\n作为工院的研究生，如果选了或者准备选《数值计算方法》这个课大家一定要避雷！\\n\\n\\n\\n这个课虽然不考试，但是作业极多！！！不仅要完成数学手算的作业，还要用matlab实现一堆题目！每周作业都多的离谱，大概有十多道题（五六道手写五六道代码），上一次做那么多作业还是在大一学高数！\\n\\n\\n\\n作为一个非数学专业、用不到这些知识、也不会使用matlab的研究生来说，这是巨大的压力，你必须在周末或者课余时间来完成这一堆的作业（没错我之前matlab都没怎么用过却让我求解这么多复杂的数学问题）。\\n\\n\\n\\n不要以为最后没有考试就万事大吉了，最后那个两道题的大作业难度巨大无比，不是数学专业的你肯定做不出来甚至连题目都看不懂。\\n\\n\\n\\n作为研究生的课其他老师都水水过去了（本科同学还是好好学习吧！），有些考试甚至比例题还简单，但这个课你是根本听不懂（也有可能是我太菜），大作业也是登天的难度\\n\\n\\n\\n如果你看了这些还是想挑战一下自己的话，那么，去吧！"},{"发表时间":"2023-11-26 08:35:59","点赞减去点踩数量":5,"点赞量":7,"点踩量":2,"内容":"（本科生跳过）事情很多，快跑"},{"发表时间":"2024-06-03 11:22:25","点赞减去点踩数量":1,"点赞量":3,"点踩量":2,"内容":"新老师，常微分讲的一般，不过不点名"},{"发表时间":"2024-09-12 09:07:28","点赞减去点踩数量":8,"点赞量":9,"点踩量":1,"内容":"老师水平很强，上课很有深度，人也特别好，也会耐心解答问题。  \\n\\n\\n\\n（声明:以下言论对事不对人，仅代表个人观点。老师还是很好的，只是评价《计算物理中的数学方法》这门课！） \\n\\n\\n\\n这门课不用选的，只开给鲁老师课题组和相关课题组的同学作讨论班用，每节课确定好同学分享部分内容的。选了也会被直接劝退走人，毕竟没有机会参与也拿不了学分，不过欢迎旁听特别是感兴趣的同学！\\n\\n\\n\\n建议选课系统后台把这几位同学拉进去就好，不用让不知情的同学跑一趟来听课又被劝退，毕竟选课界面的介绍也没说授课形式是特定同学的汇报。\\n\\n\\n\\n建议数院推广将课题组讨论班用于授课，组里的同学能拿个学分，老师也能完成教学任务，讨论班内容、时间、地点都放在选课界面上，感兴趣的同学都能来旁听👍。"},{"发表时间":"2024-10-16 17:15:37","点赞减去点踩数量":1,"点赞量":3,"点踩量":2,"内容":"认真负责，讲课清晰，好好老师"},{"发表时间":"2024-10-17 05:18:09","点赞减去点踩数量":2,"点赞量":2,"点踩量":0,"内容":"请问计算物理中的数学方法是开给谁的呢🥹"},{"发表时间":"2024-11-16 03:44:30","点赞减去点踩数量":5,"点赞量":7,"点踩量":2,"内容":"给分差，出分慢，还不告知期末分数不予查卷"},{"发表时间":"2024-11-10 11:59:59","点赞减去点踩数量":-4,"点赞量":2,"点踩量":6,"内容":"谢谢鲁爹救我复变😭😭😭😭"},{"发表时间":"2024-11-14 11:48:09","点赞减去点踩数量":2,"点赞量":2,"点踩量":0,"内容":"不点名\\n\\n但是，老师您怎么还不出分啊"},{"发表时间":"2024-11-16 02:24:46","点赞减去点踩数量":-5,"点赞量":0,"点踩量":5,"内容":"复变 感谢老师捞捞～"},{"发表时间":"2024-11-17 07:26:00","点赞减去点踩数量":3,"点赞量":3,"点踩量":0,"内容":"给分确实差。。。"},{"发表时间":"2024-12-30 18:16:34","点赞减去点踩数量":2,"点赞量":2,"点踩量":0,"内容":"讲得很一般……不知道为什么复变扣了我这么多"},{"发表时间":"2025-01-16 02:51:44","点赞减去点踩数量":2,"点赞量":3,"点踩量":1,"内容":"两个学期的常微分和复变都没点名\\n\\n但新老师没经验讲的很不好，进度安排不合理，给分也很差，答疑也不及时"}],"gpa_info":[["偏微分方程","3.25","143","1.16"],["前沿数学专题讨论","4.17","9","0.50"],["复变函数与积分变换","3.52","193","0.88"],["常微分方程","3.63","140","1.03"],["渐近法与摄动理论","3.77","94","1.05"],["现代数学进展","4.69","21","0.22"]]},{"id":4230,"姓名":"刘帅","学院":"本科生院求是学院","热度":1364,"评分人数":0,"评分":0.0,"拼音":"liushuai","拼音缩写":"ls","comments":[],"gpa_info":[["思想道德与法治","4.26","127","0.47"],["职业生涯规划","4.44","352","0.51"],["药用高分子材料学","4.40","13","0.32"]]},{"id":4231,"姓名":"刘博","学院":"管理学院","热度":2434,"评分人数":47,"评分":6.54234,"拼音":"liubo","拼音缩写":"lb","comments":[{"发表时间":"2018-03-15 00:20:40","点赞减去点踩数量":7,"点赞量":15,"点踩量":8,"内容":"同学互换批作业！还打分！上课讲贼快"},{"发表时间":"2018-03-29 17:08:36","点赞减去点踩数量":4,"点赞量":13,"点踩量":9,"内容":"很烂 烂极了。"},{"发表时间":"2018-03-29 00:37:19","点赞减去点踩数量":7,"点赞量":15,"点踩量":8,"内容":"事多 冷脸"},{"发表时间":"2018-04-03 15:01:08","点赞减去点踩数量":-2,"点赞量":12,"点踩量":14,"内容":"老师可能经验不足吧，但态度是认真的，不应该这样黑她"},{"发表时间":"2018-04-19 00:24:15","点赞减去点踩数量":-3,"点赞量":16,"点踩量":19,"内容":"真的0分 可惜查老师没有0分\\n\\n讲课垃圾\\n\\n声音轻\\n\\n作业事多\\n\\n总是自以为是的在想\\n\\n上课总会自己突然提一个观点然后自己都不知道对不对然后问大家“你们觉得对不对呢我们讨论一下”我们都没学过这门课做什么判断啊？？你是脑子进水的吗？？？不能在上课前先知道最后结果再发问？？\\n\\n上课体验极差\\n\\n最前面还很努力了，又是这种圣母论断也笑死讲的不好就该直接讲知道吗"},{"发表时间":"2018-04-26 02:43:17","点赞减去点踩数量":5,"点赞量":10,"点踩量":5,"内容":"作业同学互批，给分没有标准\\n\\n事多，上课逻辑混乱、声音轻\\n\\n上课感受极其心塞"},{"发表时间":"2018-05-08 03:38:01","点赞减去点踩数量":-6,"点赞量":3,"点踩量":9,"内容":"讲课真一般\\n\\n给分真的好"},{"发表时间":"2018-05-08 06:26:30","点赞减去点踩数量":-3,"点赞量":2,"点踩量":5,"内容":"给分好"},{"发表时间":"2018-05-09 06:06:01","点赞减去点踩数量":-8,"点赞量":1,"点踩量":9,"内容":"给分不是一般的好！！"},{"发表时间":"2018-05-09 06:29:37","点赞减去点踩数量":-6,"点赞量":2,"点踩量":8,"内容":"给分好 不解释"},{"发表时间":"2018-05-30 03:38:47","点赞减去点踩数量":4,"点赞量":6,"点踩量":2,"内容":"一言难尽"},{"发表时间":"2018-06-15 02:03:31","点赞减去点踩数量":3,"点赞量":6,"点踩量":3,"内容":"所以这是个体育老师吗?？"},{"发表时间":"2018-06-27 04:50:33","点赞减去点踩数量":62,"点赞量":82,"点踩量":20,"内容":"看前面的评论，搞搞清楚这是哪个老师吧\\n\\n教篮球班的刘博，作业互批？上课圣母？\\n\\n别的我不说，就冲前面这几位神仙的态度，应该先去配副眼镜吧。\\n\\n上篮球课的刘博，满分，放心大胆选。"},{"发表时间":"2018-07-07 01:58:10","点赞减去点踩数量":-2,"点赞量":3,"点踩量":5,"内容":"老师考试还是很好的呀"},{"发表时间":"2019-05-14 10:28:44","点赞减去点踩数量":12,"点赞量":18,"点踩量":6,"内容":"差 上课不知道在讲什么 缺课一次请假也没用 直接两点几 祝早日得到报应\\n\\n"},{"发表时间":"2018-11-26 19:54:58","点赞减去点踩数量":10,"点赞量":18,"点踩量":8,"内容":"垃圾！讲课贼烂！请假得不到回复 被点到一次名不在直接给60几 给分随心所欲毫无标准。"},{"发表时间":"2019-01-03 07:05:18","点赞减去点踩数量":3,"点赞量":5,"点踩量":2,"内容":"体育篮球课的刘博老师是一个好老师，上课幽默风趣，篮球课唯一的缺点就是考核对于没有基础的人来说比较困难"},{"发表时间":"2019-01-22 08:37:34","点赞减去点踩数量":-3,"点赞量":2,"点踩量":5,"内容":"老师人超好 对女生好不说 而且给分超级棒"},{"发表时间":"2019-01-25 17:02:50","点赞减去点踩数量":12,"点赞量":17,"点踩量":5,"内容":"想请问一下老师，战略成本管理的第三次小测您看了吗，说好的取最高的一次呢，还是只用来点名了 微笑.jpg"},{"发表时间":"2019-04-20 07:17:53","点赞减去点踩数量":6,"点赞量":10,"点踩量":4,"内容":"管理会计讲课节奏太快了，太快了，太快了，感觉有很多东西都没讲清楚"},{"发表时间":"2019-04-30 11:28:41","点赞减去点踩数量":0,"点赞量":4,"点踩量":4,"内容":"管会给分好！"},{"发表时间":"2019-04-30 11:34:09","点赞减去点踩数量":2,"点赞量":5,"点踩量":3,"内容":"差评 给一分 一生黑"},{"发表时间":"2019-05-01 09:22:59","点赞减去点踩数量":3,"点赞量":4,"点踩量":1,"内容":"老师讲课比较快 上课不能走神 不然会跟不上 给分挺好的"},{"发表时间":"2019-05-08 03:40:23","点赞减去点踩数量":0,"点赞量":2,"点踩量":2,"内容":"有点无聊，不如多讲在实际中的应用，不然就是计算方法那自己也可以学明白"},{"发表时间":"2019-05-23 07:06:31","点赞减去点踩数量":1,"点赞量":6,"点踩量":5,"内容":"这个老师给人一种阴森森的感觉，对学生要求极其严格，实际自己上课水平有限，讲不清楚。沟通困难，这样有性格障碍的人为什么可以做老师？"},{"发表时间":"2019-11-07 04:10:22","点赞减去点踩数量":5,"点赞量":5,"点踩量":0,"内容":"极品的体验"},{"发表时间":"2019-11-07 04:13:14","点赞减去点踩数量":2,"点赞量":4,"点踩量":2,"内容":"专门为了为难学生而存在的老师"},{"发表时间":"2019-11-11 12:46:00","点赞减去点踩数量":1,"点赞量":2,"点踩量":1,"内容":"小测好狠呀"},{"发表时间":"2019-11-12 09:15:15","点赞减去点踩数量":0,"点赞量":1,"点踩量":1,"内容":"出分没有大家没有默契谢谢老师的一门课"},{"发表时间":"2019-11-14 16:19:32","点赞减去点踩数量":-3,"点赞量":1,"点踩量":4,"内容":"给分是真的好，说给分不好的要么平时没有好好学要么就是期末没考好吧"},{"发表时间":"2020-07-02 05:28:29","点赞减去点踩数量":2,"点赞量":3,"点踩量":1,"内容":"遇到就赶紧跑吧"},{"发表时间":"2020-11-24 16:04:32","点赞减去点踩数量":0,"点赞量":1,"点踩量":1,"内容":"还挺好"},{"发表时间":"2020-12-25 06:22:33","点赞减去点踩数量":3,"点赞量":4,"点踩量":1,"内容":"这是篮球老师，话不多说，就是很好"},{"发表时间":"2020-12-25 09:54:35","点赞减去点踩数量":4,"点赞量":4,"点踩量":0,"内容":"哈哈哈哈大家都搞错了吧，刘博老师是教篮球的，人超级奈斯"},{"发表时间":"2021-01-13 08:01:30","点赞减去点踩数量":-3,"点赞量":3,"点踩量":6,"内容":"这种垃圾老师，太阴暗了，上课讲的超级烂不说，什么也学不到，然后评价体系也十分苛刻，好像给学生高分对她有很大的损失一样.....手动白眼。"},{"发表时间":"2021-04-27 13:43:43","点赞减去点踩数量":6,"点赞量":7,"点踩量":1,"内容":"搞搞清楚好不好啦，这是篮球课的老师，人好得不行好吧，真服了，果断10分"},{"发表时间":"2021-06-11 04:10:43","点赞减去点踩数量":5,"点赞量":5,"点踩量":0,"内容":"篮球课的刘老师是我遇到过最好的篮球老师，给分贼好"},{"发表时间":"2021-12-21 05:00:46","点赞减去点踩数量":10,"点赞量":10,"点踩量":0,"内容":"这是体育老师啊！！！我为刘博姐姐正名！！！其他人怪不得拿低分，老师不看清楚就在这狂喷，活该！"},{"发表时间":"2023-05-03 02:08:32","点赞减去点踩数量":-1,"点赞量":0,"点踩量":1,"内容":"快跑！！！"},{"发表时间":"2023-06-02 05:17:46","点赞减去点踩数量":1,"点赞量":1,"点踩量":0,"内容":"篮球超好"},{"发表时间":"2023-12-22 05:20:32","点赞减去点踩数量":2,"点赞量":2,"点踩量":0,"内容":"这TM是体育老师啊\\n\\n给刘老师正名\\n\\n体育课哪里来的作业互评\\n\\n——————————————\\n\\n期末考没过会多给你机会直到过了为止\\n\\n加上篮球中级班的本来就不难\\n\\n所以一般人都能拿到满分的"},{"发表时间":"2024-12-13 02:47:18","点赞减去点踩数量":0,"点赞量":0,"点踩量":0,"内容":"篮球初级班\\n\\n好"}],"gpa_info":[["体育训练与比赛Ⅰ","4.51","91","0.21"],["体育训练与比赛Ⅱ","4.58","59","0.23"],["战略成本管理","3.95","33","0.95"],["篮球（中级班）","4.64","500+","0.60"],["篮球（中级）","4.70","63","0.59"],["篮球（初级班）","4.54","500+","0.67"],["篮球（初级）","4.63","189","0.66"]]},{"id":4237,"姓名":"李永明","学院":"光华法学院","热度":1107,"评分人数":1,"评分":0.0,"拼音":"liyongming","拼音缩写":"lym","comments":[{"发表时间":"2018-09-19 06:39:21","点赞减去点踩数量":0,"点赞量":0,"点踩量":0,"内容":"选了老师的课虽然只上了第一节但就是莫名的喜欢这位老师，很有想法很有趣❤️"}],"gpa_info":[["司法实习","4.88","158","0.20"],["知识产权法","3.44","167","0.79"],["知识产权法案例研习","4.01","19","0.72"]]},{"id":4239,"姓名":"金盛","学院":"建筑工程学院","热度":4747,"评分人数":7,"评分":8.73931,"拼音":"jinsheng","拼音缩写":"js","comments":[{"发表时间":"2023-06-14 08:21:25","点赞减去点踩数量":12,"点赞量":15,"点踩量":3,"内容":"展示课请全班吃KFC"},{"发表时间":"2023-06-14 08:25:16","点赞减去点踩数量":5,"点赞量":6,"点踩量":1,"内容":"爹！！"},{"发表时间":"2023-06-19 05:47:31","点赞减去点踩数量":4,"点赞量":4,"点踩量":0,"内容":"很好很好的老师，作业很少，体谅同学，上课用心"},{"发表时间":"2024-05-19 13:21:42","点赞减去点踩数量":0,"点赞量":1,"点踩量":1,"内容":"挺温柔的一个老师，上课也蛮有意思"},{"发表时间":"2024-06-25 08:40:20","点赞减去点踩数量":3,"点赞量":3,"点踩量":0,"内容":"交通管理与控制，仔细听了金老师的课，可以发现金老师讲的真的很透彻很好，对于对交通感兴趣的同学还是非常适合的，金老师上课也非常耐心，讲课非常清晰，普通话可以用字正腔圆来形容了。"}],"gpa_info":[["交通工程","3.32","500+","0.85"],["交通管理与控制","3.40","144","0.78"]]},{"id":4242,"姓名":"欧阳润清","学院":"光电科学与工程学院","热度":551,"评分人数":17,"评分":8.4021,"拼音":"ouyangrunqing","拼音缩写":"oyrq","comments":[{"发表时间":"2018-01-28 14:41:15","点赞减去点踩数量":2,"点赞量":4,"点踩量":2,"内容":"睡了一学期"},{"发表时间":"2018-06-11 03:28:02","点赞减去点踩数量":0,"点赞量":3,"点踩量":3,"内容":"上课很水~但是最后给分很好~不知道别人咋样，看来作业认真完成+期末考稍微认真一点，就行啦"},{"发表时间":"2019-01-09 01:10:17","点赞减去点踩数量":0,"点赞量":2,"点踩量":2,"内容":"老师只给我们上了一次思修课 但是很有礼貌！"},{"发表时间":"2019-01-26 06:16:21","点赞减去点踩数量":0,"点赞量":2,"点踩量":2,"内容":"给分巨好么么哒"},{"发表时间":"2019-06-12 10:12:19","点赞减去点踩数量":-1,"点赞量":3,"点踩量":4,"内容":"作为辅导员，许多问题都不清楚，无法解决学生的问题就直接无视。"},{"发表时间":"2019-06-12 10:10:01","点赞减去点踩数量":4,"点赞量":8,"点踩量":4,"内容":"会做人"},{"发表时间":"2021-09-14 08:45:53","点赞减去点踩数量":-2,"点赞量":1,"点踩量":3,"内容":"老师人非常好，给分满满给，大家不要怕有雷，可以放心选。中国好老师！"},{"发表时间":"2021-11-13 06:45:40","点赞减去点踩数量":1,"点赞量":1,"点踩量":0,"内容":"职规给分不得行啊"},{"发表时间":"2021-11-17 09:20:08","点赞减去点踩数量":0,"点赞量":2,"点踩量":2,"内容":"老师人很好，课堂设计还是用心的，课上也有很多讨论时间，偶尔点名，而且因为是在玉泉开课，上课的都是大三大四养老人，展示没有很卷，总的来说这门课上的很舒适，给分也不错(相对于任务量来说)"},{"发表时间":"2021-12-28 00:07:34","点赞减去点踩数量":-1,"点赞量":0,"点踩量":1,"内容":"有一说一，理工男教思修真不咋样\\n\\n或者说，思修这门课就是恶心🤢"},{"发表时间":"2022-01-03 08:24:18","点赞减去点踩数量":0,"点赞量":0,"点踩量":0,"内容":"我的心中只有感恩"},{"发表时间":"2022-01-05 07:45:16","点赞减去点踩数量":0,"点赞量":0,"点踩量":0,"内容":"人好不好不清楚，事挺少适合养老，期末任务不重，最后给分也4.5也还行"},{"发表时间":"2022-01-06 08:01:55","点赞减去点踩数量":0,"点赞量":0,"点踩量":0,"内容":"相对于课程作业量，认真做了，分数也不错了"},{"发表时间":"2022-01-06 08:01:40","点赞减去点踩数量":0,"点赞量":0,"点踩量":0,"内容":"相对于课程作业量，认真做了，分数也不错了"},{"发表时间":"2022-01-06 08:21:43","点赞减去点踩数量":0,"点赞量":0,"点踩量":0,"内容":"事不多 给分行"},{"发表时间":"2022-01-07 15:22:41","点赞减去点踩数量":0,"点赞量":0,"点踩量":0,"内容":"还可以"},{"发表时间":"2022-01-08 06:28:57","点赞减去点踩数量":0,"点赞量":0,"点踩量":0,"内容":"职规事少分高，老师究极摸鱼"}],"gpa_info":[["思想道德与法治","4.14","77","0.56"],["思想道德修养与法律基础","3.82","164","0.44"],["职业生涯规划A","4.15","236","0.62"]]},{"id":4244,"姓名":"吕成祯","学院":"光电科学与工程学院","热度":662,"评分人数":0,"评分":0.0,"拼音":"lvchengzhen","拼音缩写":"lcz","comments":[],"gpa_info":[["形势与政策Ⅰ","4.05","294","0.48"]]},{"id":4245,"姓名":"王淼","学院":"人文学院","热度":13419,"评分人数":124,"评分":8.92276,"拼音":"wangmiao","拼音缩写":"wm","comments":[{"发表时间":"2018-02-01 05:46:08","点赞减去点踩数量":-6,"点赞量":2,"点踩量":8,"内容":"科技史，给分超棒！"},{"发表时间":"2018-07-05 12:24:01","点赞减去点踩数量":6,"点赞量":10,"点踩量":4,"内容":"不要选?，绩杀，认真和不认真的绩点都是一样的........"},{"发表时间":"2018-07-06 03:27:33","点赞减去点踩数量":5,"点赞量":17,"点踩量":12,"内容":"王淼老师有两个，上工程伦理导论的是人文学院，感觉很垃圾，每节课点名，一篇论文+一篇作文，加期末随堂考（开卷），很水，感觉什么都学不到，上课也没意思。"},{"发表时间":"2018-08-26 06:39:42","点赞减去点踩数量":-3,"点赞量":1,"点踩量":4,"内容":"还没有听过老师的课，但是觉得老师人特别亲善，很有耐心。"},{"发表时间":"2018-11-16 01:26:58","点赞减去点踩数量":4,"点赞量":14,"点踩量":10,"内容":"比较无聊，成绩正态分布，和平时努力不成正比"},{"发表时间":"2018-11-16 03:07:50","点赞减去点踩数量":-8,"点赞量":1,"点踩量":9,"内容":"科技史不错的，很有收获！"},{"发表时间":"2018-11-16 10:37:52","点赞减去点踩数量":-5,"点赞量":1,"点踩量":6,"内容":"还行的"},{"发表时间":"2018-11-16 11:48:01","点赞减去点踩数量":10,"点赞量":17,"点踩量":7,"内容":"什么都做 一节课没翘 绩点低的不行"},{"发表时间":"2018-11-17 01:56:10","点赞减去点踩数量":-6,"点赞量":1,"点踩量":7,"内容":"很有意思的体验，学到了许多预期之外的内容"},{"发表时间":"2018-11-17 05:59:46","点赞减去点踩数量":-8,"点赞量":6,"点踩量":14,"内容":"超棒 认真写论文 做小组展示 满绩前来感谢老师！"},{"发表时间":"2018-11-17 17:18:23","点赞减去点踩数量":0,"点赞量":9,"点踩量":9,"内容":"感觉老师人很好，讲课也比较清楚，就是进度比较慢\\n\\n作业是小组讨论展示+论文3000字+期末开卷考试 个人认为还是比较水的\\n\\n重点是给分超好！上课从没回答过问题，论文一天写完，居然绩点还有4.5，超级感动了！"},{"发表时间":"2018-11-19 08:54:53","点赞减去点踩数量":-1,"点赞量":3,"点踩量":4,"内容":"蛮轻松的 \\n\\n，老师人也很好，最后的考试很简单"},{"发表时间":"2018-11-20 09:00:01","点赞减去点踩数量":-3,"点赞量":3,"点踩量":6,"内容":"感觉老师很博学，认真听的话会学到许多东西，喜欢点名，整个秋学期好像只有一次没点名，最后一次的小测试很简单，是开卷，是真真正正意义上的开卷。"},{"发表时间":"2018-11-20 10:28:01","点赞减去点踩数量":-5,"点赞量":4,"点踩量":9,"内容":"上课内容充实，努力与收获成正比"},{"发表时间":"2018-11-22 05:31:29","点赞减去点踩数量":-2,"点赞量":6,"点踩量":8,"内容":"小组展示+3000字论文+完全开卷小测。没听过一节课，论文查资料水过去，小测多写了点，绩点4.5。老师人很温和，点了三四次名，虽然是水课。"},{"发表时间":"2019-01-20 16:28:59","点赞减去点踩数量":9,"点赞量":13,"点踩量":4,"内容":"正态分布卡绩"},{"发表时间":"2019-01-22 13:11:19","点赞减去点踩数量":4,"点赞量":10,"点踩量":6,"内容":"世界科技史，绩杀了。不过喜欢这门课就好。"},{"发表时间":"2019-01-23 16:33:22","点赞减去点踩数量":5,"点赞量":10,"点踩量":5,"内容":"讨论课展示+辩论赛辩手+每堂课都有去，居然只有3.3？？不能接受"},{"发表时间":"2019-01-23 16:41:28","点赞减去点踩数量":-1,"点赞量":5,"点踩量":6,"内容":"希望王淼老师。老师其实很用心了，工程伦理这一块也重在意见交流为主。研讨课还花钱给大家辩论赛买东西买奖品。给分也不错吧，想拿高分多在讨论课上发言吧。"},{"发表时间":"2019-01-24 23:28:42","点赞减去点踩数量":14,"点赞量":20,"点踩量":6,"内容":"瞎给分垃圾"},{"发表时间":"2019-06-01 12:07:16","点赞减去点踩数量":-1,"点赞量":8,"点踩量":9,"内容":"王淼老师很亲切呀，没有架子，脾气和修养都很好。"},{"发表时间":"2019-11-11 11:45:22","点赞减去点踩数量":7,"点赞量":10,"点踩量":3,"内容":"自然辨证法咋不写个脚本给分呢？真没见过这么垃圾的老师"},{"发表时间":"2019-09-25 10:15:31","点赞减去点踩数量":11,"点赞量":13,"点踩量":2,"内容":"...别搞混了"},{"发表时间":"2019-11-11 01:07:05","点赞减去点踩数量":1,"点赞量":9,"点踩量":8,"内容":"科技史。本人上课不听，点名答道。论文要求3000字我写了3200左右，期末选择题很简单，对于选考历史100无障碍（手动狗头，论述题和高中难度相比相差不大，最终4.5。虽然很开心，但。。评分很迷完全不像是一个不听的人该有的。个人案例，仅供参考。"},{"发表时间":"2019-11-11 04:01:04","点赞减去点踩数量":-1,"点赞量":6,"点踩量":7,"内容":"虽然上课水但考试更水，水了一学期什么都没听都有4.5，虽然上课无聊但你给我4.5我就给你10分吧"},{"发表时间":"2019-11-11 04:35:23","点赞减去点踩数量":-3,"点赞量":2,"点踩量":5,"内容":"有好几次点名，事不算很多，上课有点无聊。不过总体不算是很难的课，老师气质也很好，最后给分也还可以。"},{"发表时间":"2019-11-11 06:26:05","点赞减去点踩数量":-2,"点赞量":1,"点踩量":3,"内容":"真的水，讲课无聊的很，感觉所有人都是一直水课的。当然，主要是小组展示要用心，这个很重要，最后的开卷考试真的简单的一批，题少不说，也没有难度，我专门为考试买了课本教材，结果……确实很容易找到答案，但这个你相互传答案也不难，只有老师和助教两个人盯着，觉得买教材有些不值? 。选课在教务网上选教材会发现根本没有，当时老师推荐了几本可以作为教材的书，我是在网上找了个电子书，还可以。有几次课会点名，随机的，不要翘就好了。老师讲课还不错，但是真无聊。感觉绩点就是靠小组展示，我们小组很强的，读书报告我直接写成了读后感，课一直水，试随便考，最后拿了一个4.5。(话说感觉好多4.5啊)"},{"发表时间":"2019-11-13 05:50:41","点赞减去点踩数量":-3,"点赞量":4,"点踩量":7,"内容":"傻逼一个，成绩随便给"},{"发表时间":"2019-11-11 08:53:59","点赞减去点踩数量":-1,"点赞量":1,"点踩量":2,"内容":"科技史，上课挺催眠的，事不多还行，小组展示和读书报告，期末课堂小测开卷，一共点过三次名"},{"发表时间":"2019-11-12 13:22:57","点赞减去点踩数量":-1,"点赞量":5,"点踩量":6,"内容":"科技史绩点4.5  课从来没听过，基本就是去那上自习，中间会有随机几次点名，小组展示我们做得很糟，但是只要认真写论文，考试好好考，在答案中多表达自己（强调）的观点应该就没问题。\\n\\n水课，特别水"},{"发表时间":"2019-11-13 05:22:52","点赞减去点踩数量":-1,"点赞量":1,"点踩量":2,"内容":"嘎嘎嘎嘎"},{"发表时间":"2019-11-13 05:49:54","点赞减去点踩数量":0,"点赞量":5,"点踩量":5,"内容":"世界科技史。我为王老师打9分。\\n\\n首先，课程本身来说比较吸引人。世界科技史不仅仅关注多次科技进步的史实和高超的科学理念，还会介绍某个理论提出时的时代背景，介绍其历史渊源。但本课程并不会深入讲解或推导某个理论，也就是说，课程注重的是史实。课程本身有助于我们了解科学，以及从科学家们身上学习科学知识、总结探索科学的方法，是一门具有浓烈理科色彩的文科类课程。期末考试是开卷考，选择题全部在《世界科技史》这本教材上。最后的论述题可以选择两道去作答。题目有的是老师课上布置过的讨论题，有的是让论述关于这门课的看法。总体不难，但题目分值极大。\\n\\n其次，王老师很和蔼，不发火，且对学生的提出的问题会很上心，不会责怪学生。某几次课快要下课时会以增进与同学们的了解为理由进行点名。但他的讲课确实比较平淡，换言之就是无聊。当然如果你对这方面很感兴趣，也乐意听老师讲课的话，你感到无聊的频率会下降。\\n\\n老师会安排小组展示，冠名为世界科技史论坛。这个名额有限，建议抢先。\\n\\n王老师不会将历史讲得生动有趣，他更多地会进行历史陈述，所以会令人犯困。但老师讲课确实很认真，品味其词句的话，也会有很多逻辑严明之处。\\n\\n教室前面座位空余还是蛮多的，建议想要绩点的同学坐到前面听讲。\\n\\n不建议做笔记（而且你抄不下来）。我做了，但考试没用到。可能日后会有用吧。\\n\\n课程作业是一篇3000字以上的论文，要求读科学原著或科技史著作，写感想。这个不要糊弄，因为这是绩点的主要来源之一。\\n\\n注意随堂表现，才能保证有足够的绩点。这种谁都会犯困的课程，只要认真坚持，多互动，就可以保证得高绩点。老师会很在意那些积极表现的同学。不听讲很难保不会被正态。\\n\\n以上是我认真听完每一堂课后的真实感受。供大家参考。"},{"发表时间":"2019-11-13 10:32:10","点赞减去点踩数量":-1,"点赞量":2,"点踩量":3,"内容":"自习课，但是成绩很惊喜啊"},{"发表时间":"2019-11-14 14:20:09","点赞减去点踩数量":-2,"点赞量":1,"点踩量":3,"内容":"喜欢科技史的话会学到很多东西的，虽然很多人说无聊，但我真的觉得挺有意思的，看科技史名著也收获很多呀"},{"发表时间":"2019-11-17 01:59:10","点赞减去点踩数量":11,"点赞量":14,"点踩量":3,"内容":"老师讲课还行，就是给分有点迷……\\n\\n不缺勤+积极参与科技史论坛+3000论文+完全开卷选择题\\n\\n然后他给了我3.3……\\n\\n这里吐槽一下有个题选项a春秋b战国，结果我一翻书书里写的春秋战国\\n\\n真的无爱了\\n\\n是我论文写的不够好还是我考试论述题答得不够深刻？"},{"发表时间":"2019-12-15 17:26:32","点赞减去点踩数量":-3,"点赞量":0,"点踩量":3,"内容":"很儒雅的一个老师。课程内容可能有点无聊，但是认真听课，作业考试仔细思考绩点还是可以的。"},{"发表时间":"2020-02-24 04:06:09","点赞减去点踩数量":-3,"点赞量":2,"点踩量":5,"内容":"工程伦理导论，平时不是很积极没怎么听，好好写了论文考了期末，就突然满了…"},{"发表时间":"2020-07-28 03:12:06","点赞减去点踩数量":6,"点赞量":7,"点踩量":1,"内容":"搞一堆东西，分小组讨论，当小组长+全勤评分还很差"},{"发表时间":"2020-10-28 10:45:16","点赞减去点踩数量":3,"点赞量":6,"点踩量":3,"内容":"世界科学技术史。本来听完第一节课，看这任务量就想退了来着，但是想着反正通识就差一门，忍一忍就过去了。劝千万别选这课，事情太多了，完全不是1.5的学分的通识课该做的。又要小组展示，又要写论文，又要每节课点到，又要期末考试，最恶心的是有节课突然说加作业（第一节讲绩点的时候根本没提到，ppt里也没有），一周写一篇1000+小论文，然后把分算在课堂表现里。我感觉不管讲的咋样，都挺烦的，太把自己当回事了。本来就是一节通识课，竟然比专业课还有军理马原还要占用更多时间，被恶心到了，直接给2分，不给1分是给助教小姐姐的面子。"},{"发表时间":"2020-11-11 12:35:08","点赞减去点踩数量":-1,"点赞量":3,"点踩量":4,"内容":"工程伦理导论今天结课了，感觉还好，不知道分会怎么样。在分出以前先评价一下王老师。我挺喜欢这样的老师，讲课很细致，ppt做的很好，王老师人也很和蔼，讨论课时做一些其他的事情也不会管（不知道会不会扣分），讨论课在台上发言被同学的刁钻问题难到后王老师会解围。最终的考试题也很简单（虽然我不咋会），助教小姐姐也超级好，考试结束后会给我们鼓励（以及红包）。参考以前评论说给分很迷，我只能希望自己是个欧皇了……"},{"发表时间":"2020-11-23 11:24:18","点赞减去点踩数量":30,"点赞量":33,"点踩量":3,"内容":"我永远单推助教小姐姐。"},{"发表时间":"2020-11-28 02:44:39","点赞减去点踩数量":-2,"点赞量":3,"点踩量":5,"内容":"自习一学期，只要论文有观点，小组展示好好做，期末考试真的都是常识题，不错的水课"},{"发表时间":"2020-11-28 03:26:49","点赞减去点踩数量":-3,"点赞量":3,"点踩量":6,"内容":"工程伦理导论\\n\\n水课\\n\\n期末考试很水大家基本都全对应该，要写一篇论文\\n\\n感觉绩点可能主要跟论文有关？\\n\\n最后89 4.5\\n\\n感觉作为一门水课的话还挺好的"},{"发表时间":"2020-11-28 03:51:33","点赞减去点踩数量":10,"点赞量":15,"点踩量":5,"内容":"论文用心写，上课积极回答问题，每次都去问问题，结果3.3"},{"发表时间":"2020-11-28 16:58:17","点赞减去点踩数量":-2,"点赞量":3,"点踩量":5,"内容":"工程伦理导论\\n\\n我又来了……总分89，4.5\\n\\n怎么说呢，论文要求三千字，我写了四千多……\\n\\n正课很水，讨论课也……没啥事\\n\\n只要论文好好写，最后开卷考试好好写，把空写满（23333……）应该就可以了……\\n\\n总体感觉还不错吧"},{"发表时间":"2020-12-01 06:54:42","点赞减去点踩数量":1,"点赞量":4,"点踩量":3,"内容":"平时表现是没有记录的，大家基本的都做得到，绩杀3.3，正态早已预料"},{"发表时间":"2020-12-01 07:57:00","点赞减去点踩数量":1,"点赞量":4,"点踩量":3,"内容":"绩点极低 乱给分 吓死个人 吐了"},{"发表时间":"2020-12-02 10:10:40","点赞减去点踩数量":0,"点赞量":4,"点踩量":4,"内容":"没话说的垃圾"},{"发表时间":"2020-12-02 10:05:38","点赞减去点踩数量":-2,"点赞量":5,"点踩量":7,"内容":"无敌大nt老师，看心情给分？这一分当我送给助教小姐姐的了，你想拿分？不存在的！"},{"发表时间":"2020-12-13 13:44:47","点赞减去点踩数量":0,"点赞量":2,"点踩量":2,"内容":"垃圾"},{"发表时间":"2020-12-23 09:43:07","点赞减去点踩数量":-6,"点赞量":3,"点踩量":9,"内容":"我挺喜欢这节课的，老师给人一种很温和儒雅的感觉，一直很有耐心。"},{"发表时间":"2021-07-16 09:05:14","点赞减去点踩数量":-3,"点赞量":2,"点踩量":5,"内容":"老师稍微对教学上上心，也不至于作业全是别的学校的"},{"发表时间":"2021-07-19 02:22:39","点赞减去点踩数量":-4,"点赞量":0,"点踩量":4,"内容":"下面那个评价成别的老师了，报歉"},{"发表时间":"2021-11-17 01:50:31","点赞减去点踩数量":1,"点赞量":2,"点踩量":1,"内容":"啊，我没有很认真听，但考试真不难，论文好好写就行，给分还可以，4.5挺好了"},{"发表时间":"2021-11-17 07:54:19","点赞减去点踩数量":0,"点赞量":2,"点踩量":2,"内容":"今天出成绩了！！好开心居然是满绩！！论文要求三千左右我写了四千，最后开卷考就努力把论述题答满就好了！我太爱老师了！！！"},{"发表时间":"2021-11-17 02:00:25","点赞减去点踩数量":11,"点赞量":11,"点踩量":0,"内容":"的确是给分比较随缘，很多认真的人3.3，水课的4.5+的也有，毕竟一个短学期的1.5学分的通识课老师不能充分了解你，只能单纯的从论文&期末考试来给分。所以选上工程伦理导论的我还是推荐上课就随便听一听（自习），论文好好写，期末考把8个ppt过一遍就完事了。"},{"发表时间":"2021-11-17 03:08:59","点赞减去点踩数量":1,"点赞量":2,"点踩量":1,"内容":"第二次选老师的课了，这次选的是工程伦理，课业任务不太重，基本就是一篇论文+开卷考（ppt上基本都有），老师讲的也很好"},{"发表时间":"2021-11-17 05:25:44","点赞减去点踩数量":3,"点赞量":4,"点踩量":1,"内容":"上课很自由可以做自己想做的，最后开卷考也很轻松，今天刚出成绩满绩，直接10分了"},{"发表时间":"2021-11-17 06:18:12","点赞减去点踩数量":1,"点赞量":1,"点踩量":0,"内容":"怎么说？论文写了偏向专业性的，小组论坛全程一个人做，绩点不高不低，啥也没学到，凑个学分吧。很中庸的老师"},{"发表时间":"2021-11-17 09:16:07","点赞减去点踩数量":2,"点赞量":2,"点踩量":0,"内容":"非常好的老师 人特别耐心 好好听其实可以学到很多"},{"发表时间":"2021-11-17 12:11:16","点赞减去点踩数量":11,"点赞量":11,"点踩量":0,"内容":"很棒的老师，很细心耐心，课时有点多（但都挺轻松的）。助教可好了，最后一节课还发糖\\n\\n了。安利一波～"},{"发表时间":"2021-11-17 23:53:51","点赞减去点踩数量":0,"点赞量":0,"点踩量":0,"内容":"平时摸鱼最后成绩不错的选手 给分不错 上课很水 讨论课更水…考试很简单"},{"发表时间":"2021-11-18 14:10:04","点赞减去点踩数量":18,"点赞量":19,"点踩量":1,"内容":"助教小姐姐是天使吧！赞美一万句！"},{"发表时间":"2021-11-22 09:56:45","点赞减去点踩数量":-1,"点赞量":0,"点踩量":1,"内容":"作业很少 老师很儒雅"},{"发表时间":"2021-12-21 03:33:42","点赞减去点踩数量":0,"点赞量":0,"点踩量":0,"内容":"给分还可以"},{"发表时间":"2022-11-16 03:45:46","点赞减去点踩数量":0,"点赞量":0,"点踩量":0,"内容":"出分啦，绩点和想象中的差不多，而且王淼老师确实是一个十分儒雅随和的人。"},{"发表时间":"2022-11-16 09:39:48","点赞减去点踩数量":-1,"点赞量":1,"点踩量":2,"内容":"世界科学技术史全程上课做别的作业，写简单的论文，一个小组讨论就满绩啦，建议建议～"},{"发表时间":"2022-11-16 12:44:22","点赞减去点踩数量":0,"点赞量":0,"点踩量":0,"内容":"给满绩，吹爆"},{"发表时间":"2022-11-17 14:57:02","点赞减去点踩数量":1,"点赞量":1,"点踩量":0,"内容":"满级大爱"},{"发表时间":"2022-11-18 02:14:20","点赞减去点踩数量":0,"点赞量":0,"点踩量":0,"内容":"工程伦理导论满绩。老师很儒雅，助教姐姐很棒，组员也很好。\\n\\n很棒的通识课体验。"},{"发表时间":"2022-12-19 12:57:11","点赞减去点踩数量":1,"点赞量":1,"点踩量":0,"内容":"王淼老师人很好，十分和蔼，给分也不错。下课之后可以和他讨论，从日常生活到哲学思辩，老师都会和你聊，很耐心。\\n\\n世界科学技术史这门课主要任务是期中一篇论文、小组展示、期末开卷考试（论述题），其实还好。\\n\\n课堂会点名，课上要是想水也可以比较水。唯一一点有些不足的地方就是很多人感觉讲课略显沉闷，不过这个就见仁见智了。"},{"发表时间":"2023-09-07 09:09:59","点赞减去点踩数量":1,"点赞量":1,"点踩量":0,"内容":"好人一生平安"},{"发表时间":"2023-11-20 09:36:15","点赞减去点踩数量":2,"点赞量":2,"点踩量":0,"内容":"不多说 感恩老师"},{"发表时间":"2023-11-20 10:52:27","点赞减去点踩数量":1,"点赞量":1,"点踩量":0,"内容":"4.5"},{"发表时间":"2023-11-20 11:49:48","点赞减去点踩数量":5,"点赞量":5,"点踩量":0,"内容":"虽然上课讲的内容和成绩无关，但只要把论文好好写居然拿了满绩，太惊喜了！强推！老师特别棒！！"},{"发表时间":"2023-11-20 14:46:17","点赞减去点踩数量":1,"点赞量":1,"点踩量":0,"内容":"大爹没商量"},{"发表时间":"2023-11-20 15:16:44","点赞减去点踩数量":7,"点赞量":7,"点踩量":0,"内容":"简评世界科学技术史\\n\\n王老师儒雅随和，气质甚佳，对待同学们也十分亲切。备课讲课很认真。课程本身则是偏向于介绍历史，稍显枯燥，但有兴趣了解的同学还是非常值得一上的。\\n\\n2023年作业是一大一小两个论文，无期末考试，无pre，任务量不算大。\\n\\n给分的话主要看你3000大论文的质量。我想认真写的同学不会很差的。\\n\\n总之我认为属于事少分高类的通识课（以上所述仅代表个人观点，不同同学的感受并不一样，尤其给分方面还是会有一定的随机性）"},{"发表时间":"2023-11-21 06:36:11","点赞减去点踩数量":3,"点赞量":3,"点踩量":0,"内容":"上个很无聊但是超级水，事很少，平常上课和讨论课水水就行，期末就一次小作业和一篇论文，给分很好"},{"发表时间":"2023-11-21 06:36:31","点赞减去点踩数量":2,"点赞量":2,"点踩量":0,"内容":"你给我满级，我给你满分"},{"发表时间":"2023-11-22 08:38:50","点赞减去点踩数量":2,"点赞量":2,"点踩量":0,"内容":"上课不用听，讨论课一次发言，期末一天速通所有作业，分不低"},{"发表时间":"2023-11-22 11:26:45","点赞减去点踩数量":3,"点赞量":3,"点踩量":0,"内容":"老师非常的敬业，嗓子哑了依然坚持给我们上课。看得出来老师也在尽自己最大的努力传授给我们这个有些枯燥的学科的知识了，老师的课上的很好，人也很好，讨论课氛围也不错。给分很棒，没平时作业，最后写论文就可以啦，夸爆！！！"},{"发表时间":"2023-11-24 05:13:45","点赞减去点踩数量":1,"点赞量":1,"点踩量":0,"内容":"好老师，事少，给分好"},{"发表时间":"2023-11-26 08:50:12","点赞减去点踩数量":0,"点赞量":0,"点踩量":0,"内容":"事少分高，老师很儒雅，人挺好的"},{"发表时间":"2023-11-27 00:09:05","点赞减去点踩数量":0,"点赞量":0,"点踩量":0,"内容":"5.0"},{"发表时间":"2023-11-28 08:13:02","点赞减去点踩数量":0,"点赞量":0,"点踩量":0,"内容":"工程伦理B事少分高，选！"},{"发表时间":"2023-12-06 06:40:13","点赞减去点踩数量":1,"点赞量":1,"点踩量":0,"内容":"天天点名闲死了"},{"发表时间":"2023-12-12 05:11:26","点赞减去点踩数量":0,"点赞量":1,"点踩量":1,"内容":"工程伦理导论，老师讲课比较中规中矩，不能说很有趣，但内容也挺丰富的，偶尔会点名，给分的话主要看小作业和论文。"},{"发表时间":"2023-12-27 02:35:28","点赞减去点踩数量":1,"点赞量":1,"点踩量":0,"内容":"课有点无聊但是王老师真的很敬业，问一些傻傻的问题老师也会很耐心地回答，小组讨论其实还蛮有意思的，对于专业知识要求并不高，只要群策群力积极参与就行，吹爆助教小姐姐！温柔漂亮而且超级有耐心！"},{"发表时间":"2023-12-27 05:12:41","点赞减去点踩数量":1,"点赞量":1,"点踩量":0,"内容":"世界科学技术史课水，分高，只用写一次论文和一次感想。但一定要去，偶尔会点名"},{"发表时间":"2024-05-13 09:13:15","点赞减去点踩数量":0,"点赞量":0,"点踩量":0,"内容":"工程伦理导论，全用来写当天其他课作业，讨论课一学期发一次言，剩余时间自由，给分不错"},{"发表时间":"2024-05-16 10:29:58","点赞减去点踩数量":1,"点赞量":1,"点踩量":0,"内容":"事少分高"},{"发表时间":"2024-11-04 04:39:15","点赞减去点踩数量":0,"点赞量":0,"点踩量":0,"内容":"good"},{"发表时间":"2024-11-09 08:01:48","点赞减去点踩数量":4,"点赞量":5,"点踩量":1,"内容":"这个老师真的难评，真不好说。事情真多，1学分的自然辩证法这个老师跟10个学分一样，又是要求课程讨论展示又是要求看文献写论文又是要求课程考试，还要求每节课都要到，别太离谱。比起其他老师只需要考试，我的建议是千万别选，谁选谁后悔"},{"发表时间":"2024-11-12 23:42:40","点赞减去点踩数量":3,"点赞量":4,"点踩量":1,"内容":"世界科学技术史事少给分超级好"},{"发表时间":"2024-11-13 00:52:32","点赞减去点踩数量":1,"点赞量":1,"点踩量":0,"内容":"工程伦理导论事少分高！"},{"发表时间":"2024-11-13 02:50:07","点赞减去点踩数量":2,"点赞量":2,"点踩量":0,"内容":"超级棒的老师"},{"发表时间":"2024-11-13 03:02:40","点赞减去点踩数量":3,"点赞量":3,"点踩量":0,"内容":"事少分高 世界科学技术史只要3000字论文写好就行"},{"发表时间":"2024-11-13 07:47:36","点赞减去点踩数量":4,"点赞量":4,"点踩量":0,"内容":"世界科学技术史事少分高，无脑可冲！"},{"发表时间":"2024-11-13 10:41:04","点赞减去点踩数量":1,"点赞量":1,"点踩量":0,"内容":"工程伦理导论事少分高无脑选就完了"},{"发表时间":"2024-11-13 11:17:32","点赞减去点踩数量":2,"点赞量":2,"点踩量":0,"内容":"很好的老师，选上就是幸福了"},{"发表时间":"2024-11-14 09:50:07","点赞减去点踩数量":2,"点赞量":2,"点踩量":0,"内容":"非常好的老师，不管是上课内容，还是最后的给分！"},{"发表时间":"2024-11-15 15:21:27","点赞减去点踩数量":1,"点赞量":1,"点踩量":0,"内容":"事少分高"},{"发表时间":"2024-11-16 12:17:33","点赞减去点踩数量":5,"点赞量":5,"点踩量":0,"内容":"世界科学技术史，事少分高，课是不听的，老师是温柔的，论文写了的，分是高的"},{"发表时间":"2024-11-18 07:22:25","点赞减去点踩数量":1,"点赞量":1,"点踩量":0,"内容":"超温柔老师，课可以选听，事少，只有一个思考题和一篇论文，给分很好，真的很好，论文好好写就能拿高分"},{"发表时间":"2024-11-19 05:19:46","点赞减去点踩数量":3,"点赞量":3,"点踩量":0,"内容":"世界科学技术史选爆！事少分高！！"},{"发表时间":"2024-11-21 01:53:39","点赞减去点踩数量":0,"点赞量":0,"点踩量":0,"内容":"工程伦理导论无脑选"},{"发表时间":"2024-12-12 03:34:42","点赞减去点踩数量":0,"点赞量":0,"点踩量":0,"内容":"事少分高"}],"gpa_info":[["世界科学技术史","4.39","486","0.55"],["大学物理（甲）Ⅰ","3.15","500+","1.08"],["工程伦理导论","4.45","53","0.54"],["工程伦理导论(B)","4.40","325","0.54"],["毕业实习","4.36","19","0.34"],["毕业论文","4.15","20","0.38"],["社会实践","4.18","22","0.48"],["社会调查","4.63","21","0.52"]]},{"id":4246,"姓名":"任凭","学院":"马克思主义学院","热度":67,"评分人数":0,"评分":0.0,"拼音":"renping","拼音缩写":"rp","comments":[],"gpa_info":[["习近平新时代中国特色社会主义思想概论","4.15","500+","0.36"],["毛泽东思想和中国特色社会主义理论体系概论","3.92","500+","0.52"]]},{"id":4247,"姓名":"朱绍鹏","学院":"控制科学与工程学院","热度":202,"评分人数":0,"评分":0.0,"拼音":"zhushaopeng","拼音缩写":"zsp","comments":[],"gpa_info":[["新能源汽车动力系统","3.77","65","0.58"],["新能源汽车技术","4.28","113","0.57"],["汽车导论","4.41","144","0.34"],["汽车工程导论","4.66","23","0.32"],["汽车电子与控制","3.76","130","0.71"],["现代电动汽车技术","4.14","23","0.59"],["自动控制理论","3.46","148","0.85"]]},{"id":4248,"姓名":"童水光","学院":"机械工程学院","热度":7330,"评分人数":9,"评分":4.16589,"拼音":"tongshuiguang","拼音缩写":"tsg","comments":[{"发表时间":"2018-05-07 17:24:33","点赞减去点踩数量":-1,"点赞量":1,"点踩量":2,"内容":"有毒，减速器也小越好，材料越差越好，你有这要求早说啊!!答辩时候才说恶心。固有频率，nmbiu~"},{"发表时间":"2019-03-01 01:32:46","点赞减去点踩数量":2,"点赞量":3,"点踩量":1,"内容":"讲课前先练练普通话行不行"},{"发表时间":"2019-04-28 08:10:07","点赞减去点踩数量":-4,"点赞量":3,"点踩量":7,"内容":"好好好"},{"发表时间":"2021-05-11 03:01:59","点赞减去点踩数量":1,"点赞量":2,"点踩量":1,"内容":"狗 太狗了\\n\\n选他的课就是听他的助教余跃给你讲给你打分\\n\\n课程上完了拖两个星期才出成绩\\n\\n然后又他妈的改规则\\n\\n直接给大家伙平时成绩降低\\n\\n比原先的规则降了0.6个绩点\\n\\n傻逼才选他的课"},{"发表时间":"2022-04-27 11:03:44","点赞减去点踩数量":-1,"点赞量":5,"点踩量":6,"内容":"助教是余跃老师。大部分时间给同学自己看书，有问题再去提问，课程不臃肿。认可鼓励同学的创新尝试。给分很高(A+ 5.0)"},{"发表时间":"2025-02-26 06:30:33","点赞减去点踩数量":2,"点赞量":2,"点踩量":0,"内容":"上课不讲课程内容，一张PPT放一个小时大谈中美关系、世界局势、经济发展，反复说自己在清华待过，吐槽评院士，说自己不爱去参加评奖，说北方人“闲”肯定会去参加评奖balabala……"},{"发表时间":"2025-03-08 13:14:49","点赞减去点踩数量":0,"点赞量":0,"点踩量":0,"内容":"一坨答辩，做他的研究生可能三年见不到本尊，已经两年没开组会了，都他儿子管，他儿子更是重量级。。。。反正就是一坨稀"}],"gpa_info":[["机械设计课程设计（甲）","3.99","244","0.66"]]},{"id":4249,"姓名":"沈志坤","学院":"光华法学院","热度":121,"评分人数":0,"评分":0.0,"拼音":"shenzhikun","拼音缩写":"szk","comments":[],"gpa_info":[]},{"id":4250,"姓名":"喻洁","学院":"控制科学与工程学院","热度":6271,"评分人数":25,"评分":5.18054,"拼音":"yujie","拼音缩写":"yj","comments":[{"发表时间":"2018-06-13 04:56:54","点赞减去点踩数量":0,"点赞量":1,"点踩量":1,"内容":"老拖堂"},{"发表时间":"2021-04-15 06:43:27","点赞减去点踩数量":0,"点赞量":4,"点踩量":4,"内容":"差劲，差劲，差劲，布置作业一点数都没有，截止时间迷得很，中午的ddl，下午还有课，选了就要准备好不吃饭"},{"发表时间":"2021-06-17 15:41:17","点赞减去点踩数量":0,"点赞量":2,"点踩量":2,"内容":"快逃（"},{"发表时间":"2021-06-23 11:11:42","点赞减去点踩数量":1,"点赞量":5,"点踩量":4,"内容":"张光新的点名提问工具人。"},{"发表时间":"2021-07-13 11:26:23","点赞减去点踩数量":0,"点赞量":1,"点踩量":1,"内容":"课程内容完全配得上10分前面这个“1”，就是配不上后面那个“0”。"},{"发表时间":"2022-07-15 04:28:04","点赞减去点踩数量":1,"点赞量":2,"点踩量":1,"内容":"挺好的老师，可能是之前给zgx当工具人把风评搞坏了吧"},{"发表时间":"2023-03-09 02:24:19","点赞减去点踩数量":0,"点赞量":1,"点踩量":1,"内容":"sb666"},{"发表时间":"2023-06-15 02:23:25","点赞减去点踩数量":0,"点赞量":2,"点踩量":2,"内容":"纯纯nt，讲课一坨垃圾，还对学生有偏见，高高在上"},{"发表时间":"2023-06-15 02:23:34","点赞减去点踩数量":0,"点赞量":1,"点踩量":1,"内容":"离大谱，老师自己身为女性，对女学生的偏见还那么大😅😅😅"},{"发表时间":"2023-07-12 06:29:35","点赞减去点踩数量":2,"点赞量":2,"点踩量":0,"内容":"还可以吧，cmc班事情略多，给分一般性，也不算是特别差的老师"},{"发表时间":"2023-07-12 06:45:48","点赞减去点踩数量":0,"点赞量":2,"点踩量":2,"内容":"中规中矩吧，平时基本不点名也很少提问。给分的话感觉略求是，计控期末考完不难，但感觉身边人最后总评都很一般。"},{"发表时间":"2023-07-22 13:02:10","点赞减去点踩数量":3,"点赞量":3,"点踩量":0,"内容":"老师讲的也还行，事情一般般（比隔壁副院长班要少一些），就这课安排怪怪的，给分也还行"},{"发表时间":"2023-09-14 12:00:47","点赞减去点踩数量":0,"点赞量":5,"点踩量":5,"内容":"想打电话咨询一下，结果她超级不耐烦，5秒之内给挂了，无语，很难评！！！"},{"发表时间":"2024-08-09 15:39:59","点赞减去点踩数量":3,"点赞量":3,"点踩量":0,"内容":"个人感觉是计控的几个平行班内事情最少的，平常上课也基本上是放的最早的，给分个人感觉还凑合，对于计控这门课来说是推荐选的"}],"gpa_info":[["Chemical Engineering Automation & Instrumentation","3.53","97","0.70"],["计算机控制系统设计与实践","4.13","343","0.59"]]},{"id":4251,"姓名":"张新樟","学院":"马克思主义学院","热度":86,"评分人数":0,"评分":0.0,"拼音":"zhangxinzhang","拼音缩写":"zxz","comments":[],"gpa_info":[["中国特色社会主义宗教理论与实践","3.90","33","0.87"],["马克思主义基本原理概论","3.74","210","0.93"]]},{"id":4252,"姓名":"张宏建","学院":"控制科学与工程学院","热度":2587,"评分人数":4,"评分":0.0,"拼音":"zhanghongjian","拼音缩写":"zhj","comments":[{"发表时间":"2021-11-19 02:24:44","点赞减去点踩数量":3,"点赞量":4,"点踩量":1,"内容":"什么玩意"},{"发表时间":"2021-11-19 02:29:40","点赞减去点踩数量":0,"点赞量":2,"点踩量":2,"内容":"上课点人回答思考题：我觉得你声音不够洪亮；我觉得你准备的挺好，为啥不脱稿…"},{"发表时间":"2022-07-22 08:38:52","点赞减去点踩数量":0,"点赞量":1,"点踩量":1,"内容":"上他的课很难发现他就是学校副校长，平易近人，不过他基本只上几节课，分也不是他给的"},{"发表时间":"2024-09-13 04:07:40","点赞减去点踩数量":5,"点赞量":5,"点踩量":0,"内容":"鼓励发言内卷 这种课有什么好发言的我请问"}],"gpa_info":[["传感与检测","3.91","360","0.65"]]},{"id":4253,"姓名":"金毅","学院":"光电科学与工程学院","热度":5172,"评分人数":24,"评分":7.56344,"拼音":"jinyi","拼音缩写":"jy","comments":[{"发表时间":"2018-03-16 02:19:18","点赞减去点踩数量":4,"点赞量":6,"点踩量":2,"内容":"因为课程本来就比较乏味，老师讲的也很乏，建议自学PPT。"},{"发表时间":"2018-03-29 10:55:57","点赞减去点踩数量":-2,"点赞量":3,"点踩量":5,"内容":"nice"},{"发表时间":"2018-04-17 04:19:51","点赞减去点踩数量":-5,"点赞量":2,"点踩量":7,"内容":"老师说实在人很好，有问必答，但关键这门课真的入门难，同学的展示...被老师经常指出错误很尴尬也难免。"},{"发表时间":"2018-05-16 05:17:09","点赞减去点踩数量":11,"点赞量":13,"点踩量":2,"内容":"严肃脸，枯燥不走心\\n\\n文献出成绩慢加绩杀"},{"发表时间":"2018-05-16 08:32:03","点赞减去点踩数量":0,"点赞量":6,"点踩量":6,"内容":"上课无聊，但其实人挺好"},{"发表时间":"2018-05-17 06:41:18","点赞减去点踩数量":3,"点赞量":6,"点踩量":3,"内容":"呵呵呵"},{"发表时间":"2018-05-17 07:45:21","点赞减去点踩数量":11,"点赞量":12,"点踩量":1,"内容":"一夜打回解放前。绩杀"},{"发表时间":"2018-12-04 17:55:37","点赞减去点踩数量":-1,"点赞量":5,"点踩量":6,"内容":"上课枯燥乏味\\n\\n留作业不动脑子\\n\\n有问必答也挽回不了他脑子有坑这个事实\\n\\n一个文献导入的作业留了一周\\n\\n然后任务量更大的文献翻译给了2天，还不是周末\\n\\n我就想知道这是一般老师能做出来的操作?\\n\\n弱智老师讲的智障课程，慎选"},{"发表时间":"2019-03-04 00:59:31","点赞减去点踩数量":1,"点赞量":4,"点踩量":3,"内容":"垃圾老师，我们组我学的最累，啥都是我干的，3.3"},{"发表时间":"2021-05-21 10:03:43","点赞减去点踩数量":1,"点赞量":6,"点踩量":5,"内容":"冲着满了来感谢一下金老师，有一说一确实作业多任务重，本学期最累的课了......"},{"发表时间":"2021-12-22 15:01:11","点赞减去点踩数量":0,"点赞量":1,"点踩量":1,"内容":"还行吧"},{"发表时间":"2022-04-22 04:19:36","点赞减去点踩数量":4,"点赞量":6,"点踩量":2,"内容":"老师非常认真负责，讲得也很透，离散数学讲得非常好！"},{"发表时间":"2022-06-22 09:08:10","点赞减去点踩数量":-8,"点赞量":3,"点踩量":11,"内容":"不会教别教 出来祸害人"},{"发表时间":"2022-06-22 12:23:24","点赞减去点踩数量":5,"点赞量":7,"点踩量":2,"内容":"认真负责的好老师，离散讲得很透。"},{"发表时间":"2023-03-24 00:12:51","点赞减去点踩数量":0,"点赞量":0,"点踩量":0,"内容":"老师人还行"},{"发表时间":"2023-06-26 00:56:04","点赞减去点踩数量":3,"点赞量":3,"点踩量":0,"内容":"离散考前一小时来评，个人觉得老师讲的很透彻以至于有的时候觉得废话太多了（真的很不好意思），从老师上课的态度和在钉钉群提醒大家注意的问题以及我个人问老师问题老师的回复来看，老师可以说是真的很用心，就是上课有点口音，但是觉得完全可以接受，最后老师离散给我个高分吧呜呜呜"},{"发表时间":"2023-06-26 06:26:12","点赞减去点踩数量":2,"点赞量":2,"点踩量":0,"内容":"老师是好老师，很负责任又很有分寸"},{"发表时间":"2023-07-06 02:30:32","点赞减去点踩数量":2,"点赞量":2,"点踩量":0,"内容":"离散讲课清晰，给分好"},{"发表时间":"2023-07-11 04:32:28","点赞减去点踩数量":4,"点赞量":5,"点踩量":1,"内容":"不管其他课上得怎么样，离散这门课我必须要打10分。讲课清晰是一方面，更重要的是给分极好！整个大学四年都没有这样一个课，让我觉得要挂科了结果4.5的！是这样的，我前面认真学了三章然后后面就不想听了，再加上期末考试和别的科目重合，当时心态快炸了，后面零基础全靠一个晚上通宵复习，最后第九第十章都没学。结果发现考的很简单，但是估分是只有3.3左右，结果出来简直把我惊掉下巴了，4.5啊！4.5啊！"},{"发表时间":"2023-08-25 15:40:26","点赞减去点踩数量":1,"点赞量":1,"点踩量":0,"内容":"上的是老师和王攀老师一起开的文献综述与科技写作。老师人很好，上课很细致，遇到困难可以大胆找老师，金老师很有耐心，会亲自帮忙debug，手把手教会你怎么搞。但对待作业，老师十分严谨，要求较高，可以感受到十分严谨的作风，这也可以算是一种独特的光电入门方式吧。老师们对最后大作业的答辩要求很高，我认为很多原理或许并不是大一学生能掌握的。给分较为求是，但也非常透明，会公示每一次作业得分以及扣分原因和修改建议。\\n\\n打9分。"},{"发表时间":"2023-10-19 11:43:24","点赞减去点踩数量":8,"点赞量":8,"点踩量":0,"内容":"如果金老师都不算好老师的话，我不知道浙大什么样的老师称之为好。\\n\\n离散数学，老师总是用最细致的讲法跟大家讲解，虽然可能有一点口音，但是明眼人都能看出来老师的用心和努力，每次作业都是自己一道题一道题批改的，有一点小的错误都会回复批注，会自己每周总结课程的重难点，提醒同学们及时交作业，要复习，最后考试也都是很基础的题目，难的题目几乎没有；\\n\\n同时作为一个外专业的学生，我冒昧地向老师提出了写推荐信的请求，老师甚至都不知道我长啥样，就答应了给我帮忙，我自己的班主任拿着我拟好的推荐信给我直接签了字，金老师认真给我修改，我不知道10分的老师是什么样的，但是我觉得像这样的老师，这样对待学生的态度在我这里永远满分"},{"发表时间":"2024-06-21 10:48:35","点赞减去点踩数量":0,"点赞量":0,"点踩量":0,"内容":"前面的骗人，我学了好几天才3.9"},{"发表时间":"2024-06-22 12:11:46","点赞减去点踩数量":0,"点赞量":1,"点踩量":1,"内容":"不多说，能选bj就选bj老师"},{"发表时间":"2024-07-07 01:54:08","点赞减去点踩数量":0,"点赞量":0,"点踩量":0,"内容":"当跨专业刷分的，学习内容比较基础，考的也简单，就是背的东西太多了感觉和马原差不多。老师也挺认真负责的，总评作业30，考试70，作业抄下答案期末好好考就好了。最后看成绩也差不多一半的人上90了，说明考的还是简单的"}],"gpa_info":[["文献综述与科技写作","4.17","114","0.53"],["离散数学","3.97","164","0.95"]]},{"id":4255,"姓名":"李攀","学院":"生命科学学院","热度":5233,"评分人数":37,"评分":9.6398,"拼音":"lipan","拼音缩写":"lp","comments":[{"发表时间":"2018-05-24 02:00:05","点赞减去点踩数量":0,"点赞量":0,"点踩量":0,"内容":"老师很博学啊"},{"发表时间":"2018-06-13 12:19:07","点赞减去点踩数量":7,"点赞量":7,"点踩量":0,"内容":"老师超可爱\\(//∇//)\\而且很负责\\(//∇//)\\表白老师\\(//∇//)\\"},{"发表时间":"2018-07-09 10:29:51","点赞减去点踩数量":0,"点赞量":0,"点踩量":0,"内容":"老师讲的很好！\\n\\n"},{"发表时间":"2018-07-10 02:19:23","点赞减去点踩数量":0,"点赞量":0,"点踩量":0,"内容":"上课很有趣，任务有点多但是很有收获！"},{"发表时间":"2018-12-09 10:26:05","点赞减去点踩数量":-4,"点赞量":2,"点踩量":6,"内容":"生物地理学自主学习可太秀了，任务和资料都没交代清楚"},{"发表时间":"2018-12-09 15:21:01","点赞减去点踩数量":1,"点赞量":2,"点踩量":1,"内容":"老师和助教人都很好，上课很有趣。但强烈建议老师不要布置软件学习的任务，或者多教一点相关的知识，搞Genious完全不知道自己在做什么，还花了大量时间(一整个周末都在琢磨这个东西)"},{"发表时间":"2018-12-25 06:46:32","点赞减去点踩数量":0,"点赞量":1,"点踩量":1,"内容":"李老师超可爱～"},{"发表时间":"2018-12-28 04:11:15","点赞减去点踩数量":0,"点赞量":1,"点踩量":1,"内容":"生物地理干货很多，课很生动，学到了很多！"},{"发表时间":"2019-01-03 03:20:27","点赞减去点踩数量":0,"点赞量":1,"点踩量":1,"内容":"这老师太可爱了wwwww给分也超好的！【虽然我分不高嘤嘤嘤"},{"发表时间":"2019-01-05 14:48:17","点赞减去点踩数量":2,"点赞量":2,"点踩量":0,"内容":"生物地理学的软件学习让我的电脑崩了....\\n\\n任务比较重，但收获很多～老师很负责，会在群里解答问题，助教每周也会答疑.."},{"发表时间":"2019-01-26 11:13:57","点赞减去点踩数量":1,"点赞量":2,"点踩量":1,"内容":"很精彩的课呢，除了上课内容比较好玩，还有植物园和课后自主课题，作业都是没有明确要求的，你想做到什么程度决定了你花多少精力，学了什么。"},{"发表时间":"2019-01-29 12:21:47","点赞减去点踩数量":21,"点赞量":22,"点踩量":1,"内容":"老师很可爱，超级热爱植物，平时会组织校园植物认知和植物园参观，问问题都热心解答，让我一个对植物没啥兴趣的人都感受到其魅力了，虽然我每次上课都听睡着。给分也很好，虽然我比较低"},{"发表时间":"2019-07-06 07:36:49","点赞减去点踩数量":1,"点赞量":2,"点踩量":1,"内容":"老师超级可爱！！！非常敬业！讲课很认真！还会带我们出去认识校园内的植物～"},{"发表时间":"2020-01-23 05:09:46","点赞减去点踩数量":7,"点赞量":8,"点踩量":1,"内容":"真正热爱植物的学者。"},{"发表时间":"2021-01-15 07:54:40","点赞减去点踩数量":2,"点赞量":2,"点踩量":0,"内容":"是老师的魅力让我感受到了植物学的魅力"},{"发表时间":"2021-07-17 06:16:54","点赞减去点踩数量":3,"点赞量":3,"点踩量":0,"内容":"我男神"},{"发表时间":"2021-07-19 16:10:33","点赞减去点踩数量":3,"点赞量":3,"点踩量":0,"内容":"上课很认真很细致的老师"},{"发表时间":"2021-07-22 01:11:26","点赞减去点踩数量":1,"点赞量":1,"点踩量":0,"内容":"相当nice"},{"发表时间":"2021-11-12 08:15:05","点赞减去点踩数量":3,"点赞量":3,"点踩量":0,"内容":"攀攀我爱你"},{"发表时间":"2021-11-27 07:03:34","点赞减去点踩数量":12,"点赞量":12,"点踩量":0,"内容":"李老师可能是我大学以来碰到的最好的老师了，老师很年轻，一点没有架子(甚至有点小玻璃心，但是真的是为同学着想的)。上课也有很多干货，不是水课。虽然生物地理学这门课任务比较重，但是老师给分非常仁慈，为了能给同学找平时分，最后录成绩拖了很久让每个同学都交作业，不要不合格。另外，在野外实习的时候也能感受到老师对植物的热爱，常常背着个相机各种拍，也会给同学讲解各种各样的植物。但是明年开始他可能不会教生物地理学了。。。反正遇到有他的课就尽管选，不会失望的。"},{"发表时间":"2022-01-17 04:27:27","点赞减去点踩数量":5,"点赞量":5,"点踩量":0,"内容":"李攀老师超级好，可以看出老师真的热爱植物学。"},{"发表时间":"2022-03-15 03:10:15","点赞减去点踩数量":2,"点赞量":2,"点踩量":0,"内容":"男神我滴攀！"},{"发表时间":"2022-06-20 09:40:41","点赞减去点踩数量":3,"点赞量":3,"点踩量":0,"内容":"李攀老师我永远的男神！！！真的很可爱很有趣讲课也讲得好，希望以后能够进李老师的实验室做研究呜呜呜"},{"发表时间":"2022-07-11 11:08:42","点赞减去点踩数量":1,"点赞量":1,"点踩量":0,"内容":"攀攀！我滴男神！"},{"发表时间":"2023-06-08 10:02:22","点赞减去点踩数量":0,"点赞量":0,"点踩量":0,"内容":"李攀攀 我男神"},{"发表时间":"2023-07-01 01:24:23","点赞减去点踩数量":1,"点赞量":1,"点踩量":0,"内容":"神中神"},{"发表时间":"2023-07-07 08:08:13","点赞减去点踩数量":1,"点赞量":1,"点踩量":0,"内容":"攀攀老师，您是神"},{"发表时间":"2023-11-28 08:30:30","点赞减去点踩数量":0,"点赞量":0,"点踩量":0,"内容":"卡密撒嘛"},{"发表时间":"2024-01-13 15:01:32","点赞减去点踩数量":1,"点赞量":1,"点踩量":0,"内容":"很和蔼 很亲切 也很乐于解答植物学上的问题"},{"发表时间":"2024-01-18 17:37:38","点赞减去点踩数量":0,"点赞量":0,"点踩量":0,"内容":"老师最后给分还行，为学生着想"},{"发表时间":"2024-05-31 15:29:44","点赞减去点踩数量":2,"点赞量":2,"点踩量":0,"内容":"我老公"},{"发表时间":"2024-06-27 00:28:47","点赞减去点踩数量":-2,"点赞量":0,"点踩量":2,"内容":"吓鼠惹，楼上有女支女"},{"发表时间":"2024-11-11 10:36:58","点赞减去点踩数量":0,"点赞量":0,"点踩量":0,"内容":"超可爱的老师，慢慢开始对植物学有了兴趣"}],"gpa_info":[["植物学及实验（乙）","3.65","180","0.85"],["植物学及实验（甲）","3.90","500+","0.73"],["生物地理学","4.00","39","0.95"],["生物学综合野外实习","4.34","260","0.41"],["药用植物野外实习","4.40","168","0.60"],["进化生物学","3.96","302","0.61"]]},{"id":4260,"姓名":"吴卫华","学院":"光华法学院","热度":161,"评分人数":0,"评分":0.0,"拼音":"wuweihua","拼音缩写":"wwh","comments":[],"gpa_info":[["形势与政策Ⅰ","3.81","410","0.66"]]}]